Workbook

Sheet Orientações
A1: PLANILHA DE PONTUAÇÃO E PRONTIDÃO — APCN 2026
A2: Mestrado | Área 49 — Ciências Ambientais
A4: MODALIDADE | B4: Profissional | C4: Altere apenas este seletor se a proposta for acadêmica; o resumo ajusta automaticamente a exigência dos PTTs adicionais.
A6: FINALIDADE | B6: Organizar o corpo docente, classificar os artigos segundo a Área 49 e verificar a completude das produções de destaque e dos PTTs.
A7: JANELA TEMPORAL | B7: Para o Edital CAPES nº 20/2026, considerar 2021–2026: os cinco anos anteriores acrescidos do ano de submissão.
A8: ARTIGOS | B8: Registrar os artigos dos docentes permanentes com DOI. Periódicos estrangeiros: WoS e, complementarmente, Scopus. Periódicos brasileiros abaixo do percentil 50 ou não consolidados: usar as duas condições da Dimensions.
A9: REFERÊNCIA DO MESTRADO | B9: A média das produções em artigos deve alcançar índice mínimo esperado de 0,50. O resultado individual é diagnóstico; o requisito textual refere-se à média das produções do grupo.
A10: DESTAQUES | B10: Indicar duas produções de destaque por docente permanente, acompanhadas da Ficha de Impacto Real e de evidências.
A11: MESTRADO PROFISSIONAL | B11: Além dos indicadores gerais, indicar três PTTs adicionais por docente permanente, com Ficha de Impacto Real, link/anexo e justificativa de aderência.
A12: PTTs | B12: A APCN de Ciências Ambientais não fixa pontuação numérica prévia para cada tipologia. Os PTTs são avaliados por aderência, impacto, aplicabilidade, inovação e complexidade.
A13: MATERNIDADE | B13: Docentes que foram mães nos 24 meses anteriores à submissão são excluídas do cálculo geral de produção; a condição deve ser indicada claramente na proposta.
A14: CORPO DOCENTE | B14: Mínimo de 12 docentes permanentes; colaboradores até 30% do corpo docente total; externos no quadro permanente até 30%, com carta de cessão.
A15: DEDICAÇÃO | B15: Ao menos 50% dos docentes permanentes com contrato de 40h; todos com no mínimo 14h semanais no curso; média desejável de 15h.
A16: VÍNCULOS | B16: A Área 49 admite atuação como permanente em até dois PPGs, incluindo propostas novas. O Edital também impede cadastrar quem já atua em três programas/propostas.
A17: USO | B17: 1) Preencha “Lançamentos - Artigos”. 2) Preencha “Destaques e PTTs”. 3) Acompanhe as pendências no resumo e no checklist.
A18: LIMITAÇÃO | B18: Planilha de apoio baseada nos documentos oficiais vigentes em setembro de 2026.
A20: FONTES OFICIAIS ORGANIZADAS NA PASTA
A21: Documento orientador APCN — Ciências Ambientais 2026 | E21: =HYPERLINK("https://drive.google.com/file/d/1sPPe5quxj4cmBdZ1kJ_cUaX2jb0-3fwV/view?usp=drivesdk","Abrir arquivo na pasta") -> Abrir arquivo na pasta
A22: Ficha de avaliação — Ciências Ambientais 2025–2028 | E22: =HYPERLINK("https://drive.google.com/file/d/1nZ2Wg1-k6_pl-n21MEjwS4dYw9e7-AEU/view?usp=drivesdk","Abrir arquivo na pasta") -> Abrir arquivo na pasta
A23: Documento de Área — Ciências Ambientais 2025–2028 | E23: =HYPERLINK("https://drive.google.com/file/d/1v6Bm0-3GNPp-Qrp6tzjtcfZlH0ItC5hq/view?usp=drivesdk","Abrir arquivo na pasta") -> Abrir arquivo na pasta
A24: Anexo — Ficha de Impacto Real | E24: =HYPERLINK("https://drive.google.com/file/d/1yHDw_hEfQZtOsEV3U-ewKTrH9DGMT8Bh/view?usp=drivesdk","Abrir arquivo na pasta") -> Abrir arquivo na pasta
A25: Edital CAPES nº 20/2026 — APCN | E25: =HYPERLINK("https://drive.google.com/file/d/1Bzs3znyv-K_yff20DxvfyTZQe-Zg3qBK/view?usp=drivesdk","Abrir arquivo na pasta") -> Abrir arquivo na pasta
A26: Portaria CAPES nº 246/2026 — APCN | E26: =HYPERLINK("https://drive.google.com/file/d/1z_WwJI1RBFcgcNhSAU5JHqbzwa8aQbu_/view?usp=drivesdk","Abrir arquivo na pasta") -> Abrir arquivo na pasta
A27: Guia de submissão APCN 2026 | E27: =HYPERLINK("https://drive.google.com/file/d/1t-dJ_SNpGh7GKI96Z43gB6ZZ2AIc-UlC/view?usp=drivesdk","Abrir arquivo na pasta") -> Abrir arquivo na pasta
A28: Ofício nº 30/2026 — produções, Lattes e OpenAlex | E28: =HYPERLINK("https://drive.google.com/file/d/1Y4Y2L-Jl2SQZbTJorXAru3hC5GdFrGPE/view?usp=drivesdk","Abrir arquivo na pasta") -> Abrir arquivo na pasta

Sheet Estratos e PTTs
A1: CRITÉRIOS DE REFERÊNCIA — ÁREA 49
A2: Estrato | B2: WoS/Scopus: percentil | C2: Dimensions: maior % de artigos citados | D2: Dimensions: média de citações | E2: Índice por artigo
A3: E1 | B3: ≥ 87,5 | C3: ≥ 87,5 | D3: ≥ 2,00 | E3: 1
A4: E2 | B4: ≥ 75,0 | C4: ≥ 75,0 | D4: ≥ 1,50 | E4: 0.875
A5: E3 | B5: ≥ 62,5 | C5: ≥ 62,5 | D5: ≥ 1,00 | E5: 0.75
A6: E4 | B6: ≥ 50,0 | C6: ≥ 50,0 | D6: ≥ 0,75 | E6: 0.625
A7: E5 | B7: ≥ 37,5 | C7: ≥ 37,5 | D7: ≥ 0,50 | E7: 0.5
A8: E6 | B8: ≥ 25,0 | C8: ≥ 25,0 | D8: ≥ 0,25 | E8: 0.375
A9: E7 | B9: ≥ 12,5 | C9: ≥ 12,5 | D9: ≥ 0,125 | E9: 0.25
A10: E8 | B10: ≥ 0,01 | C10: ≥ 0,01 | D10: ≥ 0,01 | E10: 0.125
A11: Dimensions: aplicar simultaneamente as duas condições e usar o resultado de menor desempenho. Quando o periódico estiver em WoS e Scopus, utilizar o percentil mais favorável.
A13: 16 TIPOLOGIAS DE PRODUTOS TÉCNICOS E TECNOLÓGICOS (PTTs)
A14: Código | B14: Tipologia oficial | C14: Exemplos / escopo | D14: Dimensões avaliadas | E14: Tratamento na APCN
A15: PTT01 | B15: Produto bibliográfico | C15: Artigo em revista técnica ou de divulgação científica; livro ou série técnica | D15: Aderência, impacto, aplicabilidade, inovação e complexidade | E15: Sem pontos APCN pré-fixados; avaliação qualitativa
A16: PTT02 | B16: Ativos de Propriedade Intelectual | C16: Patente; desenho industrial; indicação geográfica; marca; topografia de circuito | D16: Aderência, impacto, aplicabilidade, inovação e complexidade | E16: Sem pontos APCN pré-fixados; avaliação qualitativa
A17: PTT03 | B17: Tecnologia Social | C17: Técnicas ou metodologias transformadoras desenvolvidas/aplicadas com a população | D17: Aderência, impacto, aplicabilidade, inovação e complexidade | E17: Sem pontos APCN pré-fixados; avaliação qualitativa
A18: PTT04 | B18: Produto de editoração | C18: Catálogo, coletânea, enciclopédia, revista, anais ou catálogo artístico organizado | D18: Aderência, impacto, aplicabilidade, inovação e complexidade | E18: Sem pontos APCN pré-fixados; avaliação qualitativa
A19: PTT05 | B19: Material didático ou educacional | C19: Material finalizado para processos de ensino, formação ou educação | D19: Aderência, impacto, aplicabilidade, inovação e complexidade | E19: Sem pontos APCN pré-fixados; avaliação qualitativa
A20: PTT06 | B20: Software/Aplicativo | C20: Programa de computador ou aplicativo | D20: Aderência, impacto, aplicabilidade, inovação e complexidade | E20: Sem pontos APCN pré-fixados; avaliação qualitativa
A21: PTT07 | B21: Norma ou Marco regulatório | C21: Norma, anteprojeto, estudo de regulamentação, audiência pública, peça técnica | D21: Aderência, impacto, aplicabilidade, inovação e complexidade | E21: Sem pontos APCN pré-fixados; avaliação qualitativa
A22: PTT08 | B22: Relatório técnico conclusivo | C22: Relatório, processo de gestão, pesquisa de mercado, simulação, modelo ou parecer técnico | D22: Aderência, impacto, aplicabilidade, inovação e complexidade | E22: Sem pontos APCN pré-fixados; avaliação qualitativa
A23: PTT09 | B23: Manual/Protocolo | C23: Protocolo tecnológico, POP ou manual de operação técnica | D23: Aderência, impacto, aplicabilidade, inovação e complexidade | E23: Sem pontos APCN pré-fixados; avaliação qualitativa
A24: PTT10 | B24: Acervo | C24: Curadoria de mostras, exposições, coleções biológicas ou acervos produzidos | D24: Aderência, impacto, aplicabilidade, inovação e complexidade | E24: Sem pontos APCN pré-fixados; avaliação qualitativa
A25: PTT11 | B25: Cultivar | C25: Cultivar desenvolvida ou registrada | D25: Aderência, impacto, aplicabilidade, inovação e complexidade | E25: Sem pontos APCN pré-fixados; avaliação qualitativa
... A30: PTT16 | B30: Processo/Tecnologia e Produto/Material não patenteável | C30: Processo, tecnologia, produto ou material sem proteção patentária | D30: Aderência, impacto, aplicabilidade, inovação e complexidade | E30: Sem pontos APCN pré-fixados; avaliação qualitativa

Sheet Resumo por docente
A1: RESUMO E CADASTRO DO CORPO DOCENTE — MESTRADO
A2: Modalidade | B2: ='Orientações'!B4 -> Profissional | D2: DP cadastrados | E2: =COUNTA($A$8:$A$57) -> 17 | G2: Mínimo exigido | H2: 12 | J2: Situação do quantitativo | K2: =IF(E2>=H2,"ATENDE","FALTAM "&(H2-E2)) -> ATENDE
A3: Média dos artigos do grupo | B3: =IFERROR(SUMIFS($H$8:$H$57,$A$8:$A$57,"<>",$C$8:$C$57,"<>sim")/SUMIFS($G$8:$G$57,$A$8:$A$57,"<>",$C$8:$C$57,"<>sim"),0) -> 0.71428571 | D3: Referência do mestrado | E3: 0.5 | G3: Situação da média | H3: =IF(B3>=E3,"ATENDE","ABAIXO DE 0,50") -> ATENDE | J3: DP 40h | K3: =IFERROR(COUNTIFS($A$8:$A$57,"<>",$D$8:$D$57,"sim")/COUNTA($A$8:$A$57),0) -> 1
A4: Carga mínima de 14h | B4: =IF(COUNTA($A$8:$A$57)=0,"AGUARDANDO",IF(COUNTIFS($A$8:$A$57,"<>",$E$8:$E$57,">=14")=COUNTA($A$8:$A$57),"ATENDE","REVISAR")) -> REVISAR | D4: Média de horas | E4: =IFERROR(AVERAGEIF($A$8:$A$57,"<>",$E$8:$E$57),0) -> 14 | G4: Maior nº de vínculos DP | H4: =IFERROR(MAX($F$8:$F$57),0) -> 1 | J4: Situação dedicação | K4: =IF(COUNTA($A$8:$A$57)=0,"AGUARDANDO",IF(AND(B4="ATENDE",E4>=15,H4<=2,K3>=50%),"ATENDE","REVISAR")) -> REVISAR
A5: DP com indicações completas | B5: =COUNTIF($M$8:$M$57,"OK") -> 1 | D5: Total de DP | E5: =COUNTA($A$8:$A$57) -> 17 | G5: Situação das indicações | H5: =IF(E5=0,"AGUARDANDO",IF(B5=E5,"ATENDE","PENDENTE")) -> PENDENTE | J5: Regra | K5: =IF('Orientações'!B4="Profissional","2 destaques + 3 PTTs/DP","2 destaques/DP") -> 2 destaques + 3 PTTs/DP
A6: Preencha as colunas amarelas. As demais são calculadas automaticamente.
A7: Docente permanente | B7: Linha de pesquisa/atuação | C7: Maternidade nos 24 meses? | D7: Vinculo 40h | E7: Horas semanais no curso | F7: Nº de vínculos como DP (inclui proposta) | G7: Artigos válidos | H7: Soma dos índices | I7: Média dos artigos | J7: Diagnóstico da produção | K7: Destaques completos | L7: PTTs adicionais completos | M7: Indicações exigidas | N7: Situação geral | O7: Observações
A8: ANDERSON SALDANHA BUENO | B8: Biodiversidade, Saúde Ambiental e Conservação | C8: não | D8: sim | G8: =IF($A8="","",COUNTIFS('Lançamentos - Artigos'!$A$2:$A$506,$A8,'Lançamentos - Artigos'!$L$2:$L$506,">0")) -> 0 | H8: =IF($A8="","",SUMIFS('Lançamentos - Artigos'!$L$2:$L$506,'Lançamentos - Artigos'!$A$2:$A$506,$A8)) -> 0 | I8: =IF(OR($A8="",G8=0),"",H8/G8) | J8: =IF($A8="","",IF(LOWER($C8)="sim","EXCLUÍDA DO CÁLCULO GERAL",IF(G8=0,"SEM ARTIGO VÁLIDO",IF(I8>=0.5,"REFERÊNCIA ATENDIDA","ABAIXO DE 0,50")))) -> SEM ARTIGO VÁLIDO | K8: =IF($A8="","",COUNTIFS('Destaques e PTTs'!$A$2:$A$501,$A8,'Destaques e PTTs'!$C$2:$C$501,"Destaque*",'Destaques e PTTs'!$W$2:$W$501,"OK")) -> 0 | L8: =IF($A8="","",COUNTIFS('Destaques e PTTs'!$A$2:$A$501,$A8,'Destaques e PTTs'!$C$2:$C$501,"PTT adicional*",'Destaques e PTTs'!$W$2:$W$501,"OK")) -> 0 | M8: =IF($A8="","",IF('Orientações'!$B$4="Profissional",IF(AND(K8=2,L8=3),"OK",IF(OR(K8>2,L8>3),"EXCEDE","PENDENTE")),IF(K8=2,"OK",IF(K8>2,"EXCEDE","PENDENTE")))) -> PENDENTE | N8: =IF($A8="","",IF(OR(LOWER($D8)<>"sim",$E8<14,$F8>2,$M8<>"OK",AND(LOWER($C8)<>"sim",G8=0)),"REVISAR","OK")) -> REVISAR
A9: CARLOS RODRIGO LEHN | B9: Biodiversidade, Saúde Ambiental e Conservação | C9: não | D9: sim | G9: =IF($A9="","",COUNTIFS('Lançamentos - Artigos'!$A$2:$A$506,$A9,'Lançamentos - Artigos'!$L$2:$L$506,">0")) -> 0 | H9: =IF($A9="","",SUMIFS('Lançamentos - Artigos'!$L$2:$L$506,'Lançamentos - Artigos'!$A$2:$A$506,$A9)) -> 0 | I9: =IF(OR($A9="",G9=0),"",H9/G9) | J9: =IF($A9="","",IF(LOWER($C9)="sim","EXCLUÍDA DO CÁLCULO GERAL",IF(G9=0,"SEM ARTIGO VÁLIDO",IF(I9>=0.5,"REFERÊNCIA ATENDIDA","ABAIXO DE 0,50")))) -> SEM ARTIGO VÁLIDO | K9: =IF($A9="","",COUNTIFS('Destaques e PTTs'!$A$2:$A$501,$A9,'Destaques e PTTs'!$C$2:$C$501,"Destaque*",'Destaques e PTTs'!$W$2:$W$501,"OK")) -> 0 | L9: =IF($A9="","",COUNTIFS('Destaques e PTTs'!$A$2:$A$501,$A9,'Destaques e PTTs'!$C$2:$C$501,"PTT adicional*",'Destaques e PTTs'!$W$2:$W$501,"OK")) -> 0 | M9: =IF($A9="","",IF('Orientações'!$B$4="Profissional",IF(AND(K9=2,L9=3),"OK",IF(OR(K9>2,L9>3),"EXCEDE","PENDENTE")),IF(K9=2,"OK",IF(K9>2,"EXCEDE","PENDENTE")))) -> PENDENTE | N9: =IF($A9="","",IF(OR(LOWER($D9)<>"sim",$E9<14,$F9>2,$M9<>"OK",AND(LOWER($C9)<>"sim",G9=0)),"REVISAR","OK")) -> REVISAR
A10: CAROLINE LEUCHTENBERGER | B10: Biodiversidade, Saúde Ambiental e Conservação | C10: não | D10: sim | G10: =IF($A10="","",COUNTIFS('Lançamentos - Artigos'!$A$2:$A$506,$A10,'Lançamentos - Artigos'!$L$2:$L$506,">0")) -> 0 | H10: =IF($A10="","",SUMIFS('Lançamentos - Artigos'!$L$2:$L$506,'Lançamentos - Artigos'!$A$2:$A$506,$A10)) -> 0 | I10: =IF(OR($A10="",G10=0),"",H10/G10) | J10: =IF($A10="","",IF(LOWER($C10)="sim","EXCLUÍDA DO CÁLCULO GERAL",IF(G10=0,"SEM ARTIGO VÁLIDO",IF(I10>=0.5,"REFERÊNCIA ATENDIDA","ABAIXO DE 0,50")))) -> SEM ARTIGO VÁLIDO | K10: =IF($A10="","",COUNTIFS('Destaques e PTTs'!$A$2:$A$501,$A10,'Destaques e PTTs'!$C$2:$C$501,"Destaque*",'Destaques e PTTs'!$W$2:$W$501,"OK")) -> 0 | L10: =IF($A10="","",COUNTIFS('Destaques e PTTs'!$A$2:$A$501,$A10,'Destaques e PTTs'!$C$2:$C$501,"PTT adicional*",'Destaques e PTTs'!$W$2:$W$501,"OK")) -> 0 | M10: =IF($A10="","",IF('Orientações'!$B$4="Profissional",IF(AND(K10=2,L10=3),"OK",IF(OR(K10>2,L10>3),"EXCEDE","PENDENTE")),IF(K10=2,"OK",IF(K10>2,"EXCEDE","PENDENTE")))) -> PENDENTE | N10: =IF($A10="","",IF(OR(LOWER($D10)<>"sim",$E10<14,$F10>2,$M10<>"OK",AND(LOWER($C10)<>"sim",G10=0)),"REVISAR","OK")) -> REVISAR
A11: EMANUELE JUNGES | B11: Inovação, Biotecnologia e Sustentabilidade Produtiva | C11: não | D11: sim | E11: 14 | F11: 0 | G11: =IF($A11="","",COUNTIFS('Lançamentos - Artigos'!$A$2:$A$506,$A11,'Lançamentos - Artigos'!$L$2:$L$506,">0")) -> 0 | H11: =IF($A11="","",SUMIFS('Lançamentos - Artigos'!$L$2:$L$506,'Lançamentos - Artigos'!$A$2:$A$506,$A11)) -> 0 | I11: =IF(OR($A11="",G11=0),"",H11/G11) | J11: =IF($A11="","",IF(LOWER($C11)="sim","EXCLUÍDA DO CÁLCULO GERAL",IF(G11=0,"SEM ARTIGO VÁLIDO",IF(I11>=0.5,"REFERÊNCIA ATENDIDA","ABAIXO DE 0,50")))) -> SEM ARTIGO VÁLIDO | K11: =IF($A11="","",COUNTIFS('Destaques e PTTs'!$A$2:$A$501,$A11,'Destaques e PTTs'!$C$2:$C$501,"Destaque*",'Destaques e PTTs'!$W$2:$W$501,"OK")) -> 0 | L11: =IF($A11="","",COUNTIFS('Destaques e PTTs'!$A$2:$A$501,$A11,'Destaques e PTTs'!$C$2:$C$501,"PTT adicional*",'Destaques e PTTs'!$W$2:$W$501,"OK")) -> 0 | M11: =IF($A11="","",IF('Orientações'!$B$4="Profissional",IF(AND(K11=2,L11=3),"OK",IF(OR(K11>2,L11>3),"EXCEDE","PENDENTE")),IF(K11=2,"OK",IF(K11>2,"EXCEDE","PENDENTE")))) -> PENDENTE | N11: =IF($A11="","",IF(OR(LOWER($D11)<>"sim",$E11<14,$F11>2,$M11<>"OK",AND(LOWER($C11)<>"sim",G11=0)),"REVISAR","OK")) -> REVISAR
A12: EVERTON LUTZ | D12: sim | G12: =IF($A12="","",COUNTIFS('Lançamentos - Artigos'!$A$2:$A$506,$A12,'Lançamentos - Artigos'!$L$2:$L$506,">0")) -> 0 | H12: =IF($A12="","",SUMIFS('Lançamentos - Artigos'!$L$2:$L$506,'Lançamentos - Artigos'!$A$2:$A$506,$A12)) -> 0 | I12: =IF(OR($A12="",G12=0),"",H12/G12) | J12: =IF($A12="","",IF(LOWER($C12)="sim","EXCLUÍDA DO CÁLCULO GERAL",IF(G12=0,"SEM ARTIGO VÁLIDO",IF(I12>=0.5,"REFERÊNCIA ATENDIDA","ABAIXO DE 0,50")))) -> SEM ARTIGO VÁLIDO | K12: =IF($A12="","",COUNTIFS('Destaques e PTTs'!$A$2:$A$501,$A12,'Destaques e PTTs'!$C$2:$C$501,"Destaque*",'Destaques e PTTs'!$W$2:$W$501,"OK")) -> 0 | L12: =IF($A12="","",COUNTIFS('Destaques e PTTs'!$A$2:$A$501,$A12,'Destaques e PTTs'!$C$2:$C$501,"PTT adicional*",'Destaques e PTTs'!$W$2:$W$501,"OK")) -> 0 | M12: =IF($A12="","",IF('Orientações'!$B$4="Profissional",IF(AND(K12=2,L12=3),"OK",IF(OR(K12>2,L12>3),"EXCEDE","PENDENTE")),IF(K12=2,"OK",IF(K12>2,"EXCEDE","PENDENTE")))) -> PENDENTE | N12: =IF($A12="","",IF(OR(LOWER($D12)<>"sim",$E12<14,$F12>2,$M12<>"OK",AND(LOWER($C12)<>"sim",G12=0)),"REVISAR","OK")) -> REVISAR
A13: FELIPE KETZER | B13: Inovação, Biotecnologia e Sustentabilidade Produtiva | C13: não | D13: sim | E13: 14 | F13: 1 | G13: =IF($A13="","",COUNTIFS('Lançamentos - Artigos'!$A$2:$A$506,$A13,'Lançamentos - Artigos'!$L$2:$L$506,">0")) -> 0 | H13: =IF($A13="","",SUMIFS('Lançamentos - Artigos'!$L$2:$L$506,'Lançamentos - Artigos'!$A$2:$A$506,$A13)) -> 0 | I13: =IF(OR($A13="",G13=0),"",H13/G13) | J13: =IF($A13="","",IF(LOWER($C13)="sim","EXCLUÍDA DO CÁLCULO GERAL",IF(G13=0,"SEM ARTIGO VÁLIDO",IF(I13>=0.5,"REFERÊNCIA ATENDIDA","ABAIXO DE 0,50")))) -> SEM ARTIGO VÁLIDO | K13: =IF($A13="","",COUNTIFS('Destaques e PTTs'!$A$2:$A$501,$A13,'Destaques e PTTs'!$C$2:$C$501,"Destaque*",'Destaques e PTTs'!$W$2:$W$501,"OK")) -> 0 | L13: =IF($A13="","",COUNTIFS('Destaques e PTTs'!$A$2:$A$501,$A13,'Destaques e PTTs'!$C$2:$C$501,"PTT adicional*",'Destaques e PTTs'!$W$2:$W$501,"OK")) -> 0 | M13: =IF($A13="","",IF('Orientações'!$B$4="Profissional",IF(AND(K13=2,L13=3),"OK",IF(OR(K13>2,L13>3),"EXCEDE","PENDENTE")),IF(K13=2,"OK",IF(K13>2,"EXCEDE","PENDENTE")))) -> PENDENTE | N13: =IF($A13="","",IF(OR(LOWER($D13)<>"sim",$E13<14,$F13>2,$M13<>"OK",AND(LOWER($C13)<>"sim",G13=0)),"REVISAR","OK")) -> REVISAR
A14: GERSON AZULIM MULLER | B14: Biodiversidade, Saúde Ambiental e Conservação | C14: não | D14: sim | E14: 14 | F14: 1 | G14: =IF($A14="","",COUNTIFS('Lançamentos - Artigos'!$A$2:$A$506,$A14,'Lançamentos - Artigos'!$L$2:$L$506,">0")) -> 0 | H14: =IF($A14="","",SUMIFS('Lançamentos - Artigos'!$L$2:$L$506,'Lançamentos - Artigos'!$A$2:$A$506,$A14)) -> 0 | I14: =IF(OR($A14="",G14=0),"",H14/G14) | J14: =IF($A14="","",IF(LOWER($C14)="sim","EXCLUÍDA DO CÁLCULO GERAL",IF(G14=0,"SEM ARTIGO VÁLIDO",IF(I14>=0.5,"REFERÊNCIA ATENDIDA","ABAIXO DE 0,50")))) -> SEM ARTIGO VÁLIDO | K14: =IF($A14="","",COUNTIFS('Destaques e PTTs'!$A$2:$A$501,$A14,'Destaques e PTTs'!$C$2:$C$501,"Destaque*",'Destaques e PTTs'!$W$2:$W$501,"OK")) -> 0 | L14: =IF($A14="","",COUNTIFS('Destaques e PTTs'!$A$2:$A$501,$A14,'Destaques e PTTs'!$C$2:$C$501,"PTT adicional*",'Destaques e PTTs'!$W$2:$W$501,"OK")) -> 0 | M14: =IF($A14="","",IF('Orientações'!$B$4="Profissional",IF(AND(K14=2,L14=3),"OK",IF(OR(K14>2,L14>3),"EXCEDE","PENDENTE")),IF(K14=2,"OK",IF(K14>2,"EXCEDE","PENDENTE")))) -> PENDENTE | N14: =IF($A14="","",IF(OR(LOWER($D14)<>"sim",$E14<14,$F14>2,$M14<>"OK",AND(LOWER($C14)<>"sim",G14=0)),"REVISAR","OK")) -> REVISAR
A15: GERUZA LEAL MELO | B15: Biodiversidade, Saúde Ambiental e Conservação | C15: não | D15: sim | E15: 14 | F15: 1 | G15: =IF($A15="","",COUNTIFS('Lançamentos - Artigos'!$A$2:$A$506,$A15,'Lançamentos - Artigos'!$L$2:$L$506,">0")) -> 0 | H15: =IF($A15="","",SUMIFS('Lançamentos - Artigos'!$L$2:$L$506,'Lançamentos - Artigos'!$A$2:$A$506,$A15)) -> 0 | I15: =IF(OR($A15="",G15=0),"",H15/G15) | J15: =IF($A15="","",IF(LOWER($C15)="sim","EXCLUÍDA DO CÁLCULO GERAL",IF(G15=0,"SEM ARTIGO VÁLIDO",IF(I15>=0.5,"REFERÊNCIA ATENDIDA","ABAIXO DE 0,50")))) -> SEM ARTIGO VÁLIDO | K15: =IF($A15="","",COUNTIFS('Destaques e PTTs'!$A$2:$A$501,$A15,'Destaques e PTTs'!$C$2:$C$501,"Destaque*",'Destaques e PTTs'!$W$2:$W$501,"OK")) -> 0 | L15: =IF($A15="","",COUNTIFS('Destaques e PTTs'!$A$2:$A$501,$A15,'Destaques e PTTs'!$C$2:$C$501,"PTT adicional*",'Destaques e PTTs'!$W$2:$W$501,"OK")) -> 0 | M15: =IF($A15="","",IF('Orientações'!$B$4="Profissional",IF(AND(K15=2,L15=3),"OK",IF(OR(K15>2,L15>3),"EXCEDE","PENDENTE")),IF(K15=2,"OK",IF(K15>2,"EXCEDE","PENDENTE")))) -> PENDENTE | N15: =IF($A15="","",IF(OR(LOWER($D15)<>"sim",$E15<14,$F15>2,$M15<>"OK",AND(LOWER($C15)<>"sim",G15=0)),"REVISAR","OK")) -> REVISAR
A16: JONAS SPONCHIADO | B16: Biodiversidade, Saúde Ambiental e Conservação | C16: não | D16: sim | E16: 14 | F16: 1 | G16: =IF($A16="","",COUNTIFS('Lançamentos - Artigos'!$A$2:$A$506,$A16,'Lançamentos - Artigos'!$L$2:$L$506,">0")) -> 0 | H16: =IF($A16="","",SUMIFS('Lançamentos - Artigos'!$L$2:$L$506,'Lançamentos - Artigos'!$A$2:$A$506,$A16)) -> 0 | I16: =IF(OR($A16="",G16=0),"",H16/G16) | J16: =IF($A16="","",IF(LOWER($C16)="sim","EXCLUÍDA DO CÁLCULO GERAL",IF(G16=0,"SEM ARTIGO VÁLIDO",IF(I16>=0.5,"REFERÊNCIA ATENDIDA","ABAIXO DE 0,50")))) -> SEM ARTIGO VÁLIDO | K16: =IF($A16="","",COUNTIFS('Destaques e PTTs'!$A$2:$A$501,$A16,'Destaques e PTTs'!$C$2:$C$501,"Destaque*",'Destaques e PTTs'!$W$2:$W$501,"OK")) -> 0 | L16: =IF($A16="","",COUNTIFS('Destaques e PTTs'!$A$2:$A$501,$A16,'Destaques e PTTs'!$C$2:$C$501,"PTT adicional*",'Destaques e PTTs'!$W$2:$W$501,"OK")) -> 0 | M16: =IF($A16="","",IF('Orientações'!$B$4="Profissional",IF(AND(K16=2,L16=3),"OK",IF(OR(K16>2,L16>3),"EXCEDE","PENDENTE")),IF(K16=2,"OK",IF(K16>2,"EXCEDE","PENDENTE")))) -> PENDENTE | N16: =IF($A16="","",IF(OR(LOWER($D16)<>"sim",$E16<14,$F16>2,$M16<>"OK",AND(LOWER($C16)<>"sim",G16=0)),"REVISAR","OK")) -> REVISAR
A17: LESSANDRO DE CONTI | D17: sim | G17: =IF($A17="","",COUNTIFS('Lançamentos - Artigos'!$A$2:$A$506,$A17,'Lançamentos - Artigos'!$L$2:$L$506,">0")) -> 0 | H17: =IF($A17="","",SUMIFS('Lançamentos - Artigos'!$L$2:$L$506,'Lançamentos - Artigos'!$A$2:$A$506,$A17)) -> 0 | I17: =IF(OR($A17="",G17=0),"",H17/G17) | J17: =IF($A17="","",IF(LOWER($C17)="sim","EXCLUÍDA DO CÁLCULO GERAL",IF(G17=0,"SEM ARTIGO VÁLIDO",IF(I17>=0.5,"REFERÊNCIA ATENDIDA","ABAIXO DE 0,50")))) -> SEM ARTIGO VÁLIDO | K17: =IF($A17="","",COUNTIFS('Destaques e PTTs'!$A$2:$A$501,$A17,'Destaques e PTTs'!$C$2:$C$501,"Destaque*",'Destaques e PTTs'!$W$2:$W$501,"OK")) -> 0 | L17: =IF($A17="","",COUNTIFS('Destaques e PTTs'!$A$2:$A$501,$A17,'Destaques e PTTs'!$C$2:$C$501,"PTT adicional*",'Destaques e PTTs'!$W$2:$W$501,"OK")) -> 0 | M17: =IF($A17="","",IF('Orientações'!$B$4="Profissional",IF(AND(K17=2,L17=3),"OK",IF(OR(K17>2,L17>3),"EXCEDE","PENDENTE")),IF(K17=2,"OK",IF(K17>2,"EXCEDE","PENDENTE")))) -> PENDENTE | N17: =IF($A17="","",IF(OR(LOWER($D17)<>"sim",$E17<14,$F17>2,$M17<>"OK",AND(LOWER($C17)<>"sim",G17=0)),"REVISAR","OK")) -> REVISAR
A18: LETICIA TREVISAN GRESSLER | D18: sim | G18: =IF($A18="","",COUNTIFS('Lançamentos - Artigos'!$A$2:$A$506,$A18,'Lançamentos - Artigos'!$L$2:$L$506,">0")) -> 0 | H18: =IF($A18="","",SUMIFS('Lançamentos - Artigos'!$L$2:$L$506,'Lançamentos - Artigos'!$A$2:$A$506,$A18)) -> 0 | I18: =IF(OR($A18="",G18=0),"",H18/G18) | J18: =IF($A18="","",IF(LOWER($C18)="sim","EXCLUÍDA DO CÁLCULO GERAL",IF(G18=0,"SEM ARTIGO VÁLIDO",IF(I18>=0.5,"REFERÊNCIA ATENDIDA","ABAIXO DE 0,50")))) -> SEM ARTIGO VÁLIDO | K18: =IF($A18="","",COUNTIFS('Destaques e PTTs'!$A$2:$A$501,$A18,'Destaques e PTTs'!$C$2:$C$501,"Destaque*",'Destaques e PTTs'!$W$2:$W$501,"OK")) -> 0 | L18: =IF($A18="","",COUNTIFS('Destaques e PTTs'!$A$2:$A$501,$A18,'Destaques e PTTs'!$C$2:$C$501,"PTT adicional*",'Destaques e PTTs'!$W$2:$W$501,"OK")) -> 0 | M18: =IF($A18="","",IF('Orientações'!$B$4="Profissional",IF(AND(K18=2,L18=3),"OK",IF(OR(K18>2,L18>3),"EXCEDE","PENDENTE")),IF(K18=2,"OK",IF(K18>2,"EXCEDE","PENDENTE")))) -> PENDENTE | N18: =IF($A18="","",IF(OR(LOWER($D18)<>"sim",$E18<14,$F18>2,$M18<>"OK",AND(LOWER($C18)<>"sim",G18=0)),"REVISAR","OK")) -> REVISAR
A19: MICAELA GUIDOTTI TAKEUCHI | B19: Inovação, Biotecnologia e Sustentabilidade Produtiva | C19: não | D19: sim | E19: 14 | F19: 1 | H19: =IF($A19="","",SUMIFS('Lançamentos - Artigos'!$L$2:$L$506,'Lançamentos - Artigos'!$A$2:$A$506,$A19)) -> 0 | I19: =IF(OR($A19="",G19=0),"",H19/G19) | J19: =IF($A19="","",IF(LOWER($C19)="sim","EXCLUÍDA DO CÁLCULO GERAL",IF(G19=0,"SEM ARTIGO VÁLIDO",IF(I19>=0.5,"REFERÊNCIA ATENDIDA","ABAIXO DE 0,50")))) -> SEM ARTIGO VÁLIDO | K19: =IF($A19="","",COUNTIFS('Destaques e PTTs'!$A$2:$A$501,$A19,'Destaques e PTTs'!$C$2:$C$501,"Destaque*",'Destaques e PTTs'!$W$2:$W$501,"OK")) -> 0 | L19: =IF($A19="","",COUNTIFS('Destaques e PTTs'!$A$2:$A$501,$A19,'Destaques e PTTs'!$C$2:$C$501,"PTT adicional*",'Destaques e PTTs'!$W$2:$W$501,"OK")) -> 0 | M19: =IF($A19="","",IF('Orientações'!$B$4="Profissional",IF(AND(K19=2,L19=3),"OK",IF(OR(K19>2,L19>3),"EXCEDE","PENDENTE")),IF(K19=2,"OK",IF(K19>2,"EXCEDE","PENDENTE")))) -> PENDENTE | N19: =IF($A19="","",IF(OR(LOWER($D19)<>"sim",$E19<14,$F19>2,$M19<>"OK",AND(LOWER($C19)<>"sim",G19=0)),"REVISAR","OK")) -> REVISAR
A20: RANGEL FERNANDES PACHECO | B20: Inovação, Biotecnologia e Sustentabilidade Produtiva | C20: não | D20: sim | E20: 14 | F20: 1 | G20: =IF($A20="","",COUNTIFS('Lançamentos - Artigos'!$A$2:$A$506,$A20,'Lançamentos - Artigos'!$L$2:$L$506,">0")) -> 7 | H20: =IF($A20="","",SUMIFS('Lançamentos - Artigos'!$L$2:$L$506,'Lançamentos - Artigos'!$A$2:$A$506,$A20)) -> 5 | I20: =IF(OR($A20="",G20=0),"",H20/G20) -> 0.71428571 | J20: =IF($A20="","",IF(LOWER($C20)="sim","EXCLUÍDA DO CÁLCULO GERAL",IF(G20=0,"SEM ARTIGO VÁLIDO",IF(I20>=0.5,"REFERÊNCIA ATENDIDA","ABAIXO DE 0,50")))) -> REFERÊNCIA ATENDIDA | K20: =IF($A20="","",COUNTIFS('Destaques e PTTs'!$A$2:$A$501,$A20,'Destaques e PTTs'!$C$2:$C$501,"Destaque*",'Destaques e PTTs'!$W$2:$W$501,"OK")) -> 2 | L20: =IF($A20="","",COUNTIFS('Destaques e PTTs'!$A$2:$A$501,$A20,'Destaques e PTTs'!$C$2:$C$501,"PTT adicional*",'Destaques e PTTs'!$W$2:$W$501,"OK")) -> 3 | M20: =IF($A20="","",IF('Orientações'!$B$4="Profissional",IF(AND(K20=2,L20=3),"OK",IF(OR(K20>2,L20>3),"EXCEDE","PENDENTE")),IF(K20=2,"OK",IF(K20>2,"EXCEDE","PENDENTE")))) -> OK | N20: =IF($A20="","",IF(OR(LOWER($D20)<>"sim",$E20<14,$F20>2,$M20<>"OK",AND(LOWER($C20)<>"sim",G20=0)),"REVISAR","OK")) -> OK
A21: TATIANA TOZZI MARTINS SOUZA RODRIGUES | D21: sim | G21: =IF($A21="","",COUNTIFS('Lançamentos - Artigos'!$A$2:$A$506,$A21,'Lançamentos - Artigos'!$L$2:$L$506,">0")) -> 0 | H21: =IF($A21="","",SUMIFS('Lançamentos - Artigos'!$L$2:$L$506,'Lançamentos - Artigos'!$A$2:$A$506,$A21)) -> 0 | I21: =IF(OR($A21="",G21=0),"",H21/G21) | J21: =IF($A21="","",IF(LOWER($C21)="sim","EXCLUÍDA DO CÁLCULO GERAL",IF(G21=0,"SEM ARTIGO VÁLIDO",IF(I21>=0.5,"REFERÊNCIA ATENDIDA","ABAIXO DE 0,50")))) -> SEM ARTIGO VÁLIDO | K21: =IF($A21="","",COUNTIFS('Destaques e PTTs'!$A$2:$A$501,$A21,'Destaques e PTTs'!$C$2:$C$501,"Destaque*",'Destaques e PTTs'!$W$2:$W$501,"OK")) -> 0 | L21: =IF($A21="","",COUNTIFS('Destaques e PTTs'!$A$2:$A$501,$A21,'Destaques e PTTs'!$C$2:$C$501,"PTT adicional*",'Destaques e PTTs'!$W$2:$W$501,"OK")) -> 0 | M21: =IF($A21="","",IF('Orientações'!$B$4="Profissional",IF(AND(K21=2,L21=3),"OK",IF(OR(K21>2,L21>3),"EXCEDE","PENDENTE")),IF(K21=2,"OK",IF(K21>2,"EXCEDE","PENDENTE")))) -> PENDENTE | N21: =IF($A21="","",IF(OR(LOWER($D21)<>"sim",$E21<14,$F21>2,$M21<>"OK",AND(LOWER($C21)<>"sim",G21=0)),"REVISAR","OK")) -> REVISAR
A22: Kátia Maria Cardinal | B22: Inovação, Biotecnologia e Sustentabilidade Produtiva | C22: não | D22: sim | E22: 14 | F22: 1 | G22: 0 | H22: =IF($A22="","",SUMIFS('Lançamentos - Artigos'!$L$2:$L$506,'Lançamentos - Artigos'!$A$2:$A$506,$A22)) -> 0 | I22: =IF(OR($A22="",G22=0),"",H22/G22) | J22: =IF($A22="","",IF(LOWER($C22)="sim","EXCLUÍDA DO CÁLCULO GERAL",IF(G22=0,"SEM ARTIGO VÁLIDO",IF(I22>=0.5,"REFERÊNCIA ATENDIDA","ABAIXO DE 0,50")))) -> SEM ARTIGO VÁLIDO | K22: =IF($A22="","",COUNTIFS('Destaques e PTTs'!$A$2:$A$501,$A22,'Destaques e PTTs'!$C$2:$C$501,"Destaque*",'Destaques e PTTs'!$W$2:$W$501,"OK")) -> 2 | L22: =IF($A22="","",COUNTIFS('Destaques e PTTs'!$A$2:$A$501,$A22,'Destaques e PTTs'!$C$2:$C$501,"PTT adicional*",'Destaques e PTTs'!$W$2:$W$501,"OK")) -> 0 | M22: =IF($A22="","",IF('Orientações'!$B$4="Profissional",IF(AND(K22=2,L22=3),"OK",IF(OR(K22>2,L22>3),"EXCEDE","PENDENTE")),IF(K22=2,"OK",IF(K22>2,"EXCEDE","PENDENTE")))) -> PENDENTE | N22: =IF($A22="","",IF(OR(LOWER($D22)<>"sim",$E22<14,$F22>2,$M22<>"OK",AND(LOWER($C22)<>"sim",G22=0)),"REVISAR","OK")) -> REVISAR
A23: Luana Mendes dos Santos | D23: sim | G23: =IF($A23="","",COUNTIFS('Lançamentos - Artigos'!$A$2:$A$506,$A23,'Lançamentos - Artigos'!$L$2:$L$506,">0")) -> 0 | H23: =IF($A23="","",SUMIFS('Lançamentos - Artigos'!$L$2:$L$506,'Lançamentos - Artigos'!$A$2:$A$506,$A23)) -> 0 | I23: =IF(OR($A23="",G23=0),"",H23/G23) | J23: =IF($A23="","",IF(LOWER($C23)="sim","EXCLUÍDA DO CÁLCULO GERAL",IF(G23=0,"SEM ARTIGO VÁLIDO",IF(I23>=0.5,"REFERÊNCIA ATENDIDA","ABAIXO DE 0,50")))) -> SEM ARTIGO VÁLIDO | K23: =IF($A23="","",COUNTIFS('Destaques e PTTs'!$A$2:$A$501,$A23,'Destaques e PTTs'!$C$2:$C$501,"Destaque*",'Destaques e PTTs'!$W$2:$W$501,"OK")) -> 0 | L23: =IF($A23="","",COUNTIFS('Destaques e PTTs'!$A$2:$A$501,$A23,'Destaques e PTTs'!$C$2:$C$501,"PTT adicional*",'Destaques e PTTs'!$W$2:$W$501,"OK")) -> 0 | M23: =IF($A23="","",IF('Orientações'!$B$4="Profissional",IF(AND(K23=2,L23=3),"OK",IF(OR(K23>2,L23>3),"EXCEDE","PENDENTE")),IF(K23=2,"OK",IF(K23>2,"EXCEDE","PENDENTE")))) -> PENDENTE | N23: =IF($A23="","",IF(OR(LOWER($D23)<>"sim",$E23<14,$F23>2,$M23<>"OK",AND(LOWER($C23)<>"sim",G23=0)),"REVISAR","OK")) -> REVISAR
A24: Volnei Luiz Meneghetti | B24: Inovação, Biotecnologia e Sustentabilidade Produtiva | C24: não | D24: sim | E24: 14 | F24: 1 | G24: =IF($A24="","",COUNTIFS('Lançamentos - Artigos'!$A$2:$A$506,$A24,'Lançamentos - Artigos'!$L$2:$L$506,">0")) -> 0 | H24: =IF($A24="","",SUMIFS('Lançamentos - Artigos'!$L$2:$L$506,'Lançamentos - Artigos'!$A$2:$A$506,$A24)) -> 0 | I24: =IF(OR($A24="",G24=0),"",H24/G24) | J24: =IF($A24="","",IF(LOWER($C24)="sim","EXCLUÍDA DO CÁLCULO GERAL",IF(G24=0,"SEM ARTIGO VÁLIDO",IF(I24>=0.5,"REFERÊNCIA ATENDIDA","ABAIXO DE 0,50")))) -> SEM ARTIGO VÁLIDO | K24: =IF($A24="","",COUNTIFS('Destaques e PTTs'!$A$2:$A$501,$A24,'Destaques e PTTs'!$C$2:$C$501,"Destaque*",'Destaques e PTTs'!$W$2:$W$501,"OK")) -> 1 | L24: =IF($A24="","",COUNTIFS('Destaques e PTTs'!$A$2:$A$501,$A24,'Destaques e PTTs'!$C$2:$C$501,"PTT adicional*",'Destaques e PTTs'!$W$2:$W$501,"OK")) -> 0 | M24: =IF($A24="","",IF('Orientações'!$B$4="Profissional",IF(AND(K24=2,L24=3),"OK",IF(OR(K24>2,L24>3),"EXCEDE","PENDENTE")),IF(K24=2,"OK",IF(K24>2,"EXCEDE","PENDENTE")))) -> PENDENTE | N24: =IF($A24="","",IF(OR(LOWER($D24)<>"sim",$E24<14,$F24>2,$M24<>"OK",AND(LOWER($C24)<>"sim",G24=0)),"REVISAR","OK")) -> REVISAR
D25: sim | G25: =IF($A25="","",COUNTIFS('Lançamentos - Artigos'!$A$2:$A$506,$A25,'Lançamentos - Artigos'!$L$2:$L$506,">0")) | H25: =IF($A25="","",SUMIFS('Lançamentos - Artigos'!$L$2:$L$506,'Lançamentos - Artigos'!$A$2:$A$506,$A25)) | I25: =IF(OR($A25="",G25=0),"",H25/G25) | J25: =IF($A25="","",IF(LOWER($C25)="sim","EXCLUÍDA DO CÁLCULO GERAL",IF(G25=0,"SEM ARTIGO VÁLIDO",IF(I25>=0.5,"REFERÊNCIA ATENDIDA","ABAIXO DE 0,50")))) | K25: =IF($A25="","",COUNTIFS('Destaques e PTTs'!$A$2:$A$501,$A25,'Destaques e PTTs'!$C$2:$C$501,"Destaque*",'Destaques e PTTs'!$W$2:$W$501,"OK")) | L25: =IF($A25="","",COUNTIFS('Destaques e PTTs'!$A$2:$A$501,$A25,'Destaques e PTTs'!$C$2:$C$501,"PTT adicional*",'Destaques e PTTs'!$W$2:$W$501,"OK")) | M25: =IF($A25="","",IF('Orientações'!$B$4="Profissional",IF(AND(K25=2,L25=3),"OK",IF(OR(K25>2,L25>3),"EXCEDE","PENDENTE")),IF(K25=2,"OK",IF(K25>2,"EXCEDE","PENDENTE")))) | N25: =IF($A25="","",IF(OR(LOWER($D25)<>"sim",$E25<14,$F25>2,$M25<>"OK",AND(LOWER($C25)<>"sim",G25=0)),"REVISAR","OK"))
D26: sim | G26: =IF($A26="","",COUNTIFS('Lançamentos - Artigos'!$A$2:$A$506,$A26,'Lançamentos - Artigos'!$L$2:$L$506,">0")) | H26: =IF($A26="","",SUMIFS('Lançamentos - Artigos'!$L$2:$L$506,'Lançamentos - Artigos'!$A$2:$A$506,$A26)) | I26: =IF(OR($A26="",G26=0),"",H26/G26) | J26: =IF($A26="","",IF(LOWER($C26)="sim","EXCLUÍDA DO CÁLCULO GERAL",IF(G26=0,"SEM ARTIGO VÁLIDO",IF(I26>=0.5,"REFERÊNCIA ATENDIDA","ABAIXO DE 0,50")))) | K26: =IF($A26="","",COUNTIFS('Destaques e PTTs'!$A$2:$A$501,$A26,'Destaques e PTTs'!$C$2:$C$501,"Destaque*",'Destaques e PTTs'!$W$2:$W$501,"OK")) | L26: =IF($A26="","",COUNTIFS('Destaques e PTTs'!$A$2:$A$501,$A26,'Destaques e PTTs'!$C$2:$C$501,"PTT adicional*",'Destaques e PTTs'!$W$2:$W$501,"OK")) | M26: =IF($A26="","",IF('Orientações'!$B$4="Profissional",IF(AND(K26=2,L26=3),"OK",IF(OR(K26>2,L26>3),"EXCEDE","PENDENTE")),IF(K26=2,"OK",IF(K26>2,"EXCEDE","PENDENTE")))) | N26: =IF($A26="","",IF(OR(LOWER($D26)<>"sim",$E26<14,$F26>2,$M26<>"OK",AND(LOWER($C26)<>"sim",G26=0)),"REVISAR","OK"))
D27: sim | G27: =IF($A27="","",COUNTIFS('Lançamentos - Artigos'!$A$2:$A$506,$A27,'Lançamentos - Artigos'!$L$2:$L$506,">0")) | H27: =IF($A27="","",SUMIFS('Lançamentos - Artigos'!$L$2:$L$506,'Lançamentos - Artigos'!$A$2:$A$506,$A27)) | I27: =IF(OR($A27="",G27=0),"",H27/G27) | J27: =IF($A27="","",IF(LOWER($C27)="sim","EXCLUÍDA DO CÁLCULO GERAL",IF(G27=0,"SEM ARTIGO VÁLIDO",IF(I27>=0.5,"REFERÊNCIA ATENDIDA","ABAIXO DE 0,50")))) | K27: =IF($A27="","",COUNTIFS('Destaques e PTTs'!$A$2:$A$501,$A27,'Destaques e PTTs'!$C$2:$C$501,"Destaque*",'Destaques e PTTs'!$W$2:$W$501,"OK")) | L27: =IF($A27="","",COUNTIFS('Destaques e PTTs'!$A$2:$A$501,$A27,'Destaques e PTTs'!$C$2:$C$501,"PTT adicional*",'Destaques e PTTs'!$W$2:$W$501,"OK")) | M27: =IF($A27="","",IF('Orientações'!$B$4="Profissional",IF(AND(K27=2,L27=3),"OK",IF(OR(K27>2,L27>3),"EXCEDE","PENDENTE")),IF(K27=2,"OK",IF(K27>2,"EXCEDE","PENDENTE")))) | N27: =IF($A27="","",IF(OR(LOWER($D27)<>"sim",$E27<14,$F27>2,$M27<>"OK",AND(LOWER($C27)<>"sim",G27=0)),"REVISAR","OK"))
D28: sim | G28: =IF($A28="","",COUNTIFS('Lançamentos - Artigos'!$A$2:$A$506,$A28,'Lançamentos - Artigos'!$L$2:$L$506,">0")) | H28: =IF($A28="","",SUMIFS('Lançamentos - Artigos'!$L$2:$L$506,'Lançamentos - Artigos'!$A$2:$A$506,$A28)) | I28: =IF(OR($A28="",G28=0),"",H28/G28) | J28: =IF($A28="","",IF(LOWER($C28)="sim","EXCLUÍDA DO CÁLCULO GERAL",IF(G28=0,"SEM ARTIGO VÁLIDO",IF(I28>=0.5,"REFERÊNCIA ATENDIDA","ABAIXO DE 0,50")))) | K28: =IF($A28="","",COUNTIFS('Destaques e PTTs'!$A$2:$A$501,$A28,'Destaques e PTTs'!$C$2:$C$501,"Destaque*",'Destaques e PTTs'!$W$2:$W$501,"OK")) | L28: =IF($A28="","",COUNTIFS('Destaques e PTTs'!$A$2:$A$501,$A28,'Destaques e PTTs'!$C$2:$C$501,"PTT adicional*",'Destaques e PTTs'!$W$2:$W$501,"OK")) | M28: =IF($A28="","",IF('Orientações'!$B$4="Profissional",IF(AND(K28=2,L28=3),"OK",IF(OR(K28>2,L28>3),"EXCEDE","PENDENTE")),IF(K28=2,"OK",IF(K28>2,"EXCEDE","PENDENTE")))) | N28: =IF($A28="","",IF(OR(LOWER($D28)<>"sim",$E28<14,$F28>2,$M28<>"OK",AND(LOWER($C28)<>"sim",G28=0)),"REVISAR","OK"))
D29: sim | G29: =IF($A29="","",COUNTIFS('Lançamentos - Artigos'!$A$2:$A$506,$A29,'Lançamentos - Artigos'!$L$2:$L$506,">0")) | H29: =IF($A29="","",SUMIFS('Lançamentos - Artigos'!$L$2:$L$506,'Lançamentos - Artigos'!$A$2:$A$506,$A29)) | I29: =IF(OR($A29="",G29=0),"",H29/G29) | J29: =IF($A29="","",IF(LOWER($C29)="sim","EXCLUÍDA DO CÁLCULO GERAL",IF(G29=0,"SEM ARTIGO VÁLIDO",IF(I29>=0.5,"REFERÊNCIA ATENDIDA","ABAIXO DE 0,50")))) | K29: =IF($A29="","",COUNTIFS('Destaques e PTTs'!$A$2:$A$501,$A29,'Destaques e PTTs'!$C$2:$C$501,"Destaque*",'Destaques e PTTs'!$W$2:$W$501,"OK")) | L29: =IF($A29="","",COUNTIFS('Destaques e PTTs'!$A$2:$A$501,$A29,'Destaques e PTTs'!$C$2:$C$501,"PTT adicional*",'Destaques e PTTs'!$W$2:$W$501,"OK")) | M29: =IF($A29="","",IF('Orientações'!$B$4="Profissional",IF(AND(K29=2,L29=3),"OK",IF(OR(K29>2,L29>3),"EXCEDE","PENDENTE")),IF(K29=2,"OK",IF(K29>2,"EXCEDE","PENDENTE")))) | N29: =IF($A29="","",IF(OR(LOWER($D29)<>"sim",$E29<14,$F29>2,$M29<>"OK",AND(LOWER($C29)<>"sim",G29=0)),"REVISAR","OK"))
D30: sim | G30: =IF($A30="","",COUNTIFS('Lançamentos - Artigos'!$A$2:$A$506,$A30,'Lançamentos - Artigos'!$L$2:$L$506,">0")) | H30: =IF($A30="","",SUMIFS('Lançamentos - Artigos'!$L$2:$L$506,'Lançamentos - Artigos'!$A$2:$A$506,$A30)) | I30: =IF(OR($A30="",G30=0),"",H30/G30) | J30: =IF($A30="","",IF(LOWER($C30)="sim","EXCLUÍDA DO CÁLCULO GERAL",IF(G30=0,"SEM ARTIGO VÁLIDO",IF(I30>=0.5,"REFERÊNCIA ATENDIDA","ABAIXO DE 0,50")))) | K30: =IF($A30="","",COUNTIFS('Destaques e PTTs'!$A$2:$A$501,$A30,'Destaques e PTTs'!$C$2:$C$501,"Destaque*",'Destaques e PTTs'!$W$2:$W$501,"OK")) | L30: =IF($A30="","",COUNTIFS('Destaques e PTTs'!$A$2:$A$501,$A30,'Destaques e PTTs'!$C$2:$C$501,"PTT adicional*",'Destaques e PTTs'!$W$2:$W$501,"OK")) | M30: =IF($A30="","",IF('Orientações'!$B$4="Profissional",IF(AND(K30=2,L30=3),"OK",IF(OR(K30>2,L30>3),"EXCEDE","PENDENTE")),IF(K30=2,"OK",IF(K30>2,"EXCEDE","PENDENTE")))) | N30: =IF($A30="","",IF(OR(LOWER($D30)<>"sim",$E30<14,$F30>2,$M30<>"OK",AND(LOWER($C30)<>"sim",G30=0)),"REVISAR","OK"))
D31: sim | G31: =IF($A31="","",COUNTIFS('Lançamentos - Artigos'!$A$2:$A$506,$A31,'Lançamentos - Artigos'!$L$2:$L$506,">0")) | H31: =IF($A31="","",SUMIFS('Lançamentos - Artigos'!$L$2:$L$506,'Lançamentos - Artigos'!$A$2:$A$506,$A31)) | I31: =IF(OR($A31="",G31=0),"",H31/G31) | J31: =IF($A31="","",IF(LOWER($C31)="sim","EXCLUÍDA DO CÁLCULO GERAL",IF(G31=0,"SEM ARTIGO VÁLIDO",IF(I31>=0.5,"REFERÊNCIA ATENDIDA","ABAIXO DE 0,50")))) | K31: =IF($A31="","",COUNTIFS('Destaques e PTTs'!$A$2:$A$501,$A31,'Destaques e PTTs'!$C$2:$C$501,"Destaque*",'Destaques e PTTs'!$W$2:$W$501,"OK")) | L31: =IF($A31="","",COUNTIFS('Destaques e PTTs'!$A$2:$A$501,$A31,'Destaques e PTTs'!$C$2:$C$501,"PTT adicional*",'Destaques e PTTs'!$W$2:$W$501,"OK")) | M31: =IF($A31="","",IF('Orientações'!$B$4="Profissional",IF(AND(K31=2,L31=3),"OK",IF(OR(K31>2,L31>3),"EXCEDE","PENDENTE")),IF(K31=2,"OK",IF(K31>2,"EXCEDE","PENDENTE")))) | N31: =IF($A31="","",IF(OR(LOWER($D31)<>"sim",$E31<14,$F31>2,$M31<>"OK",AND(LOWER($C31)<>"sim",G31=0)),"REVISAR","OK"))
D32: sim | G32: =IF($A32="","",COUNTIFS('Lançamentos - Artigos'!$A$2:$A$506,$A32,'Lançamentos - Artigos'!$L$2:$L$506,">0")) | H32: =IF($A32="","",SUMIFS('Lançamentos - Artigos'!$L$2:$L$506,'Lançamentos - Artigos'!$A$2:$A$506,$A32)) | I32: =IF(OR($A32="",G32=0),"",H32/G32) | J32: =IF($A32="","",IF(LOWER($C32)="sim","EXCLUÍDA DO CÁLCULO GERAL",IF(G32=0,"SEM ARTIGO VÁLIDO",IF(I32>=0.5,"REFERÊNCIA ATENDIDA","ABAIXO DE 0,50")))) | K32: =IF($A32="","",COUNTIFS('Destaques e PTTs'!$A$2:$A$501,$A32,'Destaques e PTTs'!$C$2:$C$501,"Destaque*",'Destaques e PTTs'!$W$2:$W$501,"OK")) | L32: =IF($A32="","",COUNTIFS('Destaques e PTTs'!$A$2:$A$501,$A32,'Destaques e PTTs'!$C$2:$C$501,"PTT adicional*",'Destaques e PTTs'!$W$2:$W$501,"OK")) | M32: =IF($A32="","",IF('Orientações'!$B$4="Profissional",IF(AND(K32=2,L32=3),"OK",IF(OR(K32>2,L32>3),"EXCEDE","PENDENTE")),IF(K32=2,"OK",IF(K32>2,"EXCEDE","PENDENTE")))) | N32: =IF($A32="","",IF(OR(LOWER($D32)<>"sim",$E32<14,$F32>2,$M32<>"OK",AND(LOWER($C32)<>"sim",G32=0)),"REVISAR","OK"))
D33: sim | G33: =IF($A33="","",COUNTIFS('Lançamentos - Artigos'!$A$2:$A$506,$A33,'Lançamentos - Artigos'!$L$2:$L$506,">0")) | H33: =IF($A33="","",SUMIFS('Lançamentos - Artigos'!$L$2:$L$506,'Lançamentos - Artigos'!$A$2:$A$506,$A33)) | I33: =IF(OR($A33="",G33=0),"",H33/G33) | J33: =IF($A33="","",IF(LOWER($C33)="sim","EXCLUÍDA DO CÁLCULO GERAL",IF(G33=0,"SEM ARTIGO VÁLIDO",IF(I33>=0.5,"REFERÊNCIA ATENDIDA","ABAIXO DE 0,50")))) | K33: =IF($A33="","",COUNTIFS('Destaques e PTTs'!$A$2:$A$501,$A33,'Destaques e PTTs'!$C$2:$C$501,"Destaque*",'Destaques e PTTs'!$W$2:$W$501,"OK")) | L33: =IF($A33="","",COUNTIFS('Destaques e PTTs'!$A$2:$A$501,$A33,'Destaques e PTTs'!$C$2:$C$501,"PTT adicional*",'Destaques e PTTs'!$W$2:$W$501,"OK")) | M33: =IF($A33="","",IF('Orientações'!$B$4="Profissional",IF(AND(K33=2,L33=3),"OK",IF(OR(K33>2,L33>3),"EXCEDE","PENDENTE")),IF(K33=2,"OK",IF(K33>2,"EXCEDE","PENDENTE")))) | N33: =IF($A33="","",IF(OR(LOWER($D33)<>"sim",$E33<14,$F33>2,$M33<>"OK",AND(LOWER($C33)<>"sim",G33=0)),"REVISAR","OK"))
D34: sim | G34: =IF($A34="","",COUNTIFS('Lançamentos - Artigos'!$A$2:$A$506,$A34,'Lançamentos - Artigos'!$L$2:$L$506,">0")) | H34: =IF($A34="","",SUMIFS('Lançamentos - Artigos'!$L$2:$L$506,'Lançamentos - Artigos'!$A$2:$A$506,$A34)) | I34: =IF(OR($A34="",G34=0),"",H34/G34) | J34: =IF($A34="","",IF(LOWER($C34)="sim","EXCLUÍDA DO CÁLCULO GERAL",IF(G34=0,"SEM ARTIGO VÁLIDO",IF(I34>=0.5,"REFERÊNCIA ATENDIDA","ABAIXO DE 0,50")))) | K34: =IF($A34="","",COUNTIFS('Destaques e PTTs'!$A$2:$A$501,$A34,'Destaques e PTTs'!$C$2:$C$501,"Destaque*",'Destaques e PTTs'!$W$2:$W$501,"OK")) | L34: =IF($A34="","",COUNTIFS('Destaques e PTTs'!$A$2:$A$501,$A34,'Destaques e PTTs'!$C$2:$C$501,"PTT adicional*",'Destaques e PTTs'!$W$2:$W$501,"OK")) | M34: =IF($A34="","",IF('Orientações'!$B$4="Profissional",IF(AND(K34=2,L34=3),"OK",IF(OR(K34>2,L34>3),"EXCEDE","PENDENTE")),IF(K34=2,"OK",IF(K34>2,"EXCEDE","PENDENTE")))) | N34: =IF($A34="","",IF(OR(LOWER($D34)<>"sim",$E34<14,$F34>2,$M34<>"OK",AND(LOWER($C34)<>"sim",G34=0)),"REVISAR","OK"))
D35: sim | G35: =IF($A35="","",COUNTIFS('Lançamentos - Artigos'!$A$2:$A$506,$A35,'Lançamentos - Artigos'!$L$2:$L$506,">0")) | H35: =IF($A35="","",SUMIFS('Lançamentos - Artigos'!$L$2:$L$506,'Lançamentos - Artigos'!$A$2:$A$506,$A35)) | I35: =IF(OR($A35="",G35=0),"",H35/G35) | J35: =IF($A35="","",IF(LOWER($C35)="sim","EXCLUÍDA DO CÁLCULO GERAL",IF(G35=0,"SEM ARTIGO VÁLIDO",IF(I35>=0.5,"REFERÊNCIA ATENDIDA","ABAIXO DE 0,50")))) | K35: =IF($A35="","",COUNTIFS('Destaques e PTTs'!$A$2:$A$501,$A35,'Destaques e PTTs'!$C$2:$C$501,"Destaque*",'Destaques e PTTs'!$W$2:$W$501,"OK")) | L35: =IF($A35="","",COUNTIFS('Destaques e PTTs'!$A$2:$A$501,$A35,'Destaques e PTTs'!$C$2:$C$501,"PTT adicional*",'Destaques e PTTs'!$W$2:$W$501,"OK")) | M35: =IF($A35="","",IF('Orientações'!$B$4="Profissional",IF(AND(K35=2,L35=3),"OK",IF(OR(K35>2,L35>3),"EXCEDE","PENDENTE")),IF(K35=2,"OK",IF(K35>2,"EXCEDE","PENDENTE")))) | N35: =IF($A35="","",IF(OR(LOWER($D35)<>"sim",$E35<14,$F35>2,$M35<>"OK",AND(LOWER($C35)<>"sim",G35=0)),"REVISAR","OK"))
D36: sim | G36: =IF($A36="","",COUNTIFS('Lançamentos - Artigos'!$A$2:$A$506,$A36,'Lançamentos - Artigos'!$L$2:$L$506,">0")) | H36: =IF($A36="","",SUMIFS('Lançamentos - Artigos'!$L$2:$L$506,'Lançamentos - Artigos'!$A$2:$A$506,$A36)) | I36: =IF(OR($A36="",G36=0),"",H36/G36) | J36: =IF($A36="","",IF(LOWER($C36)="sim","EXCLUÍDA DO CÁLCULO GERAL",IF(G36=0,"SEM ARTIGO VÁLIDO",IF(I36>=0.5,"REFERÊNCIA ATENDIDA","ABAIXO DE 0,50")))) | K36: =IF($A36="","",COUNTIFS('Destaques e PTTs'!$A$2:$A$501,$A36,'Destaques e PTTs'!$C$2:$C$501,"Destaque*",'Destaques e PTTs'!$W$2:$W$501,"OK")) | L36: =IF($A36="","",COUNTIFS('Destaques e PTTs'!$A$2:$A$501,$A36,'Destaques e PTTs'!$C$2:$C$501,"PTT adicional*",'Destaques e PTTs'!$W$2:$W$501,"OK")) | M36: =IF($A36="","",IF('Orientações'!$B$4="Profissional",IF(AND(K36=2,L36=3),"OK",IF(OR(K36>2,L36>3),"EXCEDE","PENDENTE")),IF(K36=2,"OK",IF(K36>2,"EXCEDE","PENDENTE")))) | N36: =IF($A36="","",IF(OR(LOWER($D36)<>"sim",$E36<14,$F36>2,$M36<>"OK",AND(LOWER($C36)<>"sim",G36=0)),"REVISAR","OK"))
... D57: sim | G57: =IF($A57="","",COUNTIFS('Lançamentos - Artigos'!$A$2:$A$506,$A57,'Lançamentos - Artigos'!$L$2:$L$506,">0")) | H57: =IF($A57="","",SUMIFS('Lançamentos - Artigos'!$L$2:$L$506,'Lançamentos - Artigos'!$A$2:$A$506,$A57)) | I57: =IF(OR($A57="",G57=0),"",H57/G57) | J57: =IF($A57="","",IF(LOWER($C57)="sim","EXCLUÍDA DO CÁLCULO GERAL",IF(G57=0,"SEM ARTIGO VÁLIDO",IF(I57>=0.5,"REFERÊNCIA ATENDIDA","ABAIXO DE 0,50")))) | K57: =IF($A57="","",COUNTIFS('Destaques e PTTs'!$A$2:$A$501,$A57,'Destaques e PTTs'!$C$2:$C$501,"Destaque*",'Destaques e PTTs'!$W$2:$W$501,"OK")) | L57: =IF($A57="","",COUNTIFS('Destaques e PTTs'!$A$2:$A$501,$A57,'Destaques e PTTs'!$C$2:$C$501,"PTT adicional*",'Destaques e PTTs'!$W$2:$W$501,"OK")) | M57: =IF($A57="","",IF('Orientações'!$B$4="Profissional",IF(AND(K57=2,L57=3),"OK",IF(OR(K57>2,L57>3),"EXCEDE","PENDENTE")),IF(K57=2,"OK",IF(K57>2,"EXCEDE","PENDENTE")))) | N57: =IF($A57="","",IF(OR(LOWER($D57)<>"sim",$E57<14,$F57>2,$M57<>"OK",AND(LOWER($C57)<>"sim",G57=0)),"REVISAR","OK"))

Sheet Lançamentos - Artigos
A1: Docente | B1: Linha de pesquisa/atuação | C1: Ano | D1: Título do artigo | E1: DOI | F1: País do periódico | G1: Base usada | H1: Percentil WoS/Scopus | I1: Dimensions: maior % de artigos citados | J1: Dimensions: média de citações | K1: Índice CAPES | L1: Índice válido | M1: FWCI/ICPC | N1: No Lattes? | O1: Aderente à proposta? | P1: Observações
A2: Anderson Saldanha Bueno | B2: =IF($A2="","",IFERROR(VLOOKUP($A2,'Resumo por docente'!$A$8:$B$57,2,FALSE),"")) -> Biodiversidade, Saúde Ambiental e Conservação | C2: 2026 | D2: Patterns of understorey bird diversity across Amazonian forests: survey effort and range maps predict local species richness | E2: https://doi.org/10.1002/ecog.07625 | K2: =IF($A2="","",IF(OR($G2="WoS",$G2="Scopus"),IF($H2="","",IF($H2>=87.5,1,IF($H2>=75,0.875,IF($H2>=62.5,0.75,IF($H2>=50,0.625,IF($H2>=37.5,0.5,IF($H2>=25,0.375,IF($H2>=12.5,0.25,IF($H2>=0.01,0.125,0))))))))),IF($G2="Dimensions",IF(OR($I2="",$J2=""),"",MIN(IF($I2>=87.5,1,IF($I2>=75,0.875,IF($I2>=62.5,0.75,IF($I2>=50,0.625,IF($I2>=37.5,0.5,IF($I2>=25,0.375,IF($I2>=12.5,0.25,IF($I2>=0.01,0.125,0)))))))),IF($J2>=2,1,IF($J2>=1.5,0.875,IF($J2>=1,0.75,IF($J2>=0.75,0.625,IF($J2>=0.5,0.5,IF($J2>=0.25,0.375,IF($J2>=0.125,0.25,IF($J2>=0.01,0.125,0)))))))))),""))) | L2: =IF($A2="","",IF(AND($C2>=2021,$C2<=2026,$E2<>"",$K2>0,LOWER($N2)="sim",LOWER($O2)="sim",OR(AND($F2="Exterior",OR($G2="WoS",$G2="Scopus")),AND($F2="Brasil",OR(AND(OR($G2="WoS",$G2="Scopus"),$H2>=50),$G2="Dimensions")))),$K2,"")) | N2: sim
A3: Anderson Saldanha Bueno | B3: =IF($A3="","",IFERROR(VLOOKUP($A3,'Resumo por docente'!$A$8:$B$57,2,FALSE),"")) -> Biodiversidade, Saúde Ambiental e Conservação | C3: 2026 | D3: High-quality surrounding landscapes mitigate avian extirpations from forest remnants | E3: https://doi.org/10.1073/pnas.2521783123 | K3: =IF($A3="","",IF(OR($G3="WoS",$G3="Scopus"),IF($H3="","",IF($H3>=87.5,1,IF($H3>=75,0.875,IF($H3>=62.5,0.75,IF($H3>=50,0.625,IF($H3>=37.5,0.5,IF($H3>=25,0.375,IF($H3>=12.5,0.25,IF($H3>=0.01,0.125,0))))))))),IF($G3="Dimensions",IF(OR($I3="",$J3=""),"",MIN(IF($I3>=87.5,1,IF($I3>=75,0.875,IF($I3>=62.5,0.75,IF($I3>=50,0.625,IF($I3>=37.5,0.5,IF($I3>=25,0.375,IF($I3>=12.5,0.25,IF($I3>=0.01,0.125,0)))))))),IF($J3>=2,1,IF($J3>=1.5,0.875,IF($J3>=1,0.75,IF($J3>=0.75,0.625,IF($J3>=0.5,0.5,IF($J3>=0.25,0.375,IF($J3>=0.125,0.25,IF($J3>=0.01,0.125,0)))))))))),""))) | L3: =IF($A3="","",IF(AND($C3>=2021,$C3<=2026,$E3<>"",$K3>0,LOWER($N3)="sim",LOWER($O3)="sim",OR(AND($F3="Exterior",OR($G3="WoS",$G3="Scopus")),AND($F3="Brasil",OR(AND(OR($G3="WoS",$G3="Scopus"),$H3>=50),$G3="Dimensions")))),$K3,"")) | N3: sim
A4: Anderson Saldanha Bueno | B4: =IF($A4="","",IFERROR(VLOOKUP($A4,'Resumo por docente'!$A$8:$B$57,2,FALSE),"")) -> Biodiversidade, Saúde Ambiental e Conservação | C4: 2026 | D4: Habitat insularization alters taxonomic and functional beta diversity of understorey birds in Amazonian forest islands | E4: https://doi.org/10.1098/rsos.260165 | K4: =IF($A4="","",IF(OR($G4="WoS",$G4="Scopus"),IF($H4="","",IF($H4>=87.5,1,IF($H4>=75,0.875,IF($H4>=62.5,0.75,IF($H4>=50,0.625,IF($H4>=37.5,0.5,IF($H4>=25,0.375,IF($H4>=12.5,0.25,IF($H4>=0.01,0.125,0))))))))),IF($G4="Dimensions",IF(OR($I4="",$J4=""),"",MIN(IF($I4>=87.5,1,IF($I4>=75,0.875,IF($I4>=62.5,0.75,IF($I4>=50,0.625,IF($I4>=37.5,0.5,IF($I4>=25,0.375,IF($I4>=12.5,0.25,IF($I4>=0.01,0.125,0)))))))),IF($J4>=2,1,IF($J4>=1.5,0.875,IF($J4>=1,0.75,IF($J4>=0.75,0.625,IF($J4>=0.5,0.5,IF($J4>=0.25,0.375,IF($J4>=0.125,0.25,IF($J4>=0.01,0.125,0)))))))))),""))) | L4: =IF($A4="","",IF(AND($C4>=2021,$C4<=2026,$E4<>"",$K4>0,LOWER($N4)="sim",LOWER($O4)="sim",OR(AND($F4="Exterior",OR($G4="WoS",$G4="Scopus")),AND($F4="Brasil",OR(AND(OR($G4="WoS",$G4="Scopus"),$H4>=50),$G4="Dimensions")))),$K4,"")) | N4: sim
A5: Anderson Saldanha Bueno | B5: =IF($A5="","",IFERROR(VLOOKUP($A5,'Resumo por docente'!$A$8:$B$57,2,FALSE),"")) -> Biodiversidade, Saúde Ambiental e Conservação | C5: 2025 | D5: Evaluation of multiple water immersions of pathogen vector mosquito (Diptera: Culicidae) eggs | E5: https://doi.org/10.3389/fitd.2025.1590603 | K5: =IF($A5="","",IF(OR($G5="WoS",$G5="Scopus"),IF($H5="","",IF($H5>=87.5,1,IF($H5>=75,0.875,IF($H5>=62.5,0.75,IF($H5>=50,0.625,IF($H5>=37.5,0.5,IF($H5>=25,0.375,IF($H5>=12.5,0.25,IF($H5>=0.01,0.125,0))))))))),IF($G5="Dimensions",IF(OR($I5="",$J5=""),"",MIN(IF($I5>=87.5,1,IF($I5>=75,0.875,IF($I5>=62.5,0.75,IF($I5>=50,0.625,IF($I5>=37.5,0.5,IF($I5>=25,0.375,IF($I5>=12.5,0.25,IF($I5>=0.01,0.125,0)))))))),IF($J5>=2,1,IF($J5>=1.5,0.875,IF($J5>=1,0.75,IF($J5>=0.75,0.625,IF($J5>=0.5,0.5,IF($J5>=0.25,0.375,IF($J5>=0.125,0.25,IF($J5>=0.01,0.125,0)))))))))),""))) | L5: =IF($A5="","",IF(AND($C5>=2021,$C5<=2026,$E5<>"",$K5>0,LOWER($N5)="sim",LOWER($O5)="sim",OR(AND($F5="Exterior",OR($G5="WoS",$G5="Scopus")),AND($F5="Brasil",OR(AND(OR($G5="WoS",$G5="Scopus"),$H5>=50),$G5="Dimensions")))),$K5,"")) | N5: sim
A6: Anderson Saldanha Bueno | B6: =IF($A6="","",IFERROR(VLOOKUP($A6,'Resumo por docente'!$A$8:$B$57,2,FALSE),"")) -> Biodiversidade, Saúde Ambiental e Conservação | C6: 2025 | D6: Tree plantations inserted in a benign environmental context can contribute to the maintenance of forest avifauna | E6: https://doi.org/10.1016/j.foreco.2025.122985 | K6: =IF($A6="","",IF(OR($G6="WoS",$G6="Scopus"),IF($H6="","",IF($H6>=87.5,1,IF($H6>=75,0.875,IF($H6>=62.5,0.75,IF($H6>=50,0.625,IF($H6>=37.5,0.5,IF($H6>=25,0.375,IF($H6>=12.5,0.25,IF($H6>=0.01,0.125,0))))))))),IF($G6="Dimensions",IF(OR($I6="",$J6=""),"",MIN(IF($I6>=87.5,1,IF($I6>=75,0.875,IF($I6>=62.5,0.75,IF($I6>=50,0.625,IF($I6>=37.5,0.5,IF($I6>=25,0.375,IF($I6>=12.5,0.25,IF($I6>=0.01,0.125,0)))))))),IF($J6>=2,1,IF($J6>=1.5,0.875,IF($J6>=1,0.75,IF($J6>=0.75,0.625,IF($J6>=0.5,0.5,IF($J6>=0.25,0.375,IF($J6>=0.125,0.25,IF($J6>=0.01,0.125,0)))))))))),""))) | L6: =IF($A6="","",IF(AND($C6>=2021,$C6<=2026,$E6<>"",$K6>0,LOWER($N6)="sim",LOWER($O6)="sim",OR(AND($F6="Exterior",OR($G6="WoS",$G6="Scopus")),AND($F6="Brasil",OR(AND(OR($G6="WoS",$G6="Scopus"),$H6>=50),$G6="Dimensions")))),$K6,"")) | N6: sim
A7: Anderson Saldanha Bueno | B7: =IF($A7="","",IFERROR(VLOOKUP($A7,'Resumo por docente'!$A$8:$B$57,2,FALSE),"")) -> Biodiversidade, Saúde Ambiental e Conservação | C7: 2025 | D7: Protocolo de amostragem da biodiversidade via monitoramento acústico passivo | K7: =IF($A7="","",IF(OR($G7="WoS",$G7="Scopus"),IF($H7="","",IF($H7>=87.5,1,IF($H7>=75,0.875,IF($H7>=62.5,0.75,IF($H7>=50,0.625,IF($H7>=37.5,0.5,IF($H7>=25,0.375,IF($H7>=12.5,0.25,IF($H7>=0.01,0.125,0))))))))),IF($G7="Dimensions",IF(OR($I7="",$J7=""),"",MIN(IF($I7>=87.5,1,IF($I7>=75,0.875,IF($I7>=62.5,0.75,IF($I7>=50,0.625,IF($I7>=37.5,0.5,IF($I7>=25,0.375,IF($I7>=12.5,0.25,IF($I7>=0.01,0.125,0)))))))),IF($J7>=2,1,IF($J7>=1.5,0.875,IF($J7>=1,0.75,IF($J7>=0.75,0.625,IF($J7>=0.5,0.5,IF($J7>=0.25,0.375,IF($J7>=0.125,0.25,IF($J7>=0.01,0.125,0)))))))))),""))) | L7: =IF($A7="","",IF(AND($C7>=2021,$C7<=2026,$E7<>"",$K7>0,LOWER($N7)="sim",LOWER($O7)="sim",OR(AND($F7="Exterior",OR($G7="WoS",$G7="Scopus")),AND($F7="Brasil",OR(AND(OR($G7="WoS",$G7="Scopus"),$H7>=50),$G7="Dimensions")))),$K7,"")) | N7: sim
A8: Anderson Saldanha Bueno | B8: =IF($A8="","",IFERROR(VLOOKUP($A8,'Resumo por docente'!$A$8:$B$57,2,FALSE),"")) -> Biodiversidade, Saúde Ambiental e Conservação | C8: 2025 | D8: Protocolo de amostragem de aves em parcelas RAPELD | K8: =IF($A8="","",IF(OR($G8="WoS",$G8="Scopus"),IF($H8="","",IF($H8>=87.5,1,IF($H8>=75,0.875,IF($H8>=62.5,0.75,IF($H8>=50,0.625,IF($H8>=37.5,0.5,IF($H8>=25,0.375,IF($H8>=12.5,0.25,IF($H8>=0.01,0.125,0))))))))),IF($G8="Dimensions",IF(OR($I8="",$J8=""),"",MIN(IF($I8>=87.5,1,IF($I8>=75,0.875,IF($I8>=62.5,0.75,IF($I8>=50,0.625,IF($I8>=37.5,0.5,IF($I8>=25,0.375,IF($I8>=12.5,0.25,IF($I8>=0.01,0.125,0)))))))),IF($J8>=2,1,IF($J8>=1.5,0.875,IF($J8>=1,0.75,IF($J8>=0.75,0.625,IF($J8>=0.5,0.5,IF($J8>=0.25,0.375,IF($J8>=0.125,0.25,IF($J8>=0.01,0.125,0)))))))))),""))) | L8: =IF($A8="","",IF(AND($C8>=2021,$C8<=2026,$E8<>"",$K8>0,LOWER($N8)="sim",LOWER($O8)="sim",OR(AND($F8="Exterior",OR($G8="WoS",$G8="Scopus")),AND($F8="Brasil",OR(AND(OR($G8="WoS",$G8="Scopus"),$H8>=50),$G8="Dimensions")))),$K8,"")) | N8: sim
A9: Anderson Saldanha Bueno | B9: =IF($A9="","",IFERROR(VLOOKUP($A9,'Resumo por docente'!$A$8:$B$57,2,FALSE),"")) -> Biodiversidade, Saúde Ambiental e Conservação | C9: 2025 | D9: Forest structure predicts plant and animal species diversity and composition changes in an Amazonian forest | E9: https://doi.org/10.1007/s10531-025-03136-4 | K9: =IF($A9="","",IF(OR($G9="WoS",$G9="Scopus"),IF($H9="","",IF($H9>=87.5,1,IF($H9>=75,0.875,IF($H9>=62.5,0.75,IF($H9>=50,0.625,IF($H9>=37.5,0.5,IF($H9>=25,0.375,IF($H9>=12.5,0.25,IF($H9>=0.01,0.125,0))))))))),IF($G9="Dimensions",IF(OR($I9="",$J9=""),"",MIN(IF($I9>=87.5,1,IF($I9>=75,0.875,IF($I9>=62.5,0.75,IF($I9>=50,0.625,IF($I9>=37.5,0.5,IF($I9>=25,0.375,IF($I9>=12.5,0.25,IF($I9>=0.01,0.125,0)))))))),IF($J9>=2,1,IF($J9>=1.5,0.875,IF($J9>=1,0.75,IF($J9>=0.75,0.625,IF($J9>=0.5,0.5,IF($J9>=0.25,0.375,IF($J9>=0.125,0.25,IF($J9>=0.01,0.125,0)))))))))),""))) | L9: =IF($A9="","",IF(AND($C9>=2021,$C9<=2026,$E9<>"",$K9>0,LOWER($N9)="sim",LOWER($O9)="sim",OR(AND($F9="Exterior",OR($G9="WoS",$G9="Scopus")),AND($F9="Brasil",OR(AND(OR($G9="WoS",$G9="Scopus"),$H9>=50),$G9="Dimensions")))),$K9,"")) | N9: sim
A10: Anderson Saldanha Bueno | B10: =IF($A10="","",IFERROR(VLOOKUP($A10,'Resumo por docente'!$A$8:$B$57,2,FALSE),"")) -> Biodiversidade, Saúde Ambiental e Conservação | C10: 2025 | D10: How much sampling is enough? Four decades of understorey bird mist-netting across Amazonia define the minimum effort to uncover species assemblage structure | E10: https://doi.org/10.1111/ibi.70015 | K10: =IF($A10="","",IF(OR($G10="WoS",$G10="Scopus"),IF($H10="","",IF($H10>=87.5,1,IF($H10>=75,0.875,IF($H10>=62.5,0.75,IF($H10>=50,0.625,IF($H10>=37.5,0.5,IF($H10>=25,0.375,IF($H10>=12.5,0.25,IF($H10>=0.01,0.125,0))))))))),IF($G10="Dimensions",IF(OR($I10="",$J10=""),"",MIN(IF($I10>=87.5,1,IF($I10>=75,0.875,IF($I10>=62.5,0.75,IF($I10>=50,0.625,IF($I10>=37.5,0.5,IF($I10>=25,0.375,IF($I10>=12.5,0.25,IF($I10>=0.01,0.125,0)))))))),IF($J10>=2,1,IF($J10>=1.5,0.875,IF($J10>=1,0.75,IF($J10>=0.75,0.625,IF($J10>=0.5,0.5,IF($J10>=0.25,0.375,IF($J10>=0.125,0.25,IF($J10>=0.01,0.125,0)))))))))),""))) | L10: =IF($A10="","",IF(AND($C10>=2021,$C10<=2026,$E10<>"",$K10>0,LOWER($N10)="sim",LOWER($O10)="sim",OR(AND($F10="Exterior",OR($G10="WoS",$G10="Scopus")),AND($F10="Brasil",OR(AND(OR($G10="WoS",$G10="Scopus"),$H10>=50),$G10="Dimensions")))),$K10,"")) | N10: sim
A11: Anderson Saldanha Bueno | B11: =IF($A11="","",IFERROR(VLOOKUP($A11,'Resumo por docente'!$A$8:$B$57,2,FALSE),"")) -> Biodiversidade, Saúde Ambiental e Conservação | C11: 2024 | D11: Disentangling the veil line for Brazilian biodiversity: An overview from two long-term research programs reveals huge gaps in ecological data reporting | E11: https://doi.org/10.1016/j.scitotenv.2024.174880 | K11: =IF($A11="","",IF(OR($G11="WoS",$G11="Scopus"),IF($H11="","",IF($H11>=87.5,1,IF($H11>=75,0.875,IF($H11>=62.5,0.75,IF($H11>=50,0.625,IF($H11>=37.5,0.5,IF($H11>=25,0.375,IF($H11>=12.5,0.25,IF($H11>=0.01,0.125,0))))))))),IF($G11="Dimensions",IF(OR($I11="",$J11=""),"",MIN(IF($I11>=87.5,1,IF($I11>=75,0.875,IF($I11>=62.5,0.75,IF($I11>=50,0.625,IF($I11>=37.5,0.5,IF($I11>=25,0.375,IF($I11>=12.5,0.25,IF($I11>=0.01,0.125,0)))))))),IF($J11>=2,1,IF($J11>=1.5,0.875,IF($J11>=1,0.75,IF($J11>=0.75,0.625,IF($J11>=0.5,0.5,IF($J11>=0.25,0.375,IF($J11>=0.125,0.25,IF($J11>=0.01,0.125,0)))))))))),""))) | L11: =IF($A11="","",IF(AND($C11>=2021,$C11<=2026,$E11<>"",$K11>0,LOWER($N11)="sim",LOWER($O11)="sim",OR(AND($F11="Exterior",OR($G11="WoS",$G11="Scopus")),AND($F11="Brasil",OR(AND(OR($G11="WoS",$G11="Scopus"),$H11>=50),$G11="Dimensions")))),$K11,"")) | N11: sim
A12: Anderson Saldanha Bueno | B12: =IF($A12="","",IFERROR(VLOOKUP($A12,'Resumo por docente'!$A$8:$B$57,2,FALSE),"")) -> Biodiversidade, Saúde Ambiental e Conservação | C12: 2024 | D12: Extending Species-Area Relationships Into the Realm of Ecoacoustics: The Soundscape-Area Relationship | E12: https://doi.org/10.1111/ele.14529 | K12: =IF($A12="","",IF(OR($G12="WoS",$G12="Scopus"),IF($H12="","",IF($H12>=87.5,1,IF($H12>=75,0.875,IF($H12>=62.5,0.75,IF($H12>=50,0.625,IF($H12>=37.5,0.5,IF($H12>=25,0.375,IF($H12>=12.5,0.25,IF($H12>=0.01,0.125,0))))))))),IF($G12="Dimensions",IF(OR($I12="",$J12=""),"",MIN(IF($I12>=87.5,1,IF($I12>=75,0.875,IF($I12>=62.5,0.75,IF($I12>=50,0.625,IF($I12>=37.5,0.5,IF($I12>=25,0.375,IF($I12>=12.5,0.25,IF($I12>=0.01,0.125,0)))))))),IF($J12>=2,1,IF($J12>=1.5,0.875,IF($J12>=1,0.75,IF($J12>=0.75,0.625,IF($J12>=0.5,0.5,IF($J12>=0.25,0.375,IF($J12>=0.125,0.25,IF($J12>=0.01,0.125,0)))))))))),""))) | L12: =IF($A12="","",IF(AND($C12>=2021,$C12<=2026,$E12<>"",$K12>0,LOWER($N12)="sim",LOWER($O12)="sim",OR(AND($F12="Exterior",OR($G12="WoS",$G12="Scopus")),AND($F12="Brasil",OR(AND(OR($G12="WoS",$G12="Scopus"),$H12>=50),$G12="Dimensions")))),$K12,"")) | N12: sim
A13: Anderson Saldanha Bueno | B13: =IF($A13="","",IFERROR(VLOOKUP($A13,'Resumo por docente'!$A$8:$B$57,2,FALSE),"")) -> Biodiversidade, Saúde Ambiental e Conservação | C13: 2023 | D13: Number of forest fragments and understory plants exert opposite effects on multiple facets of bird diversity in eucalypt plantations | E13: https://doi.org/10.1007/s10980-023-01601-5 | K13: =IF($A13="","",IF(OR($G13="WoS",$G13="Scopus"),IF($H13="","",IF($H13>=87.5,1,IF($H13>=75,0.875,IF($H13>=62.5,0.75,IF($H13>=50,0.625,IF($H13>=37.5,0.5,IF($H13>=25,0.375,IF($H13>=12.5,0.25,IF($H13>=0.01,0.125,0))))))))),IF($G13="Dimensions",IF(OR($I13="",$J13=""),"",MIN(IF($I13>=87.5,1,IF($I13>=75,0.875,IF($I13>=62.5,0.75,IF($I13>=50,0.625,IF($I13>=37.5,0.5,IF($I13>=25,0.375,IF($I13>=12.5,0.25,IF($I13>=0.01,0.125,0)))))))),IF($J13>=2,1,IF($J13>=1.5,0.875,IF($J13>=1,0.75,IF($J13>=0.75,0.625,IF($J13>=0.5,0.5,IF($J13>=0.25,0.375,IF($J13>=0.125,0.25,IF($J13>=0.01,0.125,0)))))))))),""))) | L13: =IF($A13="","",IF(AND($C13>=2021,$C13<=2026,$E13<>"",$K13>0,LOWER($N13)="sim",LOWER($O13)="sim",OR(AND($F13="Exterior",OR($G13="WoS",$G13="Scopus")),AND($F13="Brasil",OR(AND(OR($G13="WoS",$G13="Scopus"),$H13>=50),$G13="Dimensions")))),$K13,"")) | N13: sim
A14: Anderson Saldanha Bueno | B14: =IF($A14="","",IFERROR(VLOOKUP($A14,'Resumo por docente'!$A$8:$B$57,2,FALSE),"")) -> Biodiversidade, Saúde Ambiental e Conservação | C14: 2023 | D14: Pervasive gaps in Amazonian ecological research | E14: https://doi.org/10.1016/j.cub.2023.06.077 | K14: =IF($A14="","",IF(OR($G14="WoS",$G14="Scopus"),IF($H14="","",IF($H14>=87.5,1,IF($H14>=75,0.875,IF($H14>=62.5,0.75,IF($H14>=50,0.625,IF($H14>=37.5,0.5,IF($H14>=25,0.375,IF($H14>=12.5,0.25,IF($H14>=0.01,0.125,0))))))))),IF($G14="Dimensions",IF(OR($I14="",$J14=""),"",MIN(IF($I14>=87.5,1,IF($I14>=75,0.875,IF($I14>=62.5,0.75,IF($I14>=50,0.625,IF($I14>=37.5,0.5,IF($I14>=25,0.375,IF($I14>=12.5,0.25,IF($I14>=0.01,0.125,0)))))))),IF($J14>=2,1,IF($J14>=1.5,0.875,IF($J14>=1,0.75,IF($J14>=0.75,0.625,IF($J14>=0.5,0.5,IF($J14>=0.25,0.375,IF($J14>=0.125,0.25,IF($J14>=0.01,0.125,0)))))))))),""))) | L14: =IF($A14="","",IF(AND($C14>=2021,$C14<=2026,$E14<>"",$K14>0,LOWER($N14)="sim",LOWER($O14)="sim",OR(AND($F14="Exterior",OR($G14="WoS",$G14="Scopus")),AND($F14="Brasil",OR(AND(OR($G14="WoS",$G14="Scopus"),$H14>=50),$G14="Dimensions")))),$K14,"")) | N14: sim
A15: Anderson Saldanha Bueno | B15: =IF($A15="","",IFERROR(VLOOKUP($A15,'Resumo por docente'!$A$8:$B$57,2,FALSE),"")) -> Biodiversidade, Saúde Ambiental e Conservação | C15: 2022 | D15: Assessing assemblage-wide mammal responses to different types of habitat modification in Amazonian forests | E15: https://doi.org/10.1038/s41598-022-05450-1 | K15: =IF($A15="","",IF(OR($G15="WoS",$G15="Scopus"),IF($H15="","",IF($H15>=87.5,1,IF($H15>=75,0.875,IF($H15>=62.5,0.75,IF($H15>=50,0.625,IF($H15>=37.5,0.5,IF($H15>=25,0.375,IF($H15>=12.5,0.25,IF($H15>=0.01,0.125,0))))))))),IF($G15="Dimensions",IF(OR($I15="",$J15=""),"",MIN(IF($I15>=87.5,1,IF($I15>=75,0.875,IF($I15>=62.5,0.75,IF($I15>=50,0.625,IF($I15>=37.5,0.5,IF($I15>=25,0.375,IF($I15>=12.5,0.25,IF($I15>=0.01,0.125,0)))))))),IF($J15>=2,1,IF($J15>=1.5,0.875,IF($J15>=1,0.75,IF($J15>=0.75,0.625,IF($J15>=0.5,0.5,IF($J15>=0.25,0.375,IF($J15>=0.125,0.25,IF($J15>=0.01,0.125,0)))))))))),""))) | L15: =IF($A15="","",IF(AND($C15>=2021,$C15<=2026,$E15<>"",$K15>0,LOWER($N15)="sim",LOWER($O15)="sim",OR(AND($F15="Exterior",OR($G15="WoS",$G15="Scopus")),AND($F15="Brasil",OR(AND(OR($G15="WoS",$G15="Scopus"),$H15>=50),$G15="Dimensions")))),$K15,"")) | N15: sim
A16: Anderson Saldanha Bueno | B16: =IF($A16="","",IFERROR(VLOOKUP($A16,'Resumo por docente'!$A$8:$B$57,2,FALSE),"")) -> Biodiversidade, Saúde Ambiental e Conservação | C16: 2022 | D16: Emergent properties of species-habitat networks in an insular forest landscape | E16: https://doi.org/10.1126/sciadv.abm0397 | K16: =IF($A16="","",IF(OR($G16="WoS",$G16="Scopus"),IF($H16="","",IF($H16>=87.5,1,IF($H16>=75,0.875,IF($H16>=62.5,0.75,IF($H16>=50,0.625,IF($H16>=37.5,0.5,IF($H16>=25,0.375,IF($H16>=12.5,0.25,IF($H16>=0.01,0.125,0))))))))),IF($G16="Dimensions",IF(OR($I16="",$J16=""),"",MIN(IF($I16>=87.5,1,IF($I16>=75,0.875,IF($I16>=62.5,0.75,IF($I16>=50,0.625,IF($I16>=37.5,0.5,IF($I16>=25,0.375,IF($I16>=12.5,0.25,IF($I16>=0.01,0.125,0)))))))),IF($J16>=2,1,IF($J16>=1.5,0.875,IF($J16>=1,0.75,IF($J16>=0.75,0.625,IF($J16>=0.5,0.5,IF($J16>=0.25,0.375,IF($J16>=0.125,0.25,IF($J16>=0.01,0.125,0)))))))))),""))) | L16: =IF($A16="","",IF(AND($C16>=2021,$C16<=2026,$E16<>"",$K16>0,LOWER($N16)="sim",LOWER($O16)="sim",OR(AND($F16="Exterior",OR($G16="WoS",$G16="Scopus")),AND($F16="Brasil",OR(AND(OR($G16="WoS",$G16="Scopus"),$H16>=50),$G16="Dimensions")))),$K16,"")) | N16: sim
A17: Anderson Saldanha Bueno | B17: =IF($A17="","",IFERROR(VLOOKUP($A17,'Resumo por docente'!$A$8:$B$57,2,FALSE),"")) -> Biodiversidade, Saúde Ambiental e Conservação | C17: 2022 | D17: Little noticed, but very important: The role of breeding sites formed by bamboos in maintaining the diversity of mosquitoes (Diptera: Culicidae) in the Atlantic Forest biome | E17: https://doi.org/10.1371/journal.pone.0273774 | K17: =IF($A17="","",IF(OR($G17="WoS",$G17="Scopus"),IF($H17="","",IF($H17>=87.5,1,IF($H17>=75,0.875,IF($H17>=62.5,0.75,IF($H17>=50,0.625,IF($H17>=37.5,0.5,IF($H17>=25,0.375,IF($H17>=12.5,0.25,IF($H17>=0.01,0.125,0))))))))),IF($G17="Dimensions",IF(OR($I17="",$J17=""),"",MIN(IF($I17>=87.5,1,IF($I17>=75,0.875,IF($I17>=62.5,0.75,IF($I17>=50,0.625,IF($I17>=37.5,0.5,IF($I17>=25,0.375,IF($I17>=12.5,0.25,IF($I17>=0.01,0.125,0)))))))),IF($J17>=2,1,IF($J17>=1.5,0.875,IF($J17>=1,0.75,IF($J17>=0.75,0.625,IF($J17>=0.5,0.5,IF($J17>=0.25,0.375,IF($J17>=0.125,0.25,IF($J17>=0.01,0.125,0)))))))))),""))) | L17: =IF($A17="","",IF(AND($C17>=2021,$C17<=2026,$E17<>"",$K17>0,LOWER($N17)="sim",LOWER($O17)="sim",OR(AND($F17="Exterior",OR($G17="WoS",$G17="Scopus")),AND($F17="Brasil",OR(AND(OR($G17="WoS",$G17="Scopus"),$H17>=50),$G17="Dimensions")))),$K17,"")) | N17: sim
A18: Anderson Saldanha Bueno | B18: =IF($A18="","",IFERROR(VLOOKUP($A18,'Resumo por docente'!$A$8:$B$57,2,FALSE),"")) -> Biodiversidade, Saúde Ambiental e Conservação | C18: 2022 | D18: A framework for quantifying soundscape diversity using Hill numbers | E18: https://doi.org/10.1111/2041-210x.13924 | K18: =IF($A18="","",IF(OR($G18="WoS",$G18="Scopus"),IF($H18="","",IF($H18>=87.5,1,IF($H18>=75,0.875,IF($H18>=62.5,0.75,IF($H18>=50,0.625,IF($H18>=37.5,0.5,IF($H18>=25,0.375,IF($H18>=12.5,0.25,IF($H18>=0.01,0.125,0))))))))),IF($G18="Dimensions",IF(OR($I18="",$J18=""),"",MIN(IF($I18>=87.5,1,IF($I18>=75,0.875,IF($I18>=62.5,0.75,IF($I18>=50,0.625,IF($I18>=37.5,0.5,IF($I18>=25,0.375,IF($I18>=12.5,0.25,IF($I18>=0.01,0.125,0)))))))),IF($J18>=2,1,IF($J18>=1.5,0.875,IF($J18>=1,0.75,IF($J18>=0.75,0.625,IF($J18>=0.5,0.5,IF($J18>=0.25,0.375,IF($J18>=0.125,0.25,IF($J18>=0.01,0.125,0)))))))))),""))) | L18: =IF($A18="","",IF(AND($C18>=2021,$C18<=2026,$E18<>"",$K18>0,LOWER($N18)="sim",LOWER($O18)="sim",OR(AND($F18="Exterior",OR($G18="WoS",$G18="Scopus")),AND($F18="Brasil",OR(AND(OR($G18="WoS",$G18="Scopus"),$H18>=50),$G18="Dimensions")))),$K18,"")) | N18: sim
A19: Anderson Saldanha Bueno | B19: =IF($A19="","",IFERROR(VLOOKUP($A19,'Resumo por docente'!$A$8:$B$57,2,FALSE),"")) -> Biodiversidade, Saúde Ambiental e Conservação | C19: 2022 | D19: Connecting Amazonian historical biogeography and local assemblages of understorey birds: Recurrent guild proportionality within areas of endemism | E19: https://doi.org/10.1111/jbi.14301 | K19: =IF($A19="","",IF(OR($G19="WoS",$G19="Scopus"),IF($H19="","",IF($H19>=87.5,1,IF($H19>=75,0.875,IF($H19>=62.5,0.75,IF($H19>=50,0.625,IF($H19>=37.5,0.5,IF($H19>=25,0.375,IF($H19>=12.5,0.25,IF($H19>=0.01,0.125,0))))))))),IF($G19="Dimensions",IF(OR($I19="",$J19=""),"",MIN(IF($I19>=87.5,1,IF($I19>=75,0.875,IF($I19>=62.5,0.75,IF($I19>=50,0.625,IF($I19>=37.5,0.5,IF($I19>=25,0.375,IF($I19>=12.5,0.25,IF($I19>=0.01,0.125,0)))))))),IF($J19>=2,1,IF($J19>=1.5,0.875,IF($J19>=1,0.75,IF($J19>=0.75,0.625,IF($J19>=0.5,0.5,IF($J19>=0.25,0.375,IF($J19>=0.125,0.25,IF($J19>=0.01,0.125,0)))))))))),""))) | L19: =IF($A19="","",IF(AND($C19>=2021,$C19<=2026,$E19<>"",$K19>0,LOWER($N19)="sim",LOWER($O19)="sim",OR(AND($F19="Exterior",OR($G19="WoS",$G19="Scopus")),AND($F19="Brasil",OR(AND(OR($G19="WoS",$G19="Scopus"),$H19>=50),$G19="Dimensions")))),$K19,"")) | N19: sim
A20: Carlos Rodrigo Lehn | B20: =IF($A20="","",IFERROR(VLOOKUP($A20,'Resumo por docente'!$A$8:$B$57,2,FALSE),"")) -> Biodiversidade, Saúde Ambiental e Conservação | C20: 2025 | D20: Global Roadkill Data: a dataset on terrestrial vertebrate mortality caused by collision with vehicles | E20: https://doi.org/10.1038/s41597-024-04207-x | K20: =IF($A20="","",IF(OR($G20="WoS",$G20="Scopus"),IF($H20="","",IF($H20>=87.5,1,IF($H20>=75,0.875,IF($H20>=62.5,0.75,IF($H20>=50,0.625,IF($H20>=37.5,0.5,IF($H20>=25,0.375,IF($H20>=12.5,0.25,IF($H20>=0.01,0.125,0))))))))),IF($G20="Dimensions",IF(OR($I20="",$J20=""),"",MIN(IF($I20>=87.5,1,IF($I20>=75,0.875,IF($I20>=62.5,0.75,IF($I20>=50,0.625,IF($I20>=37.5,0.5,IF($I20>=25,0.375,IF($I20>=12.5,0.25,IF($I20>=0.01,0.125,0)))))))),IF($J20>=2,1,IF($J20>=1.5,0.875,IF($J20>=1,0.75,IF($J20>=0.75,0.625,IF($J20>=0.5,0.5,IF($J20>=0.25,0.375,IF($J20>=0.125,0.25,IF($J20>=0.01,0.125,0)))))))))),""))) | L20: =IF($A20="","",IF(AND($C20>=2021,$C20<=2026,$E20<>"",$K20>0,LOWER($N20)="sim",LOWER($O20)="sim",OR(AND($F20="Exterior",OR($G20="WoS",$G20="Scopus")),AND($F20="Brasil",OR(AND(OR($G20="WoS",$G20="Scopus"),$H20>=50),$G20="Dimensions")))),$K20,"")) | N20: sim
... A25: Caroline Leuchtenberger | B25: =IF($A25="","",IFERROR(VLOOKUP($A25,'Resumo por docente'!$A$8:$B$57,2,FALSE),"")) -> Biodiversidade, Saúde Ambiental e Conservação | C25: 2025 | D25: Challenges for the Conservation of the World's Largest Otter in the Land of Jaguars | E25: https://doi.org/10.1017/s003060532500002x | K25: =IF($A25="","",IF(OR($G25="WoS",$G25="Scopus"),IF($H25="","",IF($H25>=87.5,1,IF($H25>=75,0.875,IF($H25>=62.5,0.75,IF($H25>=50,0.625,IF($H25>=37.5,0.5,IF($H25>=25,0.375,IF($H25>=12.5,0.25,IF($H25>=0.01,0.125,0))))))))),IF($G25="Dimensions",IF(OR($I25="",$J25=""),"",MIN(IF($I25>=87.5,1,IF($I25>=75,0.875,IF($I25>=62.5,0.75,IF($I25>=50,0.625,IF($I25>=37.5,0.5,IF($I25>=25,0.375,IF($I25>=12.5,0.25,IF($I25>=0.01,0.125,0)))))))),IF($J25>=2,1,IF($J25>=1.5,0.875,IF($J25>=1,0.75,IF($J25>=0.75,0.625,IF($J25>=0.5,0.5,IF($J25>=0.25,0.375,IF($J25>=0.125,0.25,IF($J25>=0.01,0.125,0)))))))))),""))) | L25: =IF($A25="","",IF(AND($C25>=2021,$C25<=2026,$E25<>"",$K25>0,LOWER($N25)="sim",LOWER($O25)="sim",OR(AND($F25="Exterior",OR($G25="WoS",$G25="Scopus")),AND($F25="Brasil",OR(AND(OR($G25="WoS",$G25="Scopus"),$H25>=50),$G25="Dimensions")))),$K25,"")) | N25: sim
A26: Caroline Leuchtenberger | B26: =IF($A26="","",IFERROR(VLOOKUP($A26,'Resumo por docente'!$A$8:$B$57,2,FALSE),"")) -> Biodiversidade, Saúde Ambiental e Conservação | C26: 2025 | D26: INTERGROUP CONFLICT AND MYIASIS-INDUCED MORTALITY IN A GIANT OTTER FROM THE BRAZILIAN PANTANAL: IMPLICATIONS FOR | K26: =IF($A26="","",IF(OR($G26="WoS",$G26="Scopus"),IF($H26="","",IF($H26>=87.5,1,IF($H26>=75,0.875,IF($H26>=62.5,0.75,IF($H26>=50,0.625,IF($H26>=37.5,0.5,IF($H26>=25,0.375,IF($H26>=12.5,0.25,IF($H26>=0.01,0.125,0))))))))),IF($G26="Dimensions",IF(OR($I26="",$J26=""),"",MIN(IF($I26>=87.5,1,IF($I26>=75,0.875,IF($I26>=62.5,0.75,IF($I26>=50,0.625,IF($I26>=37.5,0.5,IF($I26>=25,0.375,IF($I26>=12.5,0.25,IF($I26>=0.01,0.125,0)))))))),IF($J26>=2,1,IF($J26>=1.5,0.875,IF($J26>=1,0.75,IF($J26>=0.75,0.625,IF($J26>=0.5,0.5,IF($J26>=0.25,0.375,IF($J26>=0.125,0.25,IF($J26>=0.01,0.125,0)))))))))),""))) | L26: =IF($A26="","",IF(AND($C26>=2021,$C26<=2026,$E26<>"",$K26>0,LOWER($N26)="sim",LOWER($O26)="sim",OR(AND($F26="Exterior",OR($G26="WoS",$G26="Scopus")),AND($F26="Brasil",OR(AND(OR($G26="WoS",$G26="Scopus"),$H26>=50),$G26="Dimensions")))),$K26,"")) | N26: sim
A27: Caroline Leuchtenberger | B27: =IF($A27="","",IFERROR(VLOOKUP($A27,'Resumo por docente'!$A$8:$B$57,2,FALSE),"")) -> Biodiversidade, Saúde Ambiental e Conservação | C27: 2025 | D27: Identifying spatial conservation priorities for the giant otter (Pteronura brasiliensis) | E27: https://doi.org/10.5597/lajam00356 | K27: =IF($A27="","",IF(OR($G27="WoS",$G27="Scopus"),IF($H27="","",IF($H27>=87.5,1,IF($H27>=75,0.875,IF($H27>=62.5,0.75,IF($H27>=50,0.625,IF($H27>=37.5,0.5,IF($H27>=25,0.375,IF($H27>=12.5,0.25,IF($H27>=0.01,0.125,0))))))))),IF($G27="Dimensions",IF(OR($I27="",$J27=""),"",MIN(IF($I27>=87.5,1,IF($I27>=75,0.875,IF($I27>=62.5,0.75,IF($I27>=50,0.625,IF($I27>=37.5,0.5,IF($I27>=25,0.375,IF($I27>=12.5,0.25,IF($I27>=0.01,0.125,0)))))))),IF($J27>=2,1,IF($J27>=1.5,0.875,IF($J27>=1,0.75,IF($J27>=0.75,0.625,IF($J27>=0.5,0.5,IF($J27>=0.25,0.375,IF($J27>=0.125,0.25,IF($J27>=0.01,0.125,0)))))))))),""))) | L27: =IF($A27="","",IF(AND($C27>=2021,$C27<=2026,$E27<>"",$K27>0,LOWER($N27)="sim",LOWER($O27)="sim",OR(AND($F27="Exterior",OR($G27="WoS",$G27="Scopus")),AND($F27="Brasil",OR(AND(OR($G27="WoS",$G27="Scopus"),$H27>=50),$G27="Dimensions")))),$K27,"")) | N27: sim
A28: Caroline Leuchtenberger | B28: =IF($A28="","",IFERROR(VLOOKUP($A28,'Resumo por docente'!$A$8:$B$57,2,FALSE),"")) -> Biodiversidade, Saúde Ambiental e Conservação | C28: 2025 | D28: Pervasive mercury contamination of a semiaquatic apex predator across the Pantanal wetland | E28: https://doi.org/10.1017/s0376892925100155 | K28: =IF($A28="","",IF(OR($G28="WoS",$G28="Scopus"),IF($H28="","",IF($H28>=87.5,1,IF($H28>=75,0.875,IF($H28>=62.5,0.75,IF($H28>=50,0.625,IF($H28>=37.5,0.5,IF($H28>=25,0.375,IF($H28>=12.5,0.25,IF($H28>=0.01,0.125,0))))))))),IF($G28="Dimensions",IF(OR($I28="",$J28=""),"",MIN(IF($I28>=87.5,1,IF($I28>=75,0.875,IF($I28>=62.5,0.75,IF($I28>=50,0.625,IF($I28>=37.5,0.5,IF($I28>=25,0.375,IF($I28>=12.5,0.25,IF($I28>=0.01,0.125,0)))))))),IF($J28>=2,1,IF($J28>=1.5,0.875,IF($J28>=1,0.75,IF($J28>=0.75,0.625,IF($J28>=0.5,0.5,IF($J28>=0.25,0.375,IF($J28>=0.125,0.25,IF($J28>=0.01,0.125,0)))))))))),""))) | L28: =IF($A28="","",IF(AND($C28>=2021,$C28<=2026,$E28<>"",$K28>0,LOWER($N28)="sim",LOWER($O28)="sim",OR(AND($F28="Exterior",OR($G28="WoS",$G28="Scopus")),AND($F28="Brasil",OR(AND(OR($G28="WoS",$G28="Scopus"),$H28>=50),$G28="Dimensions")))),$K28,"")) | N28: sim
A29: Caroline Leuchtenberger | B29: =IF($A29="","",IFERROR(VLOOKUP($A29,'Resumo por docente'!$A$8:$B$57,2,FALSE),"")) -> Biodiversidade, Saúde Ambiental e Conservação | C29: 2024 | D29: Noteworthy records of the ticks Ornithodoros rostratus and Amblyomma sculptum parasitizing Pteronura brasiliensis in the central-western region of Brazil, with pathogen investigation notes | E29: https://doi.org/10.1590/s1984-29612024003 | K29: =IF($A29="","",IF(OR($G29="WoS",$G29="Scopus"),IF($H29="","",IF($H29>=87.5,1,IF($H29>=75,0.875,IF($H29>=62.5,0.75,IF($H29>=50,0.625,IF($H29>=37.5,0.5,IF($H29>=25,0.375,IF($H29>=12.5,0.25,IF($H29>=0.01,0.125,0))))))))),IF($G29="Dimensions",IF(OR($I29="",$J29=""),"",MIN(IF($I29>=87.5,1,IF($I29>=75,0.875,IF($I29>=62.5,0.75,IF($I29>=50,0.625,IF($I29>=37.5,0.5,IF($I29>=25,0.375,IF($I29>=12.5,0.25,IF($I29>=0.01,0.125,0)))))))),IF($J29>=2,1,IF($J29>=1.5,0.875,IF($J29>=1,0.75,IF($J29>=0.75,0.625,IF($J29>=0.5,0.5,IF($J29>=0.25,0.375,IF($J29>=0.125,0.25,IF($J29>=0.01,0.125,0)))))))))),""))) | L29: =IF($A29="","",IF(AND($C29>=2021,$C29<=2026,$E29<>"",$K29>0,LOWER($N29)="sim",LOWER($O29)="sim",OR(AND($F29="Exterior",OR($G29="WoS",$G29="Scopus")),AND($F29="Brasil",OR(AND(OR($G29="WoS",$G29="Scopus"),$H29>=50),$G29="Dimensions")))),$K29,"")) | N29: sim
A30: Caroline Leuchtenberger | B30: =IF($A30="","",IFERROR(VLOOKUP($A30,'Resumo por docente'!$A$8:$B$57,2,FALSE),"")) -> Biodiversidade, Saúde Ambiental e Conservação | C30: 2024 | D30: Camera trap surveys of tlantic orest mammals: A data set for analyses considering imperfect detection (2004-2020) | E30: https://doi.org/10.1002/ecy.4298 | K30: =IF($A30="","",IF(OR($G30="WoS",$G30="Scopus"),IF($H30="","",IF($H30>=87.5,1,IF($H30>=75,0.875,IF($H30>=62.5,0.75,IF($H30>=50,0.625,IF($H30>=37.5,0.5,IF($H30>=25,0.375,IF($H30>=12.5,0.25,IF($H30>=0.01,0.125,0))))))))),IF($G30="Dimensions",IF(OR($I30="",$J30=""),"",MIN(IF($I30>=87.5,1,IF($I30>=75,0.875,IF($I30>=62.5,0.75,IF($I30>=50,0.625,IF($I30>=37.5,0.5,IF($I30>=25,0.375,IF($I30>=12.5,0.25,IF($I30>=0.01,0.125,0)))))))),IF($J30>=2,1,IF($J30>=1.5,0.875,IF($J30>=1,0.75,IF($J30>=0.75,0.625,IF($J30>=0.5,0.5,IF($J30>=0.25,0.375,IF($J30>=0.125,0.25,IF($J30>=0.01,0.125,0)))))))))),""))) | L30: =IF($A30="","",IF(AND($C30>=2021,$C30<=2026,$E30<>"",$K30>0,LOWER($N30)="sim",LOWER($O30)="sim",OR(AND($F30="Exterior",OR($G30="WoS",$G30="Scopus")),AND($F30="Brasil",OR(AND(OR($G30="WoS",$G30="Scopus"),$H30>=50),$G30="Dimensions")))),$K30,"")) | N30: sim
A31: Caroline Leuchtenberger | B31: =IF($A31="","",IFERROR(VLOOKUP($A31,'Resumo por docente'!$A$8:$B$57,2,FALSE),"")) -> Biodiversidade, Saúde Ambiental e Conservação | C31: 2024 | D31: The Salto Morato Manifest for Conservation Translocations | E31: https://doi.org/10.1017/s0030605324000231 | K31: =IF($A31="","",IF(OR($G31="WoS",$G31="Scopus"),IF($H31="","",IF($H31>=87.5,1,IF($H31>=75,0.875,IF($H31>=62.5,0.75,IF($H31>=50,0.625,IF($H31>=37.5,0.5,IF($H31>=25,0.375,IF($H31>=12.5,0.25,IF($H31>=0.01,0.125,0))))))))),IF($G31="Dimensions",IF(OR($I31="",$J31=""),"",MIN(IF($I31>=87.5,1,IF($I31>=75,0.875,IF($I31>=62.5,0.75,IF($I31>=50,0.625,IF($I31>=37.5,0.5,IF($I31>=25,0.375,IF($I31>=12.5,0.25,IF($I31>=0.01,0.125,0)))))))),IF($J31>=2,1,IF($J31>=1.5,0.875,IF($J31>=1,0.75,IF($J31>=0.75,0.625,IF($J31>=0.5,0.5,IF($J31>=0.25,0.375,IF($J31>=0.125,0.25,IF($J31>=0.01,0.125,0)))))))))),""))) | L31: =IF($A31="","",IF(AND($C31>=2021,$C31<=2026,$E31<>"",$K31>0,LOWER($N31)="sim",LOWER($O31)="sim",OR(AND($F31="Exterior",OR($G31="WoS",$G31="Scopus")),AND($F31="Brasil",OR(AND(OR($G31="WoS",$G31="Scopus"),$H31>=50),$G31="Dimensions")))),$K31,"")) | N31: sim
A32: Caroline Leuchtenberger | B32: =IF($A32="","",IFERROR(VLOOKUP($A32,'Resumo por docente'!$A$8:$B$57,2,FALSE),"")) -> Biodiversidade, Saúde Ambiental e Conservação | C32: 2023 | D32: NEW CONFIRMED RECORDS OF THE GIANT OTTER (Pteronura brasiliensis, GMELIN, 1788) IN ARGENTINA | K32: =IF($A32="","",IF(OR($G32="WoS",$G32="Scopus"),IF($H32="","",IF($H32>=87.5,1,IF($H32>=75,0.875,IF($H32>=62.5,0.75,IF($H32>=50,0.625,IF($H32>=37.5,0.5,IF($H32>=25,0.375,IF($H32>=12.5,0.25,IF($H32>=0.01,0.125,0))))))))),IF($G32="Dimensions",IF(OR($I32="",$J32=""),"",MIN(IF($I32>=87.5,1,IF($I32>=75,0.875,IF($I32>=62.5,0.75,IF($I32>=50,0.625,IF($I32>=37.5,0.5,IF($I32>=25,0.375,IF($I32>=12.5,0.25,IF($I32>=0.01,0.125,0)))))))),IF($J32>=2,1,IF($J32>=1.5,0.875,IF($J32>=1,0.75,IF($J32>=0.75,0.625,IF($J32>=0.5,0.5,IF($J32>=0.25,0.375,IF($J32>=0.125,0.25,IF($J32>=0.01,0.125,0)))))))))),""))) | L32: =IF($A32="","",IF(AND($C32>=2021,$C32<=2026,$E32<>"",$K32>0,LOWER($N32)="sim",LOWER($O32)="sim",OR(AND($F32="Exterior",OR($G32="WoS",$G32="Scopus")),AND($F32="Brasil",OR(AND(OR($G32="WoS",$G32="Scopus"),$H32>=50),$G32="Dimensions")))),$K32,"")) | N32: sim
A33: Caroline Leuchtenberger | B33: =IF($A33="","",IFERROR(VLOOKUP($A33,'Resumo por docente'!$A$8:$B$57,2,FALSE),"")) -> Biodiversidade, Saúde Ambiental e Conservação | C33: 2023 | D33: Amblyomma sculptum ticks on a giant otter from the Brazilian Pantanal | E33: https://doi.org/10.1590/s1984-29612023053 | K33: =IF($A33="","",IF(OR($G33="WoS",$G33="Scopus"),IF($H33="","",IF($H33>=87.5,1,IF($H33>=75,0.875,IF($H33>=62.5,0.75,IF($H33>=50,0.625,IF($H33>=37.5,0.5,IF($H33>=25,0.375,IF($H33>=12.5,0.25,IF($H33>=0.01,0.125,0))))))))),IF($G33="Dimensions",IF(OR($I33="",$J33=""),"",MIN(IF($I33>=87.5,1,IF($I33>=75,0.875,IF($I33>=62.5,0.75,IF($I33>=50,0.625,IF($I33>=37.5,0.5,IF($I33>=25,0.375,IF($I33>=12.5,0.25,IF($I33>=0.01,0.125,0)))))))),IF($J33>=2,1,IF($J33>=1.5,0.875,IF($J33>=1,0.75,IF($J33>=0.75,0.625,IF($J33>=0.5,0.5,IF($J33>=0.25,0.375,IF($J33>=0.125,0.25,IF($J33>=0.01,0.125,0)))))))))),""))) | L33: =IF($A33="","",IF(AND($C33>=2021,$C33<=2026,$E33<>"",$K33>0,LOWER($N33)="sim",LOWER($O33)="sim",OR(AND($F33="Exterior",OR($G33="WoS",$G33="Scopus")),AND($F33="Brasil",OR(AND(OR($G33="WoS",$G33="Scopus"),$H33>=50),$G33="Dimensions")))),$K33,"")) | N33: sim
A34: Caroline Leuchtenberger | B34: =IF($A34="","",IFERROR(VLOOKUP($A34,'Resumo por docente'!$A$8:$B$57,2,FALSE),"")) -> Biodiversidade, Saúde Ambiental e Conservação | C34: 2022 | D34: First report of myiasis caused by Cochliomyia hominivorax in free-ranging giant otter (Pteronura brasiliensis) | E34: https://doi.org/10.1590/s1984-29612022058 | K34: =IF($A34="","",IF(OR($G34="WoS",$G34="Scopus"),IF($H34="","",IF($H34>=87.5,1,IF($H34>=75,0.875,IF($H34>=62.5,0.75,IF($H34>=50,0.625,IF($H34>=37.5,0.5,IF($H34>=25,0.375,IF($H34>=12.5,0.25,IF($H34>=0.01,0.125,0))))))))),IF($G34="Dimensions",IF(OR($I34="",$J34=""),"",MIN(IF($I34>=87.5,1,IF($I34>=75,0.875,IF($I34>=62.5,0.75,IF($I34>=50,0.625,IF($I34>=37.5,0.5,IF($I34>=25,0.375,IF($I34>=12.5,0.25,IF($I34>=0.01,0.125,0)))))))),IF($J34>=2,1,IF($J34>=1.5,0.875,IF($J34>=1,0.75,IF($J34>=0.75,0.625,IF($J34>=0.5,0.5,IF($J34>=0.25,0.375,IF($J34>=0.125,0.25,IF($J34>=0.01,0.125,0)))))))))),""))) | L34: =IF($A34="","",IF(AND($C34>=2021,$C34<=2026,$E34<>"",$K34>0,LOWER($N34)="sim",LOWER($O34)="sim",OR(AND($F34="Exterior",OR($G34="WoS",$G34="Scopus")),AND($F34="Brasil",OR(AND(OR($G34="WoS",$G34="Scopus"),$H34>=50),$G34="Dimensions")))),$K34,"")) | N34: sim
A35: Caroline Leuchtenberger | B35: =IF($A35="","",IFERROR(VLOOKUP($A35,'Resumo por docente'!$A$8:$B$57,2,FALSE),"")) -> Biodiversidade, Saúde Ambiental e Conservação | C35: 2022 | D35: First report of myiasis caused by Cochliomyia hominivorax in free-ranging giant otter (Pteronura brasiliensis) | E35: https://doi.org/10.1590/s1984-29612022058 | K35: =IF($A35="","",IF(OR($G35="WoS",$G35="Scopus"),IF($H35="","",IF($H35>=87.5,1,IF($H35>=75,0.875,IF($H35>=62.5,0.75,IF($H35>=50,0.625,IF($H35>=37.5,0.5,IF($H35>=25,0.375,IF($H35>=12.5,0.25,IF($H35>=0.01,0.125,0))))))))),IF($G35="Dimensions",IF(OR($I35="",$J35=""),"",MIN(IF($I35>=87.5,1,IF($I35>=75,0.875,IF($I35>=62.5,0.75,IF($I35>=50,0.625,IF($I35>=37.5,0.5,IF($I35>=25,0.375,IF($I35>=12.5,0.25,IF($I35>=0.01,0.125,0)))))))),IF($J35>=2,1,IF($J35>=1.5,0.875,IF($J35>=1,0.75,IF($J35>=0.75,0.625,IF($J35>=0.5,0.5,IF($J35>=0.25,0.375,IF($J35>=0.125,0.25,IF($J35>=0.01,0.125,0)))))))))),""))) | L35: =IF($A35="","",IF(AND($C35>=2021,$C35<=2026,$E35<>"",$K35>0,LOWER($N35)="sim",LOWER($O35)="sim",OR(AND($F35="Exterior",OR($G35="WoS",$G35="Scopus")),AND($F35="Brasil",OR(AND(OR($G35="WoS",$G35="Scopus"),$H35>=50),$G35="Dimensions")))),$K35,"")) | N35: sim
A36: Cleudson JosÃ© Michelon | B36: =IF($A36="","",IFERROR(VLOOKUP($A36,'Resumo por docente'!$A$8:$B$57,2,FALSE),"")) | C36: 2026 | D36: Control of Meloidogyne javanica with aqueous extract of Trichilia claussenii | E36: https://doi.org/10.5902/2179460x89957 | K36: =IF($A36="","",IF(OR($G36="WoS",$G36="Scopus"),IF($H36="","",IF($H36>=87.5,1,IF($H36>=75,0.875,IF($H36>=62.5,0.75,IF($H36>=50,0.625,IF($H36>=37.5,0.5,IF($H36>=25,0.375,IF($H36>=12.5,0.25,IF($H36>=0.01,0.125,0))))))))),IF($G36="Dimensions",IF(OR($I36="",$J36=""),"",MIN(IF($I36>=87.5,1,IF($I36>=75,0.875,IF($I36>=62.5,0.75,IF($I36>=50,0.625,IF($I36>=37.5,0.5,IF($I36>=25,0.375,IF($I36>=12.5,0.25,IF($I36>=0.01,0.125,0)))))))),IF($J36>=2,1,IF($J36>=1.5,0.875,IF($J36>=1,0.75,IF($J36>=0.75,0.625,IF($J36>=0.5,0.5,IF($J36>=0.25,0.375,IF($J36>=0.125,0.25,IF($J36>=0.01,0.125,0)))))))))),""))) | L36: =IF($A36="","",IF(AND($C36>=2021,$C36<=2026,$E36<>"",$K36>0,LOWER($N36)="sim",LOWER($O36)="sim",OR(AND($F36="Exterior",OR($G36="WoS",$G36="Scopus")),AND($F36="Brasil",OR(AND(OR($G36="WoS",$G36="Scopus"),$H36>=50),$G36="Dimensions")))),$K36,"")) | N36: sim
A37: Cleudson JosÃ© Michelon | B37: =IF($A37="","",IFERROR(VLOOKUP($A37,'Resumo por docente'!$A$8:$B$57,2,FALSE),"")) | C37: 2025 | D37: Tabaco em sistema de cultivo mÃ­nimo: influÃªncia das plantas de cobertura nas propriedades fÃ­sicas do solo e produtividade | E37: https://doi.org/10.55905/rdelosv18.n69-022 | K37: =IF($A37="","",IF(OR($G37="WoS",$G37="Scopus"),IF($H37="","",IF($H37>=87.5,1,IF($H37>=75,0.875,IF($H37>=62.5,0.75,IF($H37>=50,0.625,IF($H37>=37.5,0.5,IF($H37>=25,0.375,IF($H37>=12.5,0.25,IF($H37>=0.01,0.125,0))))))))),IF($G37="Dimensions",IF(OR($I37="",$J37=""),"",MIN(IF($I37>=87.5,1,IF($I37>=75,0.875,IF($I37>=62.5,0.75,IF($I37>=50,0.625,IF($I37>=37.5,0.5,IF($I37>=25,0.375,IF($I37>=12.5,0.25,IF($I37>=0.01,0.125,0)))))))),IF($J37>=2,1,IF($J37>=1.5,0.875,IF($J37>=1,0.75,IF($J37>=0.75,0.625,IF($J37>=0.5,0.5,IF($J37>=0.25,0.375,IF($J37>=0.125,0.25,IF($J37>=0.01,0.125,0)))))))))),""))) | L37: =IF($A37="","",IF(AND($C37>=2021,$C37<=2026,$E37<>"",$K37>0,LOWER($N37)="sim",LOWER($O37)="sim",OR(AND($F37="Exterior",OR($G37="WoS",$G37="Scopus")),AND($F37="Brasil",OR(AND(OR($G37="WoS",$G37="Scopus"),$H37>=50),$G37="Dimensions")))),$K37,"")) | N37: sim
A38: Cleudson JosÃ© Michelon | B38: =IF($A38="","",IFERROR(VLOOKUP($A38,'Resumo por docente'!$A$8:$B$57,2,FALSE),"")) | C38: 2025 | D38: Cover crops as a vehicle for soil application of bio-inputs based on Azospirillum brasilense and Bacillus amyloliquefaciens | E38: https://doi.org/10.1590/1519-6984.299282 | K38: =IF($A38="","",IF(OR($G38="WoS",$G38="Scopus"),IF($H38="","",IF($H38>=87.5,1,IF($H38>=75,0.875,IF($H38>=62.5,0.75,IF($H38>=50,0.625,IF($H38>=37.5,0.5,IF($H38>=25,0.375,IF($H38>=12.5,0.25,IF($H38>=0.01,0.125,0))))))))),IF($G38="Dimensions",IF(OR($I38="",$J38=""),"",MIN(IF($I38>=87.5,1,IF($I38>=75,0.875,IF($I38>=62.5,0.75,IF($I38>=50,0.625,IF($I38>=37.5,0.5,IF($I38>=25,0.375,IF($I38>=12.5,0.25,IF($I38>=0.01,0.125,0)))))))),IF($J38>=2,1,IF($J38>=1.5,0.875,IF($J38>=1,0.75,IF($J38>=0.75,0.625,IF($J38>=0.5,0.5,IF($J38>=0.25,0.375,IF($J38>=0.125,0.25,IF($J38>=0.01,0.125,0)))))))))),""))) | L38: =IF($A38="","",IF(AND($C38>=2021,$C38<=2026,$E38<>"",$K38>0,LOWER($N38)="sim",LOWER($O38)="sim",OR(AND($F38="Exterior",OR($G38="WoS",$G38="Scopus")),AND($F38="Brasil",OR(AND(OR($G38="WoS",$G38="Scopus"),$H38>=50),$G38="Dimensions")))),$K38,"")) | N38: sim
A39: Cleudson JosÃ© Michelon | B39: =IF($A39="","",IFERROR(VLOOKUP($A39,'Resumo por docente'!$A$8:$B$57,2,FALSE),"")) | C39: 2023 | D39: PHYSICAL ATTRIBUTES OF SOIL AND WHEAT PRODUCTIVITY AS A FUNCTION OF COVERING PLANTS AND MECHANICAL CHISELING | E39: https://doi.org/10.5747/ca.2023.v19.h534 | K39: =IF($A39="","",IF(OR($G39="WoS",$G39="Scopus"),IF($H39="","",IF($H39>=87.5,1,IF($H39>=75,0.875,IF($H39>=62.5,0.75,IF($H39>=50,0.625,IF($H39>=37.5,0.5,IF($H39>=25,0.375,IF($H39>=12.5,0.25,IF($H39>=0.01,0.125,0))))))))),IF($G39="Dimensions",IF(OR($I39="",$J39=""),"",MIN(IF($I39>=87.5,1,IF($I39>=75,0.875,IF($I39>=62.5,0.75,IF($I39>=50,0.625,IF($I39>=37.5,0.5,IF($I39>=25,0.375,IF($I39>=12.5,0.25,IF($I39>=0.01,0.125,0)))))))),IF($J39>=2,1,IF($J39>=1.5,0.875,IF($J39>=1,0.75,IF($J39>=0.75,0.625,IF($J39>=0.5,0.5,IF($J39>=0.25,0.375,IF($J39>=0.125,0.25,IF($J39>=0.01,0.125,0)))))))))),""))) | L39: =IF($A39="","",IF(AND($C39>=2021,$C39<=2026,$E39<>"",$K39>0,LOWER($N39)="sim",LOWER($O39)="sim",OR(AND($F39="Exterior",OR($G39="WoS",$G39="Scopus")),AND($F39="Brasil",OR(AND(OR($G39="WoS",$G39="Scopus"),$H39>=50),$G39="Dimensions")))),$K39,"")) | N39: sim
A40: Cleudson JosÃ© Michelon | B40: =IF($A40="","",IFERROR(VLOOKUP($A40,'Resumo por docente'!$A$8:$B$57,2,FALSE),"")) | C40: 2022 | D40: GerminaÃ§Ã£o de sementes de azevÃ©m submetidas a diferentes Ã©pocas de dessecaÃ§Ã£o prÃ©-colheita | K40: =IF($A40="","",IF(OR($G40="WoS",$G40="Scopus"),IF($H40="","",IF($H40>=87.5,1,IF($H40>=75,0.875,IF($H40>=62.5,0.75,IF($H40>=50,0.625,IF($H40>=37.5,0.5,IF($H40>=25,0.375,IF($H40>=12.5,0.25,IF($H40>=0.01,0.125,0))))))))),IF($G40="Dimensions",IF(OR($I40="",$J40=""),"",MIN(IF($I40>=87.5,1,IF($I40>=75,0.875,IF($I40>=62.5,0.75,IF($I40>=50,0.625,IF($I40>=37.5,0.5,IF($I40>=25,0.375,IF($I40>=12.5,0.25,IF($I40>=0.01,0.125,0)))))))),IF($J40>=2,1,IF($J40>=1.5,0.875,IF($J40>=1,0.75,IF($J40>=0.75,0.625,IF($J40>=0.5,0.5,IF($J40>=0.25,0.375,IF($J40>=0.125,0.25,IF($J40>=0.01,0.125,0)))))))))),""))) | L40: =IF($A40="","",IF(AND($C40>=2021,$C40<=2026,$E40<>"",$K40>0,LOWER($N40)="sim",LOWER($O40)="sim",OR(AND($F40="Exterior",OR($G40="WoS",$G40="Scopus")),AND($F40="Brasil",OR(AND(OR($G40="WoS",$G40="Scopus"),$H40>=50),$G40="Dimensions")))),$K40,"")) | N40: sim
A41: Emanuele Junges | B41: =IF($A41="","",IFERROR(VLOOKUP($A41,'Resumo por docente'!$A$8:$B$57,2,FALSE),"")) -> Inovação, Biotecnologia e Sustentabilidade Produtiva | C41: 2026 | D41: First Report of Meloidogyne javanica Infecting Dietes bicolor in Brazil | E41: https://doi.org/10.1111/jph.70265 | K41: =IF($A41="","",IF(OR($G41="WoS",$G41="Scopus"),IF($H41="","",IF($H41>=87.5,1,IF($H41>=75,0.875,IF($H41>=62.5,0.75,IF($H41>=50,0.625,IF($H41>=37.5,0.5,IF($H41>=25,0.375,IF($H41>=12.5,0.25,IF($H41>=0.01,0.125,0))))))))),IF($G41="Dimensions",IF(OR($I41="",$J41=""),"",MIN(IF($I41>=87.5,1,IF($I41>=75,0.875,IF($I41>=62.5,0.75,IF($I41>=50,0.625,IF($I41>=37.5,0.5,IF($I41>=25,0.375,IF($I41>=12.5,0.25,IF($I41>=0.01,0.125,0)))))))),IF($J41>=2,1,IF($J41>=1.5,0.875,IF($J41>=1,0.75,IF($J41>=0.75,0.625,IF($J41>=0.5,0.5,IF($J41>=0.25,0.375,IF($J41>=0.125,0.25,IF($J41>=0.01,0.125,0)))))))))),""))) | L41: =IF($A41="","",IF(AND($C41>=2021,$C41<=2026,$E41<>"",$K41>0,LOWER($N41)="sim",LOWER($O41)="sim",OR(AND($F41="Exterior",OR($G41="WoS",$G41="Scopus")),AND($F41="Brasil",OR(AND(OR($G41="WoS",$G41="Scopus"),$H41>=50),$G41="Dimensions")))),$K41,"")) | N41: sim
A42: Emanuele Junges | B42: =IF($A42="","",IFERROR(VLOOKUP($A42,'Resumo por docente'!$A$8:$B$57,2,FALSE),"")) -> Inovação, Biotecnologia e Sustentabilidade Produtiva | C42: 2026 | D42: Control of Meloidogyne javanica with Aqueous Extract of Trichilia claussenii | E42: https://doi.org/10.5902/2179460x89957 | K42: =IF($A42="","",IF(OR($G42="WoS",$G42="Scopus"),IF($H42="","",IF($H42>=87.5,1,IF($H42>=75,0.875,IF($H42>=62.5,0.75,IF($H42>=50,0.625,IF($H42>=37.5,0.5,IF($H42>=25,0.375,IF($H42>=12.5,0.25,IF($H42>=0.01,0.125,0))))))))),IF($G42="Dimensions",IF(OR($I42="",$J42=""),"",MIN(IF($I42>=87.5,1,IF($I42>=75,0.875,IF($I42>=62.5,0.75,IF($I42>=50,0.625,IF($I42>=37.5,0.5,IF($I42>=25,0.375,IF($I42>=12.5,0.25,IF($I42>=0.01,0.125,0)))))))),IF($J42>=2,1,IF($J42>=1.5,0.875,IF($J42>=1,0.75,IF($J42>=0.75,0.625,IF($J42>=0.5,0.5,IF($J42>=0.25,0.375,IF($J42>=0.125,0.25,IF($J42>=0.01,0.125,0)))))))))),""))) | L42: =IF($A42="","",IF(AND($C42>=2021,$C42<=2026,$E42<>"",$K42>0,LOWER($N42)="sim",LOWER($O42)="sim",OR(AND($F42="Exterior",OR($G42="WoS",$G42="Scopus")),AND($F42="Brasil",OR(AND(OR($G42="WoS",$G42="Scopus"),$H42>=50),$G42="Dimensions")))),$K42,"")) | N42: sim
A43: Emanuele Junges | B43: =IF($A43="","",IFERROR(VLOOKUP($A43,'Resumo por docente'!$A$8:$B$57,2,FALSE),"")) -> Inovação, Biotecnologia e Sustentabilidade Produtiva | C43: 2025 | D43: Tabaco em sistema de cultivo mÃ­nimo: influÃªncia das plantas de cobertura nas propriedades fÃ­sicas do solo e produtividade | E43: https://doi.org/10.55905/rdelosv18.n69-022 | K43: =IF($A43="","",IF(OR($G43="WoS",$G43="Scopus"),IF($H43="","",IF($H43>=87.5,1,IF($H43>=75,0.875,IF($H43>=62.5,0.75,IF($H43>=50,0.625,IF($H43>=37.5,0.5,IF($H43>=25,0.375,IF($H43>=12.5,0.25,IF($H43>=0.01,0.125,0))))))))),IF($G43="Dimensions",IF(OR($I43="",$J43=""),"",MIN(IF($I43>=87.5,1,IF($I43>=75,0.875,IF($I43>=62.5,0.75,IF($I43>=50,0.625,IF($I43>=37.5,0.5,IF($I43>=25,0.375,IF($I43>=12.5,0.25,IF($I43>=0.01,0.125,0)))))))),IF($J43>=2,1,IF($J43>=1.5,0.875,IF($J43>=1,0.75,IF($J43>=0.75,0.625,IF($J43>=0.5,0.5,IF($J43>=0.25,0.375,IF($J43>=0.125,0.25,IF($J43>=0.01,0.125,0)))))))))),""))) | L43: =IF($A43="","",IF(AND($C43>=2021,$C43<=2026,$E43<>"",$K43>0,LOWER($N43)="sim",LOWER($O43)="sim",OR(AND($F43="Exterior",OR($G43="WoS",$G43="Scopus")),AND($F43="Brasil",OR(AND(OR($G43="WoS",$G43="Scopus"),$H43>=50),$G43="Dimensions")))),$K43,"")) | N43: sim
A44: Emanuele Junges | B44: =IF($A44="","",IFERROR(VLOOKUP($A44,'Resumo por docente'!$A$8:$B$57,2,FALSE),"")) -> Inovação, Biotecnologia e Sustentabilidade Produtiva | C44: 2025 | D44: Cover crops as a vehicle for soil application of bio-inputs based on Azospirillum brasilense and Bacillus amyloliquefaciens | E44: https://doi.org/10.1590/1519-6984.299282 | K44: =IF($A44="","",IF(OR($G44="WoS",$G44="Scopus"),IF($H44="","",IF($H44>=87.5,1,IF($H44>=75,0.875,IF($H44>=62.5,0.75,IF($H44>=50,0.625,IF($H44>=37.5,0.5,IF($H44>=25,0.375,IF($H44>=12.5,0.25,IF($H44>=0.01,0.125,0))))))))),IF($G44="Dimensions",IF(OR($I44="",$J44=""),"",MIN(IF($I44>=87.5,1,IF($I44>=75,0.875,IF($I44>=62.5,0.75,IF($I44>=50,0.625,IF($I44>=37.5,0.5,IF($I44>=25,0.375,IF($I44>=12.5,0.25,IF($I44>=0.01,0.125,0)))))))),IF($J44>=2,1,IF($J44>=1.5,0.875,IF($J44>=1,0.75,IF($J44>=0.75,0.625,IF($J44>=0.5,0.5,IF($J44>=0.25,0.375,IF($J44>=0.125,0.25,IF($J44>=0.01,0.125,0)))))))))),""))) | L44: =IF($A44="","",IF(AND($C44>=2021,$C44<=2026,$E44<>"",$K44>0,LOWER($N44)="sim",LOWER($O44)="sim",OR(AND($F44="Exterior",OR($G44="WoS",$G44="Scopus")),AND($F44="Brasil",OR(AND(OR($G44="WoS",$G44="Scopus"),$H44>=50),$G44="Dimensions")))),$K44,"")) | N44: sim
A45: Emanuele Junges | B45: =IF($A45="","",IFERROR(VLOOKUP($A45,'Resumo por docente'!$A$8:$B$57,2,FALSE),"")) -> Inovação, Biotecnologia e Sustentabilidade Produtiva | C45: 2023 | D45: PHYSICAL ATTRIBUTES OF SOIL AND WHEAT PRODUCTIVITY AS A FUNCTION OF COVERING PLANTS AND MECHANICAL CHISELING | E45: https://doi.org/10.5747/ca.2023.v19.h534 | K45: =IF($A45="","",IF(OR($G45="WoS",$G45="Scopus"),IF($H45="","",IF($H45>=87.5,1,IF($H45>=75,0.875,IF($H45>=62.5,0.75,IF($H45>=50,0.625,IF($H45>=37.5,0.5,IF($H45>=25,0.375,IF($H45>=12.5,0.25,IF($H45>=0.01,0.125,0))))))))),IF($G45="Dimensions",IF(OR($I45="",$J45=""),"",MIN(IF($I45>=87.5,1,IF($I45>=75,0.875,IF($I45>=62.5,0.75,IF($I45>=50,0.625,IF($I45>=37.5,0.5,IF($I45>=25,0.375,IF($I45>=12.5,0.25,IF($I45>=0.01,0.125,0)))))))),IF($J45>=2,1,IF($J45>=1.5,0.875,IF($J45>=1,0.75,IF($J45>=0.75,0.625,IF($J45>=0.5,0.5,IF($J45>=0.25,0.375,IF($J45>=0.125,0.25,IF($J45>=0.01,0.125,0)))))))))),""))) | L45: =IF($A45="","",IF(AND($C45>=2021,$C45<=2026,$E45<>"",$K45>0,LOWER($N45)="sim",LOWER($O45)="sim",OR(AND($F45="Exterior",OR($G45="WoS",$G45="Scopus")),AND($F45="Brasil",OR(AND(OR($G45="WoS",$G45="Scopus"),$H45>=50),$G45="Dimensions")))),$K45,"")) | N45: sim
A46: Emanuele Junges | B46: =IF($A46="","",IFERROR(VLOOKUP($A46,'Resumo por docente'!$A$8:$B$57,2,FALSE),"")) -> Inovação, Biotecnologia e Sustentabilidade Produtiva | C46: 2022 | D46: GerminaÃ§Ã£o de sementes de azevÃ©m submetidas a diferentes Ã©pocas de dessecaÃ§Ã£o prÃ©-colheita | K46: =IF($A46="","",IF(OR($G46="WoS",$G46="Scopus"),IF($H46="","",IF($H46>=87.5,1,IF($H46>=75,0.875,IF($H46>=62.5,0.75,IF($H46>=50,0.625,IF($H46>=37.5,0.5,IF($H46>=25,0.375,IF($H46>=12.5,0.25,IF($H46>=0.01,0.125,0))))))))),IF($G46="Dimensions",IF(OR($I46="",$J46=""),"",MIN(IF($I46>=87.5,1,IF($I46>=75,0.875,IF($I46>=62.5,0.75,IF($I46>=50,0.625,IF($I46>=37.5,0.5,IF($I46>=25,0.375,IF($I46>=12.5,0.25,IF($I46>=0.01,0.125,0)))))))),IF($J46>=2,1,IF($J46>=1.5,0.875,IF($J46>=1,0.75,IF($J46>=0.75,0.625,IF($J46>=0.5,0.5,IF($J46>=0.25,0.375,IF($J46>=0.125,0.25,IF($J46>=0.01,0.125,0)))))))))),""))) | L46: =IF($A46="","",IF(AND($C46>=2021,$C46<=2026,$E46<>"",$K46>0,LOWER($N46)="sim",LOWER($O46)="sim",OR(AND($F46="Exterior",OR($G46="WoS",$G46="Scopus")),AND($F46="Brasil",OR(AND(OR($G46="WoS",$G46="Scopus"),$H46>=50),$G46="Dimensions")))),$K46,"")) | N46: sim
A47: Éverton Lutz | B47: =IF($A47="","",IFERROR(VLOOKUP($A47,'Resumo por docente'!$A$8:$B$57,2,FALSE),"")) | C47: 2023 | D47: Effects of the storage temperature and time of corn from the center and extremities of corncob on quality parameters | E47: https://doi.org/10.1016/j.jcs.2023.103645 | K47: =IF($A47="","",IF(OR($G47="WoS",$G47="Scopus"),IF($H47="","",IF($H47>=87.5,1,IF($H47>=75,0.875,IF($H47>=62.5,0.75,IF($H47>=50,0.625,IF($H47>=37.5,0.5,IF($H47>=25,0.375,IF($H47>=12.5,0.25,IF($H47>=0.01,0.125,0))))))))),IF($G47="Dimensions",IF(OR($I47="",$J47=""),"",MIN(IF($I47>=87.5,1,IF($I47>=75,0.875,IF($I47>=62.5,0.75,IF($I47>=50,0.625,IF($I47>=37.5,0.5,IF($I47>=25,0.375,IF($I47>=12.5,0.25,IF($I47>=0.01,0.125,0)))))))),IF($J47>=2,1,IF($J47>=1.5,0.875,IF($J47>=1,0.75,IF($J47>=0.75,0.625,IF($J47>=0.5,0.5,IF($J47>=0.25,0.375,IF($J47>=0.125,0.25,IF($J47>=0.01,0.125,0)))))))))),""))) | L47: =IF($A47="","",IF(AND($C47>=2021,$C47<=2026,$E47<>"",$K47>0,LOWER($N47)="sim",LOWER($O47)="sim",OR(AND($F47="Exterior",OR($G47="WoS",$G47="Scopus")),AND($F47="Brasil",OR(AND(OR($G47="WoS",$G47="Scopus"),$H47>=50),$G47="Dimensions")))),$K47,"")) | N47: sim
A48: Éverton Lutz | B48: =IF($A48="","",IFERROR(VLOOKUP($A48,'Resumo por docente'!$A$8:$B$57,2,FALSE),"")) | C48: 2023 | D48: Equilibrium Moisture Content and Dioxide Carbon Monitoring in Real-Time to Predict the Quality of Corn Grain Stored in Silo Bags using Artificial Neural Networks | E48: https://doi.org/10.1007/s12161-023-02497-2 | K48: =IF($A48="","",IF(OR($G48="WoS",$G48="Scopus"),IF($H48="","",IF($H48>=87.5,1,IF($H48>=75,0.875,IF($H48>=62.5,0.75,IF($H48>=50,0.625,IF($H48>=37.5,0.5,IF($H48>=25,0.375,IF($H48>=12.5,0.25,IF($H48>=0.01,0.125,0))))))))),IF($G48="Dimensions",IF(OR($I48="",$J48=""),"",MIN(IF($I48>=87.5,1,IF($I48>=75,0.875,IF($I48>=62.5,0.75,IF($I48>=50,0.625,IF($I48>=37.5,0.5,IF($I48>=25,0.375,IF($I48>=12.5,0.25,IF($I48>=0.01,0.125,0)))))))),IF($J48>=2,1,IF($J48>=1.5,0.875,IF($J48>=1,0.75,IF($J48>=0.75,0.625,IF($J48>=0.5,0.5,IF($J48>=0.25,0.375,IF($J48>=0.125,0.25,IF($J48>=0.01,0.125,0)))))))))),""))) | L48: =IF($A48="","",IF(AND($C48>=2021,$C48<=2026,$E48<>"",$K48>0,LOWER($N48)="sim",LOWER($O48)="sim",OR(AND($F48="Exterior",OR($G48="WoS",$G48="Scopus")),AND($F48="Brasil",OR(AND(OR($G48="WoS",$G48="Scopus"),$H48>=50),$G48="Dimensions")))),$K48,"")) | N48: sim
A49: Éverton Lutz | B49: =IF($A49="","",IFERROR(VLOOKUP($A49,'Resumo por docente'!$A$8:$B$57,2,FALSE),"")) | C49: 2022 | D49: Applications of new technologies for monitoring and predicting grains quality stored: Sensors, Internet of Things, and Artificial Intelligence | E49: https://doi.org/10.1016/j.measurement.2021.110609 | K49: =IF($A49="","",IF(OR($G49="WoS",$G49="Scopus"),IF($H49="","",IF($H49>=87.5,1,IF($H49>=75,0.875,IF($H49>=62.5,0.75,IF($H49>=50,0.625,IF($H49>=37.5,0.5,IF($H49>=25,0.375,IF($H49>=12.5,0.25,IF($H49>=0.01,0.125,0))))))))),IF($G49="Dimensions",IF(OR($I49="",$J49=""),"",MIN(IF($I49>=87.5,1,IF($I49>=75,0.875,IF($I49>=62.5,0.75,IF($I49>=50,0.625,IF($I49>=37.5,0.5,IF($I49>=25,0.375,IF($I49>=12.5,0.25,IF($I49>=0.01,0.125,0)))))))),IF($J49>=2,1,IF($J49>=1.5,0.875,IF($J49>=1,0.75,IF($J49>=0.75,0.625,IF($J49>=0.5,0.5,IF($J49>=0.25,0.375,IF($J49>=0.125,0.25,IF($J49>=0.01,0.125,0)))))))))),""))) | L49: =IF($A49="","",IF(AND($C49>=2021,$C49<=2026,$E49<>"",$K49>0,LOWER($N49)="sim",LOWER($O49)="sim",OR(AND($F49="Exterior",OR($G49="WoS",$G49="Scopus")),AND($F49="Brasil",OR(AND(OR($G49="WoS",$G49="Scopus"),$H49>=50),$G49="Dimensions")))),$K49,"")) | N49: sim
A50: Éverton Lutz | B50: =IF($A50="","",IFERROR(VLOOKUP($A50,'Resumo por docente'!$A$8:$B$57,2,FALSE),"")) | C50: 2022 | D50: Real-time equilibrium moisture content monitoring to predict grain quality of corn stored in silo and raffia bags | E50: https://doi.org/10.1111/jfpe.14076 | K50: =IF($A50="","",IF(OR($G50="WoS",$G50="Scopus"),IF($H50="","",IF($H50>=87.5,1,IF($H50>=75,0.875,IF($H50>=62.5,0.75,IF($H50>=50,0.625,IF($H50>=37.5,0.5,IF($H50>=25,0.375,IF($H50>=12.5,0.25,IF($H50>=0.01,0.125,0))))))))),IF($G50="Dimensions",IF(OR($I50="",$J50=""),"",MIN(IF($I50>=87.5,1,IF($I50>=75,0.875,IF($I50>=62.5,0.75,IF($I50>=50,0.625,IF($I50>=37.5,0.5,IF($I50>=25,0.375,IF($I50>=12.5,0.25,IF($I50>=0.01,0.125,0)))))))),IF($J50>=2,1,IF($J50>=1.5,0.875,IF($J50>=1,0.75,IF($J50>=0.75,0.625,IF($J50>=0.5,0.5,IF($J50>=0.25,0.375,IF($J50>=0.125,0.25,IF($J50>=0.01,0.125,0)))))))))),""))) | L50: =IF($A50="","",IF(AND($C50>=2021,$C50<=2026,$E50<>"",$K50>0,LOWER($N50)="sim",LOWER($O50)="sim",OR(AND($F50="Exterior",OR($G50="WoS",$G50="Scopus")),AND($F50="Brasil",OR(AND(OR($G50="WoS",$G50="Scopus"),$H50>=50),$G50="Dimensions")))),$K50,"")) | N50: sim
A51: Éverton Lutz | B51: =IF($A51="","",IFERROR(VLOOKUP($A51,'Resumo por docente'!$A$8:$B$57,2,FALSE),"")) | C51: 2022 | D51: Prototype wireless sensor network and Internet of Things platform for real-time monitoring of intergranular equilibrium moisture content and predict the quality corn stored in silos bags | E51: https://doi.org/10.1016/j.eswa.2022.118242 | K51: =IF($A51="","",IF(OR($G51="WoS",$G51="Scopus"),IF($H51="","",IF($H51>=87.5,1,IF($H51>=75,0.875,IF($H51>=62.5,0.75,IF($H51>=50,0.625,IF($H51>=37.5,0.5,IF($H51>=25,0.375,IF($H51>=12.5,0.25,IF($H51>=0.01,0.125,0))))))))),IF($G51="Dimensions",IF(OR($I51="",$J51=""),"",MIN(IF($I51>=87.5,1,IF($I51>=75,0.875,IF($I51>=62.5,0.75,IF($I51>=50,0.625,IF($I51>=37.5,0.5,IF($I51>=25,0.375,IF($I51>=12.5,0.25,IF($I51>=0.01,0.125,0)))))))),IF($J51>=2,1,IF($J51>=1.5,0.875,IF($J51>=1,0.75,IF($J51>=0.75,0.625,IF($J51>=0.5,0.5,IF($J51>=0.25,0.375,IF($J51>=0.125,0.25,IF($J51>=0.01,0.125,0)))))))))),""))) | L51: =IF($A51="","",IF(AND($C51>=2021,$C51<=2026,$E51<>"",$K51>0,LOWER($N51)="sim",LOWER($O51)="sim",OR(AND($F51="Exterior",OR($G51="WoS",$G51="Scopus")),AND($F51="Brasil",OR(AND(OR($G51="WoS",$G51="Scopus"),$H51>=50),$G51="Dimensions")))),$K51,"")) | N51: sim
A52: Éverton Lutz | B52: =IF($A52="","",IFERROR(VLOOKUP($A52,'Resumo por docente'!$A$8:$B$57,2,FALSE),"")) | C52: 2022 | D52: Nondestructive technology for real-time monitoring and prediction of soybean quality using Machine Learning for a bulk transport simulation | E52: https://doi.org/10.1109/jsen.2022.3226168 | K52: =IF($A52="","",IF(OR($G52="WoS",$G52="Scopus"),IF($H52="","",IF($H52>=87.5,1,IF($H52>=75,0.875,IF($H52>=62.5,0.75,IF($H52>=50,0.625,IF($H52>=37.5,0.5,IF($H52>=25,0.375,IF($H52>=12.5,0.25,IF($H52>=0.01,0.125,0))))))))),IF($G52="Dimensions",IF(OR($I52="",$J52=""),"",MIN(IF($I52>=87.5,1,IF($I52>=75,0.875,IF($I52>=62.5,0.75,IF($I52>=50,0.625,IF($I52>=37.5,0.5,IF($I52>=25,0.375,IF($I52>=12.5,0.25,IF($I52>=0.01,0.125,0)))))))),IF($J52>=2,1,IF($J52>=1.5,0.875,IF($J52>=1,0.75,IF($J52>=0.75,0.625,IF($J52>=0.5,0.5,IF($J52>=0.25,0.375,IF($J52>=0.125,0.25,IF($J52>=0.01,0.125,0)))))))))),""))) | L52: =IF($A52="","",IF(AND($C52>=2021,$C52<=2026,$E52<>"",$K52>0,LOWER($N52)="sim",LOWER($O52)="sim",OR(AND($F52="Exterior",OR($G52="WoS",$G52="Scopus")),AND($F52="Brasil",OR(AND(OR($G52="WoS",$G52="Scopus"),$H52>=50),$G52="Dimensions")))),$K52,"")) | N52: sim
A53: FELIPE KETZER | B53: =IF($A53="","",IFERROR(VLOOKUP($A53,'Resumo por docente'!$A$8:$B$57,2,FALSE),"")) -> Inovação, Biotecnologia e Sustentabilidade Produtiva | C53: 2025 | D53: Fe3+ and Mn2+ Removal from Water Solutions by Clinoptilolite Zeolites as a Potential Treatment for Groundwater Wells | E53: https://doi.org/10.3390/pr13041060 | K53: =IF($A53="","",IF(OR($G53="WoS",$G53="Scopus"),IF($H53="","",IF($H53>=87.5,1,IF($H53>=75,0.875,IF($H53>=62.5,0.75,IF($H53>=50,0.625,IF($H53>=37.5,0.5,IF($H53>=25,0.375,IF($H53>=12.5,0.25,IF($H53>=0.01,0.125,0))))))))),IF($G53="Dimensions",IF(OR($I53="",$J53=""),"",MIN(IF($I53>=87.5,1,IF($I53>=75,0.875,IF($I53>=62.5,0.75,IF($I53>=50,0.625,IF($I53>=37.5,0.5,IF($I53>=25,0.375,IF($I53>=12.5,0.25,IF($I53>=0.01,0.125,0)))))))),IF($J53>=2,1,IF($J53>=1.5,0.875,IF($J53>=1,0.75,IF($J53>=0.75,0.625,IF($J53>=0.5,0.5,IF($J53>=0.25,0.375,IF($J53>=0.125,0.25,IF($J53>=0.01,0.125,0)))))))))),""))) | L53: =IF($A53="","",IF(AND($C53>=2021,$C53<=2026,$E53<>"",$K53>0,LOWER($N53)="sim",LOWER($O53)="sim",OR(AND($F53="Exterior",OR($G53="WoS",$G53="Scopus")),AND($F53="Brasil",OR(AND(OR($G53="WoS",$G53="Scopus"),$H53>=50),$G53="Dimensions")))),$K53,"")) | N53: sim
A54: FELIPE KETZER | B54: =IF($A54="","",IFERROR(VLOOKUP($A54,'Resumo por docente'!$A$8:$B$57,2,FALSE),"")) -> Inovação, Biotecnologia e Sustentabilidade Produtiva | C54: 2024 | D54: Valorization of winemaking residues as biochar for removing Ni(II) from real industrial painting process effluent in a fixed-bed column | E54: https://doi.org/10.1007/s11356-024-32385-z | K54: =IF($A54="","",IF(OR($G54="WoS",$G54="Scopus"),IF($H54="","",IF($H54>=87.5,1,IF($H54>=75,0.875,IF($H54>=62.5,0.75,IF($H54>=50,0.625,IF($H54>=37.5,0.5,IF($H54>=25,0.375,IF($H54>=12.5,0.25,IF($H54>=0.01,0.125,0))))))))),IF($G54="Dimensions",IF(OR($I54="",$J54=""),"",MIN(IF($I54>=87.5,1,IF($I54>=75,0.875,IF($I54>=62.5,0.75,IF($I54>=50,0.625,IF($I54>=37.5,0.5,IF($I54>=25,0.375,IF($I54>=12.5,0.25,IF($I54>=0.01,0.125,0)))))))),IF($J54>=2,1,IF($J54>=1.5,0.875,IF($J54>=1,0.75,IF($J54>=0.75,0.625,IF($J54>=0.5,0.5,IF($J54>=0.25,0.375,IF($J54>=0.125,0.25,IF($J54>=0.01,0.125,0)))))))))),""))) | L54: =IF($A54="","",IF(AND($C54>=2021,$C54<=2026,$E54<>"",$K54>0,LOWER($N54)="sim",LOWER($O54)="sim",OR(AND($F54="Exterior",OR($G54="WoS",$G54="Scopus")),AND($F54="Brasil",OR(AND(OR($G54="WoS",$G54="Scopus"),$H54>=50),$G54="Dimensions")))),$K54,"")) | N54: sim
A55: FELIPE KETZER | B55: =IF($A55="","",IFERROR(VLOOKUP($A55,'Resumo por docente'!$A$8:$B$57,2,FALSE),"")) -> Inovação, Biotecnologia e Sustentabilidade Produtiva | C55: 2024 | D55: Adsorption of methane by modified-biochar aiming to improve the gaseous fuels storage/transport capacity: process evaluation and modeling | E55: https://doi.org/10.1007/s11356-024-34465-6 | K55: =IF($A55="","",IF(OR($G55="WoS",$G55="Scopus"),IF($H55="","",IF($H55>=87.5,1,IF($H55>=75,0.875,IF($H55>=62.5,0.75,IF($H55>=50,0.625,IF($H55>=37.5,0.5,IF($H55>=25,0.375,IF($H55>=12.5,0.25,IF($H55>=0.01,0.125,0))))))))),IF($G55="Dimensions",IF(OR($I55="",$J55=""),"",MIN(IF($I55>=87.5,1,IF($I55>=75,0.875,IF($I55>=62.5,0.75,IF($I55>=50,0.625,IF($I55>=37.5,0.5,IF($I55>=25,0.375,IF($I55>=12.5,0.25,IF($I55>=0.01,0.125,0)))))))),IF($J55>=2,1,IF($J55>=1.5,0.875,IF($J55>=1,0.75,IF($J55>=0.75,0.625,IF($J55>=0.5,0.5,IF($J55>=0.25,0.375,IF($J55>=0.125,0.25,IF($J55>=0.01,0.125,0)))))))))),""))) | L55: =IF($A55="","",IF(AND($C55>=2021,$C55<=2026,$E55<>"",$K55>0,LOWER($N55)="sim",LOWER($O55)="sim",OR(AND($F55="Exterior",OR($G55="WoS",$G55="Scopus")),AND($F55="Brasil",OR(AND(OR($G55="WoS",$G55="Scopus"),$H55>=50),$G55="Dimensions")))),$K55,"")) | N55: sim
A56: FELIPE KETZER | B56: =IF($A56="","",IFERROR(VLOOKUP($A56,'Resumo por docente'!$A$8:$B$57,2,FALSE),"")) -> Inovação, Biotecnologia e Sustentabilidade Produtiva | C56: 2024 | D56: Sustainability Index in the Yerba Mate Industry in Southern Brazil | E56: https://doi.org/10.1007/s12161-024-02732-4 | K56: =IF($A56="","",IF(OR($G56="WoS",$G56="Scopus"),IF($H56="","",IF($H56>=87.5,1,IF($H56>=75,0.875,IF($H56>=62.5,0.75,IF($H56>=50,0.625,IF($H56>=37.5,0.5,IF($H56>=25,0.375,IF($H56>=12.5,0.25,IF($H56>=0.01,0.125,0))))))))),IF($G56="Dimensions",IF(OR($I56="",$J56=""),"",MIN(IF($I56>=87.5,1,IF($I56>=75,0.875,IF($I56>=62.5,0.75,IF($I56>=50,0.625,IF($I56>=37.5,0.5,IF($I56>=25,0.375,IF($I56>=12.5,0.25,IF($I56>=0.01,0.125,0)))))))),IF($J56>=2,1,IF($J56>=1.5,0.875,IF($J56>=1,0.75,IF($J56>=0.75,0.625,IF($J56>=0.5,0.5,IF($J56>=0.25,0.375,IF($J56>=0.125,0.25,IF($J56>=0.01,0.125,0)))))))))),""))) | L56: =IF($A56="","",IF(AND($C56>=2021,$C56<=2026,$E56<>"",$K56>0,LOWER($N56)="sim",LOWER($O56)="sim",OR(AND($F56="Exterior",OR($G56="WoS",$G56="Scopus")),AND($F56="Brasil",OR(AND(OR($G56="WoS",$G56="Scopus"),$H56>=50),$G56="Dimensions")))),$K56,"")) | N56: sim
A57: FELIPE KETZER | B57: =IF($A57="","",IFERROR(VLOOKUP($A57,'Resumo por docente'!$A$8:$B$57,2,FALSE),"")) -> Inovação, Biotecnologia e Sustentabilidade Produtiva | C57: 2022 | D57: Polishing of painting process effluents through adsorption with biochar from winemaking residues | E57: https://doi.org/10.1007/s11356-022-20488-4 | K57: =IF($A57="","",IF(OR($G57="WoS",$G57="Scopus"),IF($H57="","",IF($H57>=87.5,1,IF($H57>=75,0.875,IF($H57>=62.5,0.75,IF($H57>=50,0.625,IF($H57>=37.5,0.5,IF($H57>=25,0.375,IF($H57>=12.5,0.25,IF($H57>=0.01,0.125,0))))))))),IF($G57="Dimensions",IF(OR($I57="",$J57=""),"",MIN(IF($I57>=87.5,1,IF($I57>=75,0.875,IF($I57>=62.5,0.75,IF($I57>=50,0.625,IF($I57>=37.5,0.5,IF($I57>=25,0.375,IF($I57>=12.5,0.25,IF($I57>=0.01,0.125,0)))))))),IF($J57>=2,1,IF($J57>=1.5,0.875,IF($J57>=1,0.75,IF($J57>=0.75,0.625,IF($J57>=0.5,0.5,IF($J57>=0.25,0.375,IF($J57>=0.125,0.25,IF($J57>=0.01,0.125,0)))))))))),""))) | L57: =IF($A57="","",IF(AND($C57>=2021,$C57<=2026,$E57<>"",$K57>0,LOWER($N57)="sim",LOWER($O57)="sim",OR(AND($F57="Exterior",OR($G57="WoS",$G57="Scopus")),AND($F57="Brasil",OR(AND(OR($G57="WoS",$G57="Scopus"),$H57>=50),$G57="Dimensions")))),$K57,"")) | N57: sim
A58: FELIPE KETZER | B58: =IF($A58="","",IFERROR(VLOOKUP($A58,'Resumo por docente'!$A$8:$B$57,2,FALSE),"")) -> Inovação, Biotecnologia e Sustentabilidade Produtiva | C58: 2022 | D58: Kinetic and Thermodynamic Study of Enzymatic Hydroesterification Mechanism to Fatty Acid Methyl Esters Synthesis | E58: https://doi.org/10.1016/j.biortech.2022.127335 | K58: =IF($A58="","",IF(OR($G58="WoS",$G58="Scopus"),IF($H58="","",IF($H58>=87.5,1,IF($H58>=75,0.875,IF($H58>=62.5,0.75,IF($H58>=50,0.625,IF($H58>=37.5,0.5,IF($H58>=25,0.375,IF($H58>=12.5,0.25,IF($H58>=0.01,0.125,0))))))))),IF($G58="Dimensions",IF(OR($I58="",$J58=""),"",MIN(IF($I58>=87.5,1,IF($I58>=75,0.875,IF($I58>=62.5,0.75,IF($I58>=50,0.625,IF($I58>=37.5,0.5,IF($I58>=25,0.375,IF($I58>=12.5,0.25,IF($I58>=0.01,0.125,0)))))))),IF($J58>=2,1,IF($J58>=1.5,0.875,IF($J58>=1,0.75,IF($J58>=0.75,0.625,IF($J58>=0.5,0.5,IF($J58>=0.25,0.375,IF($J58>=0.125,0.25,IF($J58>=0.01,0.125,0)))))))))),""))) | L58: =IF($A58="","",IF(AND($C58>=2021,$C58<=2026,$E58<>"",$K58>0,LOWER($N58)="sim",LOWER($O58)="sim",OR(AND($F58="Exterior",OR($G58="WoS",$G58="Scopus")),AND($F58="Brasil",OR(AND(OR($G58="WoS",$G58="Scopus"),$H58>=50),$G58="Dimensions")))),$K58,"")) | N58: sim
A59: FELIPE KETZER | B59: =IF($A59="","",IFERROR(VLOOKUP($A59,'Resumo por docente'!$A$8:$B$57,2,FALSE),"")) -> Inovação, Biotecnologia e Sustentabilidade Produtiva | C59: 2021 | D59: An assessment on kinetic modeling of esterification reaction from oleic acid and methyl acetate over USY zeolite. | E59: http://dx.doi.org/10.1016/j.micromeso.2021.110890 | F59: Exterior | G59: Scopus | K59: =IF($A59="","",IF(OR($G59="WoS",$G59="Scopus"),IF($H59="","",IF($H59>=87.5,1,IF($H59>=75,0.875,IF($H59>=62.5,0.75,IF($H59>=50,0.625,IF($H59>=37.5,0.5,IF($H59>=25,0.375,IF($H59>=12.5,0.25,IF($H59>=0.01,0.125,0))))))))),IF($G59="Dimensions",IF(OR($I59="",$J59=""),"",MIN(IF($I59>=87.5,1,IF($I59>=75,0.875,IF($I59>=62.5,0.75,IF($I59>=50,0.625,IF($I59>=37.5,0.5,IF($I59>=25,0.375,IF($I59>=12.5,0.25,IF($I59>=0.01,0.125,0)))))))),IF($J59>=2,1,IF($J59>=1.5,0.875,IF($J59>=1,0.75,IF($J59>=0.75,0.625,IF($J59>=0.5,0.5,IF($J59>=0.25,0.375,IF($J59>=0.125,0.25,IF($J59>=0.01,0.125,0)))))))))),""))) | L59: =IF($A59="","",IF(AND($C59>=2021,$C59<=2026,$E59<>"",$K59>0,LOWER($N59)="sim",LOWER($O59)="sim",OR(AND($F59="Exterior",OR($G59="WoS",$G59="Scopus")),AND($F59="Brasil",OR(AND(OR($G59="WoS",$G59="Scopus"),$H59>=50),$G59="Dimensions")))),$K59,""))
A60: FELIPE KETZER | B60: =IF($A60="","",IFERROR(VLOOKUP($A60,'Resumo por docente'!$A$8:$B$57,2,FALSE),"")) -> Inovação, Biotecnologia e Sustentabilidade Produtiva | C60: 2021 | D60: Aprendizagem significativa: transformando a sala de aula em laboratório para o ensino de ciências. | E60: http://dx.doi.org/10.36661/2595-4520.2021v4i2.12066 | K60: =IF($A60="","",IF(OR($G60="WoS",$G60="Scopus"),IF($H60="","",IF($H60>=87.5,1,IF($H60>=75,0.875,IF($H60>=62.5,0.75,IF($H60>=50,0.625,IF($H60>=37.5,0.5,IF($H60>=25,0.375,IF($H60>=12.5,0.25,IF($H60>=0.01,0.125,0))))))))),IF($G60="Dimensions",IF(OR($I60="",$J60=""),"",MIN(IF($I60>=87.5,1,IF($I60>=75,0.875,IF($I60>=62.5,0.75,IF($I60>=50,0.625,IF($I60>=37.5,0.5,IF($I60>=25,0.375,IF($I60>=12.5,0.25,IF($I60>=0.01,0.125,0)))))))),IF($J60>=2,1,IF($J60>=1.5,0.875,IF($J60>=1,0.75,IF($J60>=0.75,0.625,IF($J60>=0.5,0.5,IF($J60>=0.25,0.375,IF($J60>=0.125,0.25,IF($J60>=0.01,0.125,0)))))))))),""))) | L60: =IF($A60="","",IF(AND($C60>=2021,$C60<=2026,$E60<>"",$K60>0,LOWER($N60)="sim",LOWER($O60)="sim",OR(AND($F60="Exterior",OR($G60="WoS",$G60="Scopus")),AND($F60="Brasil",OR(AND(OR($G60="WoS",$G60="Scopus"),$H60>=50),$G60="Dimensions")))),$K60,""))
A61: Gerson Azulim Muller | B61: =IF($A61="","",IFERROR(VLOOKUP($A61,'Resumo por docente'!$A$8:$B$57,2,FALSE),"")) -> Biodiversidade, Saúde Ambiental e Conservação | C61: 2026 | D61: Phytotelm and anthropogenic mosquitoes: community structure in natural and artificial habitats in an Atlantic Forest agroforestry system, Rio de Janeiro, Brazil | K61: =IF($A61="","",IF(OR($G61="WoS",$G61="Scopus"),IF($H61="","",IF($H61>=87.5,1,IF($H61>=75,0.875,IF($H61>=62.5,0.75,IF($H61>=50,0.625,IF($H61>=37.5,0.5,IF($H61>=25,0.375,IF($H61>=12.5,0.25,IF($H61>=0.01,0.125,0))))))))),IF($G61="Dimensions",IF(OR($I61="",$J61=""),"",MIN(IF($I61>=87.5,1,IF($I61>=75,0.875,IF($I61>=62.5,0.75,IF($I61>=50,0.625,IF($I61>=37.5,0.5,IF($I61>=25,0.375,IF($I61>=12.5,0.25,IF($I61>=0.01,0.125,0)))))))),IF($J61>=2,1,IF($J61>=1.5,0.875,IF($J61>=1,0.75,IF($J61>=0.75,0.625,IF($J61>=0.5,0.5,IF($J61>=0.25,0.375,IF($J61>=0.125,0.25,IF($J61>=0.01,0.125,0)))))))))),""))) | L61: =IF($A61="","",IF(AND($C61>=2021,$C61<=2026,$E61<>"",$K61>0,LOWER($N61)="sim",LOWER($O61)="sim",OR(AND($F61="Exterior",OR($G61="WoS",$G61="Scopus")),AND($F61="Brasil",OR(AND(OR($G61="WoS",$G61="Scopus"),$H61>=50),$G61="Dimensions")))),$K61,"")) | N61: sim
A62: Gerson Azulim Muller | B62: =IF($A62="","",IFERROR(VLOOKUP($A62,'Resumo por docente'!$A$8:$B$57,2,FALSE),"")) -> Biodiversidade, Saúde Ambiental e Conservação | C62: 2022 | D62: Mosquitoes (diptera: culicidae) in bamboo internodes in the northwestern region of the state of Rio Grande do Sul, Brazil | E62: https://doi.org/10.5216/rpt.v51i2.70392 | K62: =IF($A62="","",IF(OR($G62="WoS",$G62="Scopus"),IF($H62="","",IF($H62>=87.5,1,IF($H62>=75,0.875,IF($H62>=62.5,0.75,IF($H62>=50,0.625,IF($H62>=37.5,0.5,IF($H62>=25,0.375,IF($H62>=12.5,0.25,IF($H62>=0.01,0.125,0))))))))),IF($G62="Dimensions",IF(OR($I62="",$J62=""),"",MIN(IF($I62>=87.5,1,IF($I62>=75,0.875,IF($I62>=62.5,0.75,IF($I62>=50,0.625,IF($I62>=37.5,0.5,IF($I62>=25,0.375,IF($I62>=12.5,0.25,IF($I62>=0.01,0.125,0)))))))),IF($J62>=2,1,IF($J62>=1.5,0.875,IF($J62>=1,0.75,IF($J62>=0.75,0.625,IF($J62>=0.5,0.5,IF($J62>=0.25,0.375,IF($J62>=0.125,0.25,IF($J62>=0.01,0.125,0)))))))))),""))) | L62: =IF($A62="","",IF(AND($C62>=2021,$C62<=2026,$E62<>"",$K62>0,LOWER($N62)="sim",LOWER($O62)="sim",OR(AND($F62="Exterior",OR($G62="WoS",$G62="Scopus")),AND($F62="Brasil",OR(AND(OR($G62="WoS",$G62="Scopus"),$H62>=50),$G62="Dimensions")))),$K62,"")) | N62: sim
A63: Gerson Azulim Muller | B63: =IF($A63="","",IFERROR(VLOOKUP($A63,'Resumo por docente'!$A$8:$B$57,2,FALSE),"")) -> Biodiversidade, Saúde Ambiental e Conservação | C63: 2022 | D63: Effects of seasonality on the oviposition activity of potential vector mosquitoes (Diptera: Culicidae) from the SÃƒÂ£o JoÃƒÂ£o River Basin Environmental Protection Area of the state of Rio de Janeiro, Brazil | E63: https://doi.org/10.1080/24750263.2022.2108513 | K63: =IF($A63="","",IF(OR($G63="WoS",$G63="Scopus"),IF($H63="","",IF($H63>=87.5,1,IF($H63>=75,0.875,IF($H63>=62.5,0.75,IF($H63>=50,0.625,IF($H63>=37.5,0.5,IF($H63>=25,0.375,IF($H63>=12.5,0.25,IF($H63>=0.01,0.125,0))))))))),IF($G63="Dimensions",IF(OR($I63="",$J63=""),"",MIN(IF($I63>=87.5,1,IF($I63>=75,0.875,IF($I63>=62.5,0.75,IF($I63>=50,0.625,IF($I63>=37.5,0.5,IF($I63>=25,0.375,IF($I63>=12.5,0.25,IF($I63>=0.01,0.125,0)))))))),IF($J63>=2,1,IF($J63>=1.5,0.875,IF($J63>=1,0.75,IF($J63>=0.75,0.625,IF($J63>=0.5,0.5,IF($J63>=0.25,0.375,IF($J63>=0.125,0.25,IF($J63>=0.01,0.125,0)))))))))),""))) | L63: =IF($A63="","",IF(AND($C63>=2021,$C63<=2026,$E63<>"",$K63>0,LOWER($N63)="sim",LOWER($O63)="sim",OR(AND($F63="Exterior",OR($G63="WoS",$G63="Scopus")),AND($F63="Brasil",OR(AND(OR($G63="WoS",$G63="Scopus"),$H63>=50),$G63="Dimensions")))),$K63,"")) | N63: sim
A64: Gerson Azulim Muller | B64: =IF($A64="","",IFERROR(VLOOKUP($A64,'Resumo por docente'!$A$8:$B$57,2,FALSE),"")) -> Biodiversidade, Saúde Ambiental e Conservação | C64: 2022 | D64: Little noticed, but very important: The role of breeding sites formed by bamboos in maintaining the diversity of mosquitoes (Diptera: Culicidae) in the Atlantic Forest biome | E64: https://doi.org/10.1371/journal.pone.0273774 | K64: =IF($A64="","",IF(OR($G64="WoS",$G64="Scopus"),IF($H64="","",IF($H64>=87.5,1,IF($H64>=75,0.875,IF($H64>=62.5,0.75,IF($H64>=50,0.625,IF($H64>=37.5,0.5,IF($H64>=25,0.375,IF($H64>=12.5,0.25,IF($H64>=0.01,0.125,0))))))))),IF($G64="Dimensions",IF(OR($I64="",$J64=""),"",MIN(IF($I64>=87.5,1,IF($I64>=75,0.875,IF($I64>=62.5,0.75,IF($I64>=50,0.625,IF($I64>=37.5,0.5,IF($I64>=25,0.375,IF($I64>=12.5,0.25,IF($I64>=0.01,0.125,0)))))))),IF($J64>=2,1,IF($J64>=1.5,0.875,IF($J64>=1,0.75,IF($J64>=0.75,0.625,IF($J64>=0.5,0.5,IF($J64>=0.25,0.375,IF($J64>=0.125,0.25,IF($J64>=0.01,0.125,0)))))))))),""))) | L64: =IF($A64="","",IF(AND($C64>=2021,$C64<=2026,$E64<>"",$K64>0,LOWER($N64)="sim",LOWER($O64)="sim",OR(AND($F64="Exterior",OR($G64="WoS",$G64="Scopus")),AND($F64="Brasil",OR(AND(OR($G64="WoS",$G64="Scopus"),$H64>=50),$G64="Dimensions")))),$K64,"")) | N64: sim
A65: GERUZA LEAL MELO | B65: =IF($A65="","",IFERROR(VLOOKUP($A65,'Resumo por docente'!$A$8:$B$57,2,FALSE),"")) -> Biodiversidade, Saúde Ambiental e Conservação | C65: 2025 | D65: Marsupials (Didelphidae, Mammalia) of Mato Grosso do Sul state (Brazil): taxonomic accounts, species richness, and biogeography | E65: https://doi.org/10.3897/zookeys.1243.141601 | K65: =IF($A65="","",IF(OR($G65="WoS",$G65="Scopus"),IF($H65="","",IF($H65>=87.5,1,IF($H65>=75,0.875,IF($H65>=62.5,0.75,IF($H65>=50,0.625,IF($H65>=37.5,0.5,IF($H65>=25,0.375,IF($H65>=12.5,0.25,IF($H65>=0.01,0.125,0))))))))),IF($G65="Dimensions",IF(OR($I65="",$J65=""),"",MIN(IF($I65>=87.5,1,IF($I65>=75,0.875,IF($I65>=62.5,0.75,IF($I65>=50,0.625,IF($I65>=37.5,0.5,IF($I65>=25,0.375,IF($I65>=12.5,0.25,IF($I65>=0.01,0.125,0)))))))),IF($J65>=2,1,IF($J65>=1.5,0.875,IF($J65>=1,0.75,IF($J65>=0.75,0.625,IF($J65>=0.5,0.5,IF($J65>=0.25,0.375,IF($J65>=0.125,0.25,IF($J65>=0.01,0.125,0)))))))))),""))) | L65: =IF($A65="","",IF(AND($C65>=2021,$C65<=2026,$E65<>"",$K65>0,LOWER($N65)="sim",LOWER($O65)="sim",OR(AND($F65="Exterior",OR($G65="WoS",$G65="Scopus")),AND($F65="Brasil",OR(AND(OR($G65="WoS",$G65="Scopus"),$H65>=50),$G65="Dimensions")))),$K65,"")) | N65: sim
A66: GERUZA LEAL MELO | B66: =IF($A66="","",IFERROR(VLOOKUP($A66,'Resumo por docente'!$A$8:$B$57,2,FALSE),"")) -> Biodiversidade, Saúde Ambiental e Conservação | C66: 2023 | D66: Candidatus Rickettsia andeanae? and Probable Exclusion of Rickettsia parkeri in Ticks from Dogs in a Natural Area of the Pampa Biome in Brazil | E66: https://doi.org/10.3390/pathogens12030446 | K66: =IF($A66="","",IF(OR($G66="WoS",$G66="Scopus"),IF($H66="","",IF($H66>=87.5,1,IF($H66>=75,0.875,IF($H66>=62.5,0.75,IF($H66>=50,0.625,IF($H66>=37.5,0.5,IF($H66>=25,0.375,IF($H66>=12.5,0.25,IF($H66>=0.01,0.125,0))))))))),IF($G66="Dimensions",IF(OR($I66="",$J66=""),"",MIN(IF($I66>=87.5,1,IF($I66>=75,0.875,IF($I66>=62.5,0.75,IF($I66>=50,0.625,IF($I66>=37.5,0.5,IF($I66>=25,0.375,IF($I66>=12.5,0.25,IF($I66>=0.01,0.125,0)))))))),IF($J66>=2,1,IF($J66>=1.5,0.875,IF($J66>=1,0.75,IF($J66>=0.75,0.625,IF($J66>=0.5,0.5,IF($J66>=0.25,0.375,IF($J66>=0.125,0.25,IF($J66>=0.01,0.125,0)))))))))),""))) | L66: =IF($A66="","",IF(AND($C66>=2021,$C66<=2026,$E66<>"",$K66>0,LOWER($N66)="sim",LOWER($O66)="sim",OR(AND($F66="Exterior",OR($G66="WoS",$G66="Scopus")),AND($F66="Brasil",OR(AND(OR($G66="WoS",$G66="Scopus"),$H66>=50),$G66="Dimensions")))),$K66,"")) | N66: sim
A67: GERUZA LEAL MELO | B67: =IF($A67="","",IFERROR(VLOOKUP($A67,'Resumo por docente'!$A$8:$B$57,2,FALSE),"")) -> Biodiversidade, Saúde Ambiental e Conservação | C67: 2022 | D67: The Role of Habitat Amount and Vegetation Density for Explaining Loss of Small-Mammal Diversity in a South American Woodland Savanna | E67: https://doi.org/10.3389/fevo.2022.740371 | K67: =IF($A67="","",IF(OR($G67="WoS",$G67="Scopus"),IF($H67="","",IF($H67>=87.5,1,IF($H67>=75,0.875,IF($H67>=62.5,0.75,IF($H67>=50,0.625,IF($H67>=37.5,0.5,IF($H67>=25,0.375,IF($H67>=12.5,0.25,IF($H67>=0.01,0.125,0))))))))),IF($G67="Dimensions",IF(OR($I67="",$J67=""),"",MIN(IF($I67>=87.5,1,IF($I67>=75,0.875,IF($I67>=62.5,0.75,IF($I67>=50,0.625,IF($I67>=37.5,0.5,IF($I67>=25,0.375,IF($I67>=12.5,0.25,IF($I67>=0.01,0.125,0)))))))),IF($J67>=2,1,IF($J67>=1.5,0.875,IF($J67>=1,0.75,IF($J67>=0.75,0.625,IF($J67>=0.5,0.5,IF($J67>=0.25,0.375,IF($J67>=0.125,0.25,IF($J67>=0.01,0.125,0)))))))))),""))) | L67: =IF($A67="","",IF(AND($C67>=2021,$C67<=2026,$E67<>"",$K67>0,LOWER($N67)="sim",LOWER($O67)="sim",OR(AND($F67="Exterior",OR($G67="WoS",$G67="Scopus")),AND($F67="Brasil",OR(AND(OR($G67="WoS",$G67="Scopus"),$H67>=50),$G67="Dimensions")))),$K67,"")) | N67: sim
A68: GERUZA LEAL MELO | B68: =IF($A68="","",IFERROR(VLOOKUP($A68,'Resumo por docente'!$A$8:$B$57,2,FALSE),"")) -> Biodiversidade, Saúde Ambiental e Conservação | C68: 2022 | D68: Ecological evidence of hierarchy and competition in Didelphis aurita females | E68: https://doi.org/10.1007/s42991-022-00269-9 | K68: =IF($A68="","",IF(OR($G68="WoS",$G68="Scopus"),IF($H68="","",IF($H68>=87.5,1,IF($H68>=75,0.875,IF($H68>=62.5,0.75,IF($H68>=50,0.625,IF($H68>=37.5,0.5,IF($H68>=25,0.375,IF($H68>=12.5,0.25,IF($H68>=0.01,0.125,0))))))))),IF($G68="Dimensions",IF(OR($I68="",$J68=""),"",MIN(IF($I68>=87.5,1,IF($I68>=75,0.875,IF($I68>=62.5,0.75,IF($I68>=50,0.625,IF($I68>=37.5,0.5,IF($I68>=25,0.375,IF($I68>=12.5,0.25,IF($I68>=0.01,0.125,0)))))))),IF($J68>=2,1,IF($J68>=1.5,0.875,IF($J68>=1,0.75,IF($J68>=0.75,0.625,IF($J68>=0.5,0.5,IF($J68>=0.25,0.375,IF($J68>=0.125,0.25,IF($J68>=0.01,0.125,0)))))))))),""))) | L68: =IF($A68="","",IF(AND($C68>=2021,$C68<=2026,$E68<>"",$K68>0,LOWER($N68)="sim",LOWER($O68)="sim",OR(AND($F68="Exterior",OR($G68="WoS",$G68="Scopus")),AND($F68="Brasil",OR(AND(OR($G68="WoS",$G68="Scopus"),$H68>=50),$G68="Dimensions")))),$K68,"")) | N68: sim
A69: GERUZA LEAL MELO | B69: =IF($A69="","",IFERROR(VLOOKUP($A69,'Resumo por docente'!$A$8:$B$57,2,FALSE),"")) -> Biodiversidade, Saúde Ambiental e Conservação | C69: 2022 | D69: Rickettsial infection in ticks from a natural area of Atlantic Forest biome in southern Brazil | E69: https://doi.org/10.1007/s10493-022-00754-3 | K69: =IF($A69="","",IF(OR($G69="WoS",$G69="Scopus"),IF($H69="","",IF($H69>=87.5,1,IF($H69>=75,0.875,IF($H69>=62.5,0.75,IF($H69>=50,0.625,IF($H69>=37.5,0.5,IF($H69>=25,0.375,IF($H69>=12.5,0.25,IF($H69>=0.01,0.125,0))))))))),IF($G69="Dimensions",IF(OR($I69="",$J69=""),"",MIN(IF($I69>=87.5,1,IF($I69>=75,0.875,IF($I69>=62.5,0.75,IF($I69>=50,0.625,IF($I69>=37.5,0.5,IF($I69>=25,0.375,IF($I69>=12.5,0.25,IF($I69>=0.01,0.125,0)))))))),IF($J69>=2,1,IF($J69>=1.5,0.875,IF($J69>=1,0.75,IF($J69>=0.75,0.625,IF($J69>=0.5,0.5,IF($J69>=0.25,0.375,IF($J69>=0.125,0.25,IF($J69>=0.01,0.125,0)))))))))),""))) | L69: =IF($A69="","",IF(AND($C69>=2021,$C69<=2026,$E69<>"",$K69>0,LOWER($N69)="sim",LOWER($O69)="sim",OR(AND($F69="Exterior",OR($G69="WoS",$G69="Scopus")),AND($F69="Brasil",OR(AND(OR($G69="WoS",$G69="Scopus"),$H69>=50),$G69="Dimensions")))),$K69,"")) | N69: sim
A70: GERUZA LEAL MELO | B70: =IF($A70="","",IFERROR(VLOOKUP($A70,'Resumo por docente'!$A$8:$B$57,2,FALSE),"")) -> Biodiversidade, Saúde Ambiental e Conservação | C70: 2021 | D70: Niche partitioning in small mammals: interspecific and biome-level analyses using stable isotopes | E70: https://doi.org/10.1093/jmammal/gyab063
A71: JONAS SPONCHIADO | B71: =IF($A71="","",IFERROR(VLOOKUP($A71,'Resumo por docente'!$A$8:$B$57,2,FALSE),"")) -> Biodiversidade, Saúde Ambiental e Conservação | C71: 2025 | D71: Marsupials (Didelphidae, Mammalia) of Mato Grosso do Sul state (Brazil): taxonomic accounts, species richness, and biogeography | E71: https://doi.org/10.3897/zookeys.1243.141601 | K71: =IF($A71="","",IF(OR($G71="WoS",$G71="Scopus"),IF($H71="","",IF($H71>=87.5,1,IF($H71>=75,0.875,IF($H71>=62.5,0.75,IF($H71>=50,0.625,IF($H71>=37.5,0.5,IF($H71>=25,0.375,IF($H71>=12.5,0.25,IF($H71>=0.01,0.125,0))))))))),IF($G71="Dimensions",IF(OR($I71="",$J71=""),"",MIN(IF($I71>=87.5,1,IF($I71>=75,0.875,IF($I71>=62.5,0.75,IF($I71>=50,0.625,IF($I71>=37.5,0.5,IF($I71>=25,0.375,IF($I71>=12.5,0.25,IF($I71>=0.01,0.125,0)))))))),IF($J71>=2,1,IF($J71>=1.5,0.875,IF($J71>=1,0.75,IF($J71>=0.75,0.625,IF($J71>=0.5,0.5,IF($J71>=0.25,0.375,IF($J71>=0.125,0.25,IF($J71>=0.01,0.125,0)))))))))),""))) | L71: =IF($A71="","",IF(AND($C71>=2021,$C71<=2026,$E71<>"",$K71>0,LOWER($N71)="sim",LOWER($O71)="sim",OR(AND($F71="Exterior",OR($G71="WoS",$G71="Scopus")),AND($F71="Brasil",OR(AND(OR($G71="WoS",$G71="Scopus"),$H71>=50),$G71="Dimensions")))),$K71,"")) | N71: sim
A72: JONAS SPONCHIADO | B72: =IF($A72="","",IFERROR(VLOOKUP($A72,'Resumo por docente'!$A$8:$B$57,2,FALSE),"")) -> Biodiversidade, Saúde Ambiental e Conservação | C72: 2024 | D72: Rickettsial Infection in Ticks from a National Park in the Cerrado Biome, Midwestern Brazil | E72: https://doi.org/10.3390/pathogens13010013 | K72: =IF($A72="","",IF(OR($G72="WoS",$G72="Scopus"),IF($H72="","",IF($H72>=87.5,1,IF($H72>=75,0.875,IF($H72>=62.5,0.75,IF($H72>=50,0.625,IF($H72>=37.5,0.5,IF($H72>=25,0.375,IF($H72>=12.5,0.25,IF($H72>=0.01,0.125,0))))))))),IF($G72="Dimensions",IF(OR($I72="",$J72=""),"",MIN(IF($I72>=87.5,1,IF($I72>=75,0.875,IF($I72>=62.5,0.75,IF($I72>=50,0.625,IF($I72>=37.5,0.5,IF($I72>=25,0.375,IF($I72>=12.5,0.25,IF($I72>=0.01,0.125,0)))))))),IF($J72>=2,1,IF($J72>=1.5,0.875,IF($J72>=1,0.75,IF($J72>=0.75,0.625,IF($J72>=0.5,0.5,IF($J72>=0.25,0.375,IF($J72>=0.125,0.25,IF($J72>=0.01,0.125,0)))))))))),""))) | L72: =IF($A72="","",IF(AND($C72>=2021,$C72<=2026,$E72<>"",$K72>0,LOWER($N72)="sim",LOWER($O72)="sim",OR(AND($F72="Exterior",OR($G72="WoS",$G72="Scopus")),AND($F72="Brasil",OR(AND(OR($G72="WoS",$G72="Scopus"),$H72>=50),$G72="Dimensions")))),$K72,"")) | N72: sim
A73: JONAS SPONCHIADO | B73: =IF($A73="","",IFERROR(VLOOKUP($A73,'Resumo por docente'!$A$8:$B$57,2,FALSE),"")) -> Biodiversidade, Saúde Ambiental e Conservação | C73: 2023 | D73: Candidatus Rickettsia andeanae? and Probable Exclusion of Rickettsia parkeri in Ticks from Dogs in a Natural Area of the Pampa Biome in Brazil | E73: https://doi.org/10.3390/pathogens12030446 | K73: =IF($A73="","",IF(OR($G73="WoS",$G73="Scopus"),IF($H73="","",IF($H73>=87.5,1,IF($H73>=75,0.875,IF($H73>=62.5,0.75,IF($H73>=50,0.625,IF($H73>=37.5,0.5,IF($H73>=25,0.375,IF($H73>=12.5,0.25,IF($H73>=0.01,0.125,0))))))))),IF($G73="Dimensions",IF(OR($I73="",$J73=""),"",MIN(IF($I73>=87.5,1,IF($I73>=75,0.875,IF($I73>=62.5,0.75,IF($I73>=50,0.625,IF($I73>=37.5,0.5,IF($I73>=25,0.375,IF($I73>=12.5,0.25,IF($I73>=0.01,0.125,0)))))))),IF($J73>=2,1,IF($J73>=1.5,0.875,IF($J73>=1,0.75,IF($J73>=0.75,0.625,IF($J73>=0.5,0.5,IF($J73>=0.25,0.375,IF($J73>=0.125,0.25,IF($J73>=0.01,0.125,0)))))))))),""))) | L73: =IF($A73="","",IF(AND($C73>=2021,$C73<=2026,$E73<>"",$K73>0,LOWER($N73)="sim",LOWER($O73)="sim",OR(AND($F73="Exterior",OR($G73="WoS",$G73="Scopus")),AND($F73="Brasil",OR(AND(OR($G73="WoS",$G73="Scopus"),$H73>=50),$G73="Dimensions")))),$K73,"")) | N73: sim
A74: JONAS SPONCHIADO | B74: =IF($A74="","",IFERROR(VLOOKUP($A74,'Resumo por docente'!$A$8:$B$57,2,FALSE),"")) -> Biodiversidade, Saúde Ambiental e Conservação | C74: 2022 | D74: The Role of Habitat Amount and Vegetation Density for Explaining Loss of Small-Mammal Diversity in a South American Woodland Savanna | E74: https://doi.org/10.3389/fevo.2022.740371 | K74: =IF($A74="","",IF(OR($G74="WoS",$G74="Scopus"),IF($H74="","",IF($H74>=87.5,1,IF($H74>=75,0.875,IF($H74>=62.5,0.75,IF($H74>=50,0.625,IF($H74>=37.5,0.5,IF($H74>=25,0.375,IF($H74>=12.5,0.25,IF($H74>=0.01,0.125,0))))))))),IF($G74="Dimensions",IF(OR($I74="",$J74=""),"",MIN(IF($I74>=87.5,1,IF($I74>=75,0.875,IF($I74>=62.5,0.75,IF($I74>=50,0.625,IF($I74>=37.5,0.5,IF($I74>=25,0.375,IF($I74>=12.5,0.25,IF($I74>=0.01,0.125,0)))))))),IF($J74>=2,1,IF($J74>=1.5,0.875,IF($J74>=1,0.75,IF($J74>=0.75,0.625,IF($J74>=0.5,0.5,IF($J74>=0.25,0.375,IF($J74>=0.125,0.25,IF($J74>=0.01,0.125,0)))))))))),""))) | L74: =IF($A74="","",IF(AND($C74>=2021,$C74<=2026,$E74<>"",$K74>0,LOWER($N74)="sim",LOWER($O74)="sim",OR(AND($F74="Exterior",OR($G74="WoS",$G74="Scopus")),AND($F74="Brasil",OR(AND(OR($G74="WoS",$G74="Scopus"),$H74>=50),$G74="Dimensions")))),$K74,"")) | N74: sim
A75: JONAS SPONCHIADO | B75: =IF($A75="","",IFERROR(VLOOKUP($A75,'Resumo por docente'!$A$8:$B$57,2,FALSE),"")) -> Biodiversidade, Saúde Ambiental e Conservação | C75: 2022 | D75: Rickettsial infection in ticks from a natural area of Atlantic Forest biome in southern Brazil | E75: https://doi.org/10.1007/s10493-022-00754-3 | K75: =IF($A75="","",IF(OR($G75="WoS",$G75="Scopus"),IF($H75="","",IF($H75>=87.5,1,IF($H75>=75,0.875,IF($H75>=62.5,0.75,IF($H75>=50,0.625,IF($H75>=37.5,0.5,IF($H75>=25,0.375,IF($H75>=12.5,0.25,IF($H75>=0.01,0.125,0))))))))),IF($G75="Dimensions",IF(OR($I75="",$J75=""),"",MIN(IF($I75>=87.5,1,IF($I75>=75,0.875,IF($I75>=62.5,0.75,IF($I75>=50,0.625,IF($I75>=37.5,0.5,IF($I75>=25,0.375,IF($I75>=12.5,0.25,IF($I75>=0.01,0.125,0)))))))),IF($J75>=2,1,IF($J75>=1.5,0.875,IF($J75>=1,0.75,IF($J75>=0.75,0.625,IF($J75>=0.5,0.5,IF($J75>=0.25,0.375,IF($J75>=0.125,0.25,IF($J75>=0.01,0.125,0)))))))))),""))) | L75: =IF($A75="","",IF(AND($C75>=2021,$C75<=2026,$E75<>"",$K75>0,LOWER($N75)="sim",LOWER($O75)="sim",OR(AND($F75="Exterior",OR($G75="WoS",$G75="Scopus")),AND($F75="Brasil",OR(AND(OR($G75="WoS",$G75="Scopus"),$H75>=50),$G75="Dimensions")))),$K75,"")) | N75: sim
A76: JONAS SPONCHIADO | B76: =IF($A76="","",IFERROR(VLOOKUP($A76,'Resumo por docente'!$A$8:$B$57,2,FALSE),"")) -> Biodiversidade, Saúde Ambiental e Conservação | C76: 2021 | D76: Niche partitioning in small mammals: interspecific and biome-level analyses using stable isotopes | E76: https://doi.org/10.1093/jmammal/gyab063
A77: Kátia Maria Cardinal | B77: =IF($A77="","",IFERROR(VLOOKUP($A77,'Resumo por docente'!$A$8:$B$57,2,FALSE),"")) -> Inovação, Biotecnologia e Sustentabilidade Produtiva | C77: 2026 | D77: Aflatoxin contamination in commercial egg hens production – systematic review and meta-analysis | E77: 10.1080/00439339.2026.2626674 | F77: Exterior | G77: Scopus | H77: 0 | J77: 0 | K77: =IF($A77="","",IF(OR($G77="WoS",$G77="Scopus"),IF($H77="","",IF($H77>=87.5,1,IF($H77>=75,0.875,IF($H77>=62.5,0.75,IF($H77>=50,0.625,IF($H77>=37.5,0.5,IF($H77>=25,0.375,IF($H77>=12.5,0.25,IF($H77>=0.01,0.125,0))))))))),IF($G77="Dimensions",IF(OR($I77="",$J77=""),"",MIN(IF($I77>=87.5,1,IF($I77>=75,0.875,IF($I77>=62.5,0.75,IF($I77>=50,0.625,IF($I77>=37.5,0.5,IF($I77>=25,0.375,IF($I77>=12.5,0.25,IF($I77>=0.01,0.125,0)))))))),IF($J77>=2,1,IF($J77>=1.5,0.875,IF($J77>=1,0.75,IF($J77>=0.75,0.625,IF($J77>=0.5,0.5,IF($J77>=0.25,0.375,IF($J77>=0.125,0.25,IF($J77>=0.01,0.125,0)))))))))),""))) -> 0 | L77: =IF($A77="","",IF(AND($C77>=2021,$C77<=2026,$E77<>"",$K77>0,LOWER($N77)="sim",LOWER($O77)="sim",OR(AND($F77="Exterior",OR($G77="WoS",$G77="Scopus")),AND($F77="Brasil",OR(AND(OR($G77="WoS",$G77="Scopus"),$H77>=50),$G77="Dimensions")))),$K77,""))
A78: Kátia Maria Cardinal | B78: =IF($A78="","",IFERROR(VLOOKUP($A78,'Resumo por docente'!$A$8:$B$57,2,FALSE),"")) -> Inovação, Biotecnologia e Sustentabilidade Produtiva | C78: 2026 | D78: Global impact of antimicrobial growth promoters on livestock productivity: a meta-analysis for economic modeling | E78: 10.1016/j.prevetmed.2025.106754 | F78: Exterior | G78: Scopus | H78: 89 | J78: 3 | K78: =IF($A78="","",IF(OR($G78="WoS",$G78="Scopus"),IF($H78="","",IF($H78>=87.5,1,IF($H78>=75,0.875,IF($H78>=62.5,0.75,IF($H78>=50,0.625,IF($H78>=37.5,0.5,IF($H78>=25,0.375,IF($H78>=12.5,0.25,IF($H78>=0.01,0.125,0))))))))),IF($G78="Dimensions",IF(OR($I78="",$J78=""),"",MIN(IF($I78>=87.5,1,IF($I78>=75,0.875,IF($I78>=62.5,0.75,IF($I78>=50,0.625,IF($I78>=37.5,0.5,IF($I78>=25,0.375,IF($I78>=12.5,0.25,IF($I78>=0.01,0.125,0)))))))),IF($J78>=2,1,IF($J78>=1.5,0.875,IF($J78>=1,0.75,IF($J78>=0.75,0.625,IF($J78>=0.5,0.5,IF($J78>=0.25,0.375,IF($J78>=0.125,0.25,IF($J78>=0.01,0.125,0)))))))))),""))) -> 1 | L78: =IF($A78="","",IF(AND($C78>=2021,$C78<=2026,$E78<>"",$K78>0,LOWER($N78)="sim",LOWER($O78)="sim",OR(AND($F78="Exterior",OR($G78="WoS",$G78="Scopus")),AND($F78="Brasil",OR(AND(OR($G78="WoS",$G78="Scopus"),$H78>=50),$G78="Dimensions")))),$K78,""))
A79: Kátia Maria Cardinal | B79: =IF($A79="","",IFERROR(VLOOKUP($A79,'Resumo por docente'!$A$8:$B$57,2,FALSE),"")) -> Inovação, Biotecnologia e Sustentabilidade Produtiva | C79: 2026 | D79: Impact of phytogenic additive and sodium monensin on broiler gut microbiota and immune response to Eimeria infection | E79: 10.1016/j.rvsc.2025.105989 | F79: Exterior | G79: Scopus | H79: 0 | J79: 0 | K79: =IF($A79="","",IF(OR($G79="WoS",$G79="Scopus"),IF($H79="","",IF($H79>=87.5,1,IF($H79>=75,0.875,IF($H79>=62.5,0.75,IF($H79>=50,0.625,IF($H79>=37.5,0.5,IF($H79>=25,0.375,IF($H79>=12.5,0.25,IF($H79>=0.01,0.125,0))))))))),IF($G79="Dimensions",IF(OR($I79="",$J79=""),"",MIN(IF($I79>=87.5,1,IF($I79>=75,0.875,IF($I79>=62.5,0.75,IF($I79>=50,0.625,IF($I79>=37.5,0.5,IF($I79>=25,0.375,IF($I79>=12.5,0.25,IF($I79>=0.01,0.125,0)))))))),IF($J79>=2,1,IF($J79>=1.5,0.875,IF($J79>=1,0.75,IF($J79>=0.75,0.625,IF($J79>=0.5,0.5,IF($J79>=0.25,0.375,IF($J79>=0.125,0.25,IF($J79>=0.01,0.125,0)))))))))),""))) -> 0 | L79: =IF($A79="","",IF(AND($C79>=2021,$C79<=2026,$E79<>"",$K79>0,LOWER($N79)="sim",LOWER($O79)="sim",OR(AND($F79="Exterior",OR($G79="WoS",$G79="Scopus")),AND($F79="Brasil",OR(AND(OR($G79="WoS",$G79="Scopus"),$H79>=50),$G79="Dimensions")))),$K79,""))
A80: Kátia Maria Cardinal | B80: =IF($A80="","",IFERROR(VLOOKUP($A80,'Resumo por docente'!$A$8:$B$57,2,FALSE),"")) -> Inovação, Biotecnologia e Sustentabilidade Produtiva | C80: 2025 | D80: Is there an appropriate energy level in the diet during the cow transition period? A systematic review and meta-analysis | E80: 10.1017/S002202992510112X | F80: Exterior | G80: Scopus | H80: 58 | J80: 1 | K80: =IF($A80="","",IF(OR($G80="WoS",$G80="Scopus"),IF($H80="","",IF($H80>=87.5,1,IF($H80>=75,0.875,IF($H80>=62.5,0.75,IF($H80>=50,0.625,IF($H80>=37.5,0.5,IF($H80>=25,0.375,IF($H80>=12.5,0.25,IF($H80>=0.01,0.125,0))))))))),IF($G80="Dimensions",IF(OR($I80="",$J80=""),"",MIN(IF($I80>=87.5,1,IF($I80>=75,0.875,IF($I80>=62.5,0.75,IF($I80>=50,0.625,IF($I80>=37.5,0.5,IF($I80>=25,0.375,IF($I80>=12.5,0.25,IF($I80>=0.01,0.125,0)))))))),IF($J80>=2,1,IF($J80>=1.5,0.875,IF($J80>=1,0.75,IF($J80>=0.75,0.625,IF($J80>=0.5,0.5,IF($J80>=0.25,0.375,IF($J80>=0.125,0.25,IF($J80>=0.01,0.125,0)))))))))),""))) -> 0.625 | L80: =IF($A80="","",IF(AND($C80>=2021,$C80<=2026,$E80<>"",$K80>0,LOWER($N80)="sim",LOWER($O80)="sim",OR(AND($F80="Exterior",OR($G80="WoS",$G80="Scopus")),AND($F80="Brasil",OR(AND(OR($G80="WoS",$G80="Scopus"),$H80>=50),$G80="Dimensions")))),$K80,""))
A81: Kátia Maria Cardinal | B81: =IF($A81="","",IFERROR(VLOOKUP($A81,'Resumo por docente'!$A$8:$B$57,2,FALSE),"")) -> Inovação, Biotecnologia e Sustentabilidade Produtiva | C81: 2025 | D81: Non-invasive biomarkers for monitoring intestinal health in broilers – a systematic review | E81: 10.1016/j.rvsc.2025.105669 | F81: Exterior | G81: Scopus | H81: 75 | J81: 3 | K81: =IF($A81="","",IF(OR($G81="WoS",$G81="Scopus"),IF($H81="","",IF($H81>=87.5,1,IF($H81>=75,0.875,IF($H81>=62.5,0.75,IF($H81>=50,0.625,IF($H81>=37.5,0.5,IF($H81>=25,0.375,IF($H81>=12.5,0.25,IF($H81>=0.01,0.125,0))))))))),IF($G81="Dimensions",IF(OR($I81="",$J81=""),"",MIN(IF($I81>=87.5,1,IF($I81>=75,0.875,IF($I81>=62.5,0.75,IF($I81>=50,0.625,IF($I81>=37.5,0.5,IF($I81>=25,0.375,IF($I81>=12.5,0.25,IF($I81>=0.01,0.125,0)))))))),IF($J81>=2,1,IF($J81>=1.5,0.875,IF($J81>=1,0.75,IF($J81>=0.75,0.625,IF($J81>=0.5,0.5,IF($J81>=0.25,0.375,IF($J81>=0.125,0.25,IF($J81>=0.01,0.125,0)))))))))),""))) -> 0.875 | L81: =IF($A81="","",IF(AND($C81>=2021,$C81<=2026,$E81<>"",$K81>0,LOWER($N81)="sim",LOWER($O81)="sim",OR(AND($F81="Exterior",OR($G81="WoS",$G81="Scopus")),AND($F81="Brasil",OR(AND(OR($G81="WoS",$G81="Scopus"),$H81>=50),$G81="Dimensions")))),$K81,""))
A82: Kátia Maria Cardinal | B82: =IF($A82="","",IFERROR(VLOOKUP($A82,'Resumo por docente'!$A$8:$B$57,2,FALSE),"")) -> Inovação, Biotecnologia e Sustentabilidade Produtiva | C82: 2025 | D82: Physical characteristics of meat from native Brazilian sheep breeds: a systematic review and meta-analysis | E82: 10.5433/1679-0359.2025v46n5p1485 | F82: Brasil | G82: Scopus | H82: 68 | J82: 4 | K82: =IF($A82="","",IF(OR($G82="WoS",$G82="Scopus"),IF($H82="","",IF($H82>=87.5,1,IF($H82>=75,0.875,IF($H82>=62.5,0.75,IF($H82>=50,0.625,IF($H82>=37.5,0.5,IF($H82>=25,0.375,IF($H82>=12.5,0.25,IF($H82>=0.01,0.125,0))))))))),IF($G82="Dimensions",IF(OR($I82="",$J82=""),"",MIN(IF($I82>=87.5,1,IF($I82>=75,0.875,IF($I82>=62.5,0.75,IF($I82>=50,0.625,IF($I82>=37.5,0.5,IF($I82>=25,0.375,IF($I82>=12.5,0.25,IF($I82>=0.01,0.125,0)))))))),IF($J82>=2,1,IF($J82>=1.5,0.875,IF($J82>=1,0.75,IF($J82>=0.75,0.625,IF($J82>=0.5,0.5,IF($J82>=0.25,0.375,IF($J82>=0.125,0.25,IF($J82>=0.01,0.125,0)))))))))),""))) -> 0.75 | L82: =IF($A82="","",IF(AND($C82>=2021,$C82<=2026,$E82<>"",$K82>0,LOWER($N82)="sim",LOWER($O82)="sim",OR(AND($F82="Exterior",OR($G82="WoS",$G82="Scopus")),AND($F82="Brasil",OR(AND(OR($G82="WoS",$G82="Scopus"),$H82>=50),$G82="Dimensions")))),$K82,""))
A83: Kátia Maria Cardinal | B83: =IF($A83="","",IFERROR(VLOOKUP($A83,'Resumo por docente'!$A$8:$B$57,2,FALSE),"")) -> Inovação, Biotecnologia e Sustentabilidade Produtiva | C83: 2025 | D83: The impact of laying hen housing systems on egg production, egg quality, and intestinal microbiota of the hens | E83: 10.1079/cabireviews.2025.0060 | F83: Exterior | G83: Scopus | H83: 0 | J83: 0 | K83: =IF($A83="","",IF(OR($G83="WoS",$G83="Scopus"),IF($H83="","",IF($H83>=87.5,1,IF($H83>=75,0.875,IF($H83>=62.5,0.75,IF($H83>=50,0.625,IF($H83>=37.5,0.5,IF($H83>=25,0.375,IF($H83>=12.5,0.25,IF($H83>=0.01,0.125,0))))))))),IF($G83="Dimensions",IF(OR($I83="",$J83=""),"",MIN(IF($I83>=87.5,1,IF($I83>=75,0.875,IF($I83>=62.5,0.75,IF($I83>=50,0.625,IF($I83>=37.5,0.5,IF($I83>=25,0.375,IF($I83>=12.5,0.25,IF($I83>=0.01,0.125,0)))))))),IF($J83>=2,1,IF($J83>=1.5,0.875,IF($J83>=1,0.75,IF($J83>=0.75,0.625,IF($J83>=0.5,0.5,IF($J83>=0.25,0.375,IF($J83>=0.125,0.25,IF($J83>=0.01,0.125,0)))))))))),""))) -> 0 | L83: =IF($A83="","",IF(AND($C83>=2021,$C83<=2026,$E83<>"",$K83>0,LOWER($N83)="sim",LOWER($O83)="sim",OR(AND($F83="Exterior",OR($G83="WoS",$G83="Scopus")),AND($F83="Brasil",OR(AND(OR($G83="WoS",$G83="Scopus"),$H83>=50),$G83="Dimensions")))),$K83,""))
A84: Kátia Maria Cardinal | B84: =IF($A84="","",IFERROR(VLOOKUP($A84,'Resumo por docente'!$A$8:$B$57,2,FALSE),"")) -> Inovação, Biotecnologia e Sustentabilidade Produtiva | C84: 2024 | D84: Honey consumer's perception: are Brazilian consumers familiar with stingless bee honey? | E84: 10.14393/BJ-v40n0a2024-68089 | F84: Exterior | G84: Scopus | H84: 40 | J84: 1 | K84: =IF($A84="","",IF(OR($G84="WoS",$G84="Scopus"),IF($H84="","",IF($H84>=87.5,1,IF($H84>=75,0.875,IF($H84>=62.5,0.75,IF($H84>=50,0.625,IF($H84>=37.5,0.5,IF($H84>=25,0.375,IF($H84>=12.5,0.25,IF($H84>=0.01,0.125,0))))))))),IF($G84="Dimensions",IF(OR($I84="",$J84=""),"",MIN(IF($I84>=87.5,1,IF($I84>=75,0.875,IF($I84>=62.5,0.75,IF($I84>=50,0.625,IF($I84>=37.5,0.5,IF($I84>=25,0.375,IF($I84>=12.5,0.25,IF($I84>=0.01,0.125,0)))))))),IF($J84>=2,1,IF($J84>=1.5,0.875,IF($J84>=1,0.75,IF($J84>=0.75,0.625,IF($J84>=0.5,0.5,IF($J84>=0.25,0.375,IF($J84>=0.125,0.25,IF($J84>=0.01,0.125,0)))))))))),""))) -> 0.5 | L84: =IF($A84="","",IF(AND($C84>=2021,$C84<=2026,$E84<>"",$K84>0,LOWER($N84)="sim",LOWER($O84)="sim",OR(AND($F84="Exterior",OR($G84="WoS",$G84="Scopus")),AND($F84="Brasil",OR(AND(OR($G84="WoS",$G84="Scopus"),$H84>=50),$G84="Dimensions")))),$K84,""))
A85: Kátia Maria Cardinal | B85: =IF($A85="","",IFERROR(VLOOKUP($A85,'Resumo por docente'!$A$8:$B$57,2,FALSE),"")) -> Inovação, Biotecnologia e Sustentabilidade Produtiva | C85: 2024 | D85: Lactation performance, feed efficiency, and blood metabolites of dairy cows treated with recombinant bovine somatotropin: a systematic review and meta-analysis | E85: 10.1016/j.rvsc.2024.105274 | F85: Exterior | G85: Scopus | H85: 62 | J85: 4 | K85: =IF($A85="","",IF(OR($G85="WoS",$G85="Scopus"),IF($H85="","",IF($H85>=87.5,1,IF($H85>=75,0.875,IF($H85>=62.5,0.75,IF($H85>=50,0.625,IF($H85>=37.5,0.5,IF($H85>=25,0.375,IF($H85>=12.5,0.25,IF($H85>=0.01,0.125,0))))))))),IF($G85="Dimensions",IF(OR($I85="",$J85=""),"",MIN(IF($I85>=87.5,1,IF($I85>=75,0.875,IF($I85>=62.5,0.75,IF($I85>=50,0.625,IF($I85>=37.5,0.5,IF($I85>=25,0.375,IF($I85>=12.5,0.25,IF($I85>=0.01,0.125,0)))))))),IF($J85>=2,1,IF($J85>=1.5,0.875,IF($J85>=1,0.75,IF($J85>=0.75,0.625,IF($J85>=0.5,0.5,IF($J85>=0.25,0.375,IF($J85>=0.125,0.25,IF($J85>=0.01,0.125,0)))))))))),""))) -> 0.625 | L85: =IF($A85="","",IF(AND($C85>=2021,$C85<=2026,$E85<>"",$K85>0,LOWER($N85)="sim",LOWER($O85)="sim",OR(AND($F85="Exterior",OR($G85="WoS",$G85="Scopus")),AND($F85="Brasil",OR(AND(OR($G85="WoS",$G85="Scopus"),$H85>=50),$G85="Dimensions")))),$K85,""))
A86: Kátia Maria Cardinal | B86: =IF($A86="","",IFERROR(VLOOKUP($A86,'Resumo por docente'!$A$8:$B$57,2,FALSE),"")) -> Inovação, Biotecnologia e Sustentabilidade Produtiva | C86: 2024 | D86: The impact of different levels of functional oil supplementation in combination with salinomycin on growth performance and intestinal microbiota of broilers undergoing Eimeria challenge: an analysis of dynamics | E86: 10.1016/j.rvsc.2024.105249 | F86: Exterior | G86: Scopus | H86: 57 | J86: 4 | K86: =IF($A86="","",IF(OR($G86="WoS",$G86="Scopus"),IF($H86="","",IF($H86>=87.5,1,IF($H86>=75,0.875,IF($H86>=62.5,0.75,IF($H86>=50,0.625,IF($H86>=37.5,0.5,IF($H86>=25,0.375,IF($H86>=12.5,0.25,IF($H86>=0.01,0.125,0))))))))),IF($G86="Dimensions",IF(OR($I86="",$J86=""),"",MIN(IF($I86>=87.5,1,IF($I86>=75,0.875,IF($I86>=62.5,0.75,IF($I86>=50,0.625,IF($I86>=37.5,0.5,IF($I86>=25,0.375,IF($I86>=12.5,0.25,IF($I86>=0.01,0.125,0)))))))),IF($J86>=2,1,IF($J86>=1.5,0.875,IF($J86>=1,0.75,IF($J86>=0.75,0.625,IF($J86>=0.5,0.5,IF($J86>=0.25,0.375,IF($J86>=0.125,0.25,IF($J86>=0.01,0.125,0)))))))))),""))) -> 0.625 | L86: =IF($A86="","",IF(AND($C86>=2021,$C86<=2026,$E86<>"",$K86>0,LOWER($N86)="sim",LOWER($O86)="sim",OR(AND($F86="Exterior",OR($G86="WoS",$G86="Scopus")),AND($F86="Brasil",OR(AND(OR($G86="WoS",$G86="Scopus"),$H86>=50),$G86="Dimensions")))),$K86,""))
A87: Kátia Maria Cardinal | B87: =IF($A87="","",IFERROR(VLOOKUP($A87,'Resumo por docente'!$A$8:$B$57,2,FALSE),"")) -> Inovação, Biotecnologia e Sustentabilidade Produtiva | C87: 2023 | D87: Different life cycle assessment methods and causes of variation in estimates of global warming in chicken and pork production systems: a critical systematic review | E87: 10.1016/j.livsci.2023.105320 | F87: Exterior | G87: Scopus | H87: 81 | J87: 14 | K87: =IF($A87="","",IF(OR($G87="WoS",$G87="Scopus"),IF($H87="","",IF($H87>=87.5,1,IF($H87>=75,0.875,IF($H87>=62.5,0.75,IF($H87>=50,0.625,IF($H87>=37.5,0.5,IF($H87>=25,0.375,IF($H87>=12.5,0.25,IF($H87>=0.01,0.125,0))))))))),IF($G87="Dimensions",IF(OR($I87="",$J87=""),"",MIN(IF($I87>=87.5,1,IF($I87>=75,0.875,IF($I87>=62.5,0.75,IF($I87>=50,0.625,IF($I87>=37.5,0.5,IF($I87>=25,0.375,IF($I87>=12.5,0.25,IF($I87>=0.01,0.125,0)))))))),IF($J87>=2,1,IF($J87>=1.5,0.875,IF($J87>=1,0.75,IF($J87>=0.75,0.625,IF($J87>=0.5,0.5,IF($J87>=0.25,0.375,IF($J87>=0.125,0.25,IF($J87>=0.01,0.125,0)))))))))),""))) -> 0.875 | L87: =IF($A87="","",IF(AND($C87>=2021,$C87<=2026,$E87<>"",$K87>0,LOWER($N87)="sim",LOWER($O87)="sim",OR(AND($F87="Exterior",OR($G87="WoS",$G87="Scopus")),AND($F87="Brasil",OR(AND(OR($G87="WoS",$G87="Scopus"),$H87>=50),$G87="Dimensions")))),$K87,""))
A88: Kátia Maria Cardinal | B88: =IF($A88="","",IFERROR(VLOOKUP($A88,'Resumo por docente'!$A$8:$B$57,2,FALSE),"")) -> Inovação, Biotecnologia e Sustentabilidade Produtiva | C88: 2023 | D88: Yolk and eggshell colour: are these the parameters that influence egg purchasing? A systematic review | E88: 10.1080/00439339.2023.2234341 | F88: Exterior | G88: Scopus | H88: 59 | J88: 5 | K88: =IF($A88="","",IF(OR($G88="WoS",$G88="Scopus"),IF($H88="","",IF($H88>=87.5,1,IF($H88>=75,0.875,IF($H88>=62.5,0.75,IF($H88>=50,0.625,IF($H88>=37.5,0.5,IF($H88>=25,0.375,IF($H88>=12.5,0.25,IF($H88>=0.01,0.125,0))))))))),IF($G88="Dimensions",IF(OR($I88="",$J88=""),"",MIN(IF($I88>=87.5,1,IF($I88>=75,0.875,IF($I88>=62.5,0.75,IF($I88>=50,0.625,IF($I88>=37.5,0.5,IF($I88>=25,0.375,IF($I88>=12.5,0.25,IF($I88>=0.01,0.125,0)))))))),IF($J88>=2,1,IF($J88>=1.5,0.875,IF($J88>=1,0.75,IF($J88>=0.75,0.625,IF($J88>=0.5,0.5,IF($J88>=0.25,0.375,IF($J88>=0.125,0.25,IF($J88>=0.01,0.125,0)))))))))),""))) -> 0.625 | L88: =IF($A88="","",IF(AND($C88>=2021,$C88<=2026,$E88<>"",$K88>0,LOWER($N88)="sim",LOWER($O88)="sim",OR(AND($F88="Exterior",OR($G88="WoS",$G88="Scopus")),AND($F88="Brasil",OR(AND(OR($G88="WoS",$G88="Scopus"),$H88>=50),$G88="Dimensions")))),$K88,""))
... A91: Kátia Maria Cardinal | B91: =IF($A91="","",IFERROR(VLOOKUP($A91,'Resumo por docente'!$A$8:$B$57,2,FALSE),"")) -> Inovação, Biotecnologia e Sustentabilidade Produtiva | C91: 2021 | D91: Estimation of productive losses caused by withdrawal of antibiotic growth promoter from pig diets – Meta-analysis | E91: 10.1590/1678-992X-2020-0266 | F91: Exterior | G91: Scopus | H91: 58 | J91: 8 | K91: =IF($A91="","",IF(OR($G91="WoS",$G91="Scopus"),IF($H91="","",IF($H91>=87.5,1,IF($H91>=75,0.875,IF($H91>=62.5,0.75,IF($H91>=50,0.625,IF($H91>=37.5,0.5,IF($H91>=25,0.375,IF($H91>=12.5,0.25,IF($H91>=0.01,0.125,0))))))))),IF($G91="Dimensions",IF(OR($I91="",$J91=""),"",MIN(IF($I91>=87.5,1,IF($I91>=75,0.875,IF($I91>=62.5,0.75,IF($I91>=50,0.625,IF($I91>=37.5,0.5,IF($I91>=25,0.375,IF($I91>=12.5,0.25,IF($I91>=0.01,0.125,0)))))))),IF($J91>=2,1,IF($J91>=1.5,0.875,IF($J91>=1,0.75,IF($J91>=0.75,0.625,IF($J91>=0.5,0.5,IF($J91>=0.25,0.375,IF($J91>=0.125,0.25,IF($J91>=0.01,0.125,0)))))))))),""))) -> 0.625 | L91: =IF($A91="","",IF(AND($C91>=2021,$C91<=2026,$E91<>"",$K91>0,LOWER($N91)="sim",LOWER($O91)="sim",OR(AND($F91="Exterior",OR($G91="WoS",$G91="Scopus")),AND($F91="Brasil",OR(AND(OR($G91="WoS",$G91="Scopus"),$H91>=50),$G91="Dimensions")))),$K91,""))
A92: LESSANDRO DE CONTI | B92: =IF($A92="","",IFERROR(VLOOKUP($A92,'Resumo por docente'!$A$8:$B$57,2,FALSE),"")) | C92: 2025 | D92: Struvite potential as a slow-release fertilizer for phosphorus sustainable management in Brazilian agriculture | E92: https://doi.org/10.36783/18069657rbcs20240127 | K92: =IF($A92="","",IF(OR($G92="WoS",$G92="Scopus"),IF($H92="","",IF($H92>=87.5,1,IF($H92>=75,0.875,IF($H92>=62.5,0.75,IF($H92>=50,0.625,IF($H92>=37.5,0.5,IF($H92>=25,0.375,IF($H92>=12.5,0.25,IF($H92>=0.01,0.125,0))))))))),IF($G92="Dimensions",IF(OR($I92="",$J92=""),"",MIN(IF($I92>=87.5,1,IF($I92>=75,0.875,IF($I92>=62.5,0.75,IF($I92>=50,0.625,IF($I92>=37.5,0.5,IF($I92>=25,0.375,IF($I92>=12.5,0.25,IF($I92>=0.01,0.125,0)))))))),IF($J92>=2,1,IF($J92>=1.5,0.875,IF($J92>=1,0.75,IF($J92>=0.75,0.625,IF($J92>=0.5,0.5,IF($J92>=0.25,0.375,IF($J92>=0.125,0.25,IF($J92>=0.01,0.125,0)))))))))),""))) | L92: =IF($A92="","",IF(AND($C92>=2021,$C92<=2026,$E92<>"",$K92>0,LOWER($N92)="sim",LOWER($O92)="sim",OR(AND($F92="Exterior",OR($G92="WoS",$G92="Scopus")),AND($F92="Brasil",OR(AND(OR($G92="WoS",$G92="Scopus"),$H92>=50),$G92="Dimensions")))),$K92,"")) | N92: sim
A93: LESSANDRO DE CONTI | B93: =IF($A93="","",IFERROR(VLOOKUP($A93,'Resumo por docente'!$A$8:$B$57,2,FALSE),"")) | C93: 2024 | D93: Annual Urea Nitrogen Contribution to the Nutrition of Cabernet Sauvignon Grapevine Grown in Sandy and Clayey Soil | E93: https://doi.org/10.3390/agronomy14010101 | K93: =IF($A93="","",IF(OR($G93="WoS",$G93="Scopus"),IF($H93="","",IF($H93>=87.5,1,IF($H93>=75,0.875,IF($H93>=62.5,0.75,IF($H93>=50,0.625,IF($H93>=37.5,0.5,IF($H93>=25,0.375,IF($H93>=12.5,0.25,IF($H93>=0.01,0.125,0))))))))),IF($G93="Dimensions",IF(OR($I93="",$J93=""),"",MIN(IF($I93>=87.5,1,IF($I93>=75,0.875,IF($I93>=62.5,0.75,IF($I93>=50,0.625,IF($I93>=37.5,0.5,IF($I93>=25,0.375,IF($I93>=12.5,0.25,IF($I93>=0.01,0.125,0)))))))),IF($J93>=2,1,IF($J93>=1.5,0.875,IF($J93>=1,0.75,IF($J93>=0.75,0.625,IF($J93>=0.5,0.5,IF($J93>=0.25,0.375,IF($J93>=0.125,0.25,IF($J93>=0.01,0.125,0)))))))))),""))) | L93: =IF($A93="","",IF(AND($C93>=2021,$C93<=2026,$E93<>"",$K93>0,LOWER($N93)="sim",LOWER($O93)="sim",OR(AND($F93="Exterior",OR($G93="WoS",$G93="Scopus")),AND($F93="Brasil",OR(AND(OR($G93="WoS",$G93="Scopus"),$H93>=50),$G93="Dimensions")))),$K93,"")) | N93: sim
A94: LESSANDRO DE CONTI | B94: =IF($A94="","",IFERROR(VLOOKUP($A94,'Resumo por docente'!$A$8:$B$57,2,FALSE),"")) | C94: 2024 | D94: Cu Concentration in Vegetable-Cultivated Soil: Comparison Between Open Fields and Protected Environments in Brazil | E94: https://doi.org/10.3390/horticulturae10111183 | K94: =IF($A94="","",IF(OR($G94="WoS",$G94="Scopus"),IF($H94="","",IF($H94>=87.5,1,IF($H94>=75,0.875,IF($H94>=62.5,0.75,IF($H94>=50,0.625,IF($H94>=37.5,0.5,IF($H94>=25,0.375,IF($H94>=12.5,0.25,IF($H94>=0.01,0.125,0))))))))),IF($G94="Dimensions",IF(OR($I94="",$J94=""),"",MIN(IF($I94>=87.5,1,IF($I94>=75,0.875,IF($I94>=62.5,0.75,IF($I94>=50,0.625,IF($I94>=37.5,0.5,IF($I94>=25,0.375,IF($I94>=12.5,0.25,IF($I94>=0.01,0.125,0)))))))),IF($J94>=2,1,IF($J94>=1.5,0.875,IF($J94>=1,0.75,IF($J94>=0.75,0.625,IF($J94>=0.5,0.5,IF($J94>=0.25,0.375,IF($J94>=0.125,0.25,IF($J94>=0.01,0.125,0)))))))))),""))) | L94: =IF($A94="","",IF(AND($C94>=2021,$C94<=2026,$E94<>"",$K94>0,LOWER($N94)="sim",LOWER($O94)="sim",OR(AND($F94="Exterior",OR($G94="WoS",$G94="Scopus")),AND($F94="Brasil",OR(AND(OR($G94="WoS",$G94="Scopus"),$H94>=50),$G94="Dimensions")))),$K94,"")) | N94: sim
A95: LESSANDRO DE CONTI | B95: =IF($A95="","",IFERROR(VLOOKUP($A95,'Resumo por docente'!$A$8:$B$57,2,FALSE),"")) | C95: 2024 | D95: Qualidade fisiolÃ³gica de sementes, desempenho a campo e viabilidade econÃ´mica da cultura da soja submetida Ã inoculaÃ§Ã£o de sementes com diferentes produtos biolÃ³gicos | E95: https://doi.org/10.26669/2448-4091.2024.425 | K95: =IF($A95="","",IF(OR($G95="WoS",$G95="Scopus"),IF($H95="","",IF($H95>=87.5,1,IF($H95>=75,0.875,IF($H95>=62.5,0.75,IF($H95>=50,0.625,IF($H95>=37.5,0.5,IF($H95>=25,0.375,IF($H95>=12.5,0.25,IF($H95>=0.01,0.125,0))))))))),IF($G95="Dimensions",IF(OR($I95="",$J95=""),"",MIN(IF($I95>=87.5,1,IF($I95>=75,0.875,IF($I95>=62.5,0.75,IF($I95>=50,0.625,IF($I95>=37.5,0.5,IF($I95>=25,0.375,IF($I95>=12.5,0.25,IF($I95>=0.01,0.125,0)))))))),IF($J95>=2,1,IF($J95>=1.5,0.875,IF($J95>=1,0.75,IF($J95>=0.75,0.625,IF($J95>=0.5,0.5,IF($J95>=0.25,0.375,IF($J95>=0.125,0.25,IF($J95>=0.01,0.125,0)))))))))),""))) | L95: =IF($A95="","",IF(AND($C95>=2021,$C95<=2026,$E95<>"",$K95>0,LOWER($N95)="sim",LOWER($O95)="sim",OR(AND($F95="Exterior",OR($G95="WoS",$G95="Scopus")),AND($F95="Brasil",OR(AND(OR($G95="WoS",$G95="Scopus"),$H95>=50),$G95="Dimensions")))),$K95,"")) | N95: sim
A96: LESSANDRO DE CONTI | B96: =IF($A96="","",IFERROR(VLOOKUP($A96,'Resumo por docente'!$A$8:$B$57,2,FALSE),"")) | C96: 2023 | D96: Phosphorus critical levels in soil and grapevine leaves for South Brazil vineyards: A Bayesian approach | E96: https://doi.org/10.1016/j.eja.2023.126752 | K96: =IF($A96="","",IF(OR($G96="WoS",$G96="Scopus"),IF($H96="","",IF($H96>=87.5,1,IF($H96>=75,0.875,IF($H96>=62.5,0.75,IF($H96>=50,0.625,IF($H96>=37.5,0.5,IF($H96>=25,0.375,IF($H96>=12.5,0.25,IF($H96>=0.01,0.125,0))))))))),IF($G96="Dimensions",IF(OR($I96="",$J96=""),"",MIN(IF($I96>=87.5,1,IF($I96>=75,0.875,IF($I96>=62.5,0.75,IF($I96>=50,0.625,IF($I96>=37.5,0.5,IF($I96>=25,0.375,IF($I96>=12.5,0.25,IF($I96>=0.01,0.125,0)))))))),IF($J96>=2,1,IF($J96>=1.5,0.875,IF($J96>=1,0.75,IF($J96>=0.75,0.625,IF($J96>=0.5,0.5,IF($J96>=0.25,0.375,IF($J96>=0.125,0.25,IF($J96>=0.01,0.125,0)))))))))),""))) | L96: =IF($A96="","",IF(AND($C96>=2021,$C96<=2026,$E96<>"",$K96>0,LOWER($N96)="sim",LOWER($O96)="sim",OR(AND($F96="Exterior",OR($G96="WoS",$G96="Scopus")),AND($F96="Brasil",OR(AND(OR($G96="WoS",$G96="Scopus"),$H96>=50),$G96="Dimensions")))),$K96,"")) | N96: sim
A97: LESSANDRO DE CONTI | B97: =IF($A97="","",IFERROR(VLOOKUP($A97,'Resumo por docente'!$A$8:$B$57,2,FALSE),"")) | C97: 2023 | D97: Phytoremediation of Cu-contaminated vineyard soils in Brazil: A compendium of Brazilian pot studies | E97: https://doi.org/10.1002/jeq2.20503 | K97: =IF($A97="","",IF(OR($G97="WoS",$G97="Scopus"),IF($H97="","",IF($H97>=87.5,1,IF($H97>=75,0.875,IF($H97>=62.5,0.75,IF($H97>=50,0.625,IF($H97>=37.5,0.5,IF($H97>=25,0.375,IF($H97>=12.5,0.25,IF($H97>=0.01,0.125,0))))))))),IF($G97="Dimensions",IF(OR($I97="",$J97=""),"",MIN(IF($I97>=87.5,1,IF($I97>=75,0.875,IF($I97>=62.5,0.75,IF($I97>=50,0.625,IF($I97>=37.5,0.5,IF($I97>=25,0.375,IF($I97>=12.5,0.25,IF($I97>=0.01,0.125,0)))))))),IF($J97>=2,1,IF($J97>=1.5,0.875,IF($J97>=1,0.75,IF($J97>=0.75,0.625,IF($J97>=0.5,0.5,IF($J97>=0.25,0.375,IF($J97>=0.125,0.25,IF($J97>=0.01,0.125,0)))))))))),""))) | L97: =IF($A97="","",IF(AND($C97>=2021,$C97<=2026,$E97<>"",$K97>0,LOWER($N97)="sim",LOWER($O97)="sim",OR(AND($F97="Exterior",OR($G97="WoS",$G97="Scopus")),AND($F97="Brasil",OR(AND(OR($G97="WoS",$G97="Scopus"),$H97>=50),$G97="Dimensions")))),$K97,"")) | N97: sim
A98: LESSANDRO DE CONTI | B98: =IF($A98="","",IFERROR(VLOOKUP($A98,'Resumo por docente'!$A$8:$B$57,2,FALSE),"")) | C98: 2022 | D98: Long-Term Effects of Animal Manures on Nutrient Recovery and Soil Quality in Acid Typic Hapludalf under No-Till Conditions | E98: https://doi.org/10.3390/agronomy12020243 | K98: =IF($A98="","",IF(OR($G98="WoS",$G98="Scopus"),IF($H98="","",IF($H98>=87.5,1,IF($H98>=75,0.875,IF($H98>=62.5,0.75,IF($H98>=50,0.625,IF($H98>=37.5,0.5,IF($H98>=25,0.375,IF($H98>=12.5,0.25,IF($H98>=0.01,0.125,0))))))))),IF($G98="Dimensions",IF(OR($I98="",$J98=""),"",MIN(IF($I98>=87.5,1,IF($I98>=75,0.875,IF($I98>=62.5,0.75,IF($I98>=50,0.625,IF($I98>=37.5,0.5,IF($I98>=25,0.375,IF($I98>=12.5,0.25,IF($I98>=0.01,0.125,0)))))))),IF($J98>=2,1,IF($J98>=1.5,0.875,IF($J98>=1,0.75,IF($J98>=0.75,0.625,IF($J98>=0.5,0.5,IF($J98>=0.25,0.375,IF($J98>=0.125,0.25,IF($J98>=0.01,0.125,0)))))))))),""))) | L98: =IF($A98="","",IF(AND($C98>=2021,$C98<=2026,$E98<>"",$K98>0,LOWER($N98)="sim",LOWER($O98)="sim",OR(AND($F98="Exterior",OR($G98="WoS",$G98="Scopus")),AND($F98="Brasil",OR(AND(OR($G98="WoS",$G98="Scopus"),$H98>=50),$G98="Dimensions")))),$K98,"")) | N98: sim
A99: LESSANDRO DE CONTI | B99: =IF($A99="","",IFERROR(VLOOKUP($A99,'Resumo por docente'!$A$8:$B$57,2,FALSE),"")) | C99: 2022 | D99: Plant species and pH dependent responses to copper toxicity | E99: https://doi.org/10.1016/j.envexpbot.2022.104791 | K99: =IF($A99="","",IF(OR($G99="WoS",$G99="Scopus"),IF($H99="","",IF($H99>=87.5,1,IF($H99>=75,0.875,IF($H99>=62.5,0.75,IF($H99>=50,0.625,IF($H99>=37.5,0.5,IF($H99>=25,0.375,IF($H99>=12.5,0.25,IF($H99>=0.01,0.125,0))))))))),IF($G99="Dimensions",IF(OR($I99="",$J99=""),"",MIN(IF($I99>=87.5,1,IF($I99>=75,0.875,IF($I99>=62.5,0.75,IF($I99>=50,0.625,IF($I99>=37.5,0.5,IF($I99>=25,0.375,IF($I99>=12.5,0.25,IF($I99>=0.01,0.125,0)))))))),IF($J99>=2,1,IF($J99>=1.5,0.875,IF($J99>=1,0.75,IF($J99>=0.75,0.625,IF($J99>=0.5,0.5,IF($J99>=0.25,0.375,IF($J99>=0.125,0.25,IF($J99>=0.01,0.125,0)))))))))),""))) | L99: =IF($A99="","",IF(AND($C99>=2021,$C99<=2026,$E99<>"",$K99>0,LOWER($N99)="sim",LOWER($O99)="sim",OR(AND($F99="Exterior",OR($G99="WoS",$G99="Scopus")),AND($F99="Brasil",OR(AND(OR($G99="WoS",$G99="Scopus"),$H99>=50),$G99="Dimensions")))),$K99,"")) | N99: sim
A100: LESSANDRO DE CONTI | B100: =IF($A100="","",IFERROR(VLOOKUP($A100,'Resumo por docente'!$A$8:$B$57,2,FALSE),"")) | C100: 2022 | D100: Throwing Copper Around: How Plants Control Uptake, Distribution, and Accumulation of Copper | E100: https://doi.org/10.3390/agronomy12050994 | K100: =IF($A100="","",IF(OR($G100="WoS",$G100="Scopus"),IF($H100="","",IF($H100>=87.5,1,IF($H100>=75,0.875,IF($H100>=62.5,0.75,IF($H100>=50,0.625,IF($H100>=37.5,0.5,IF($H100>=25,0.375,IF($H100>=12.5,0.25,IF($H100>=0.01,0.125,0))))))))),IF($G100="Dimensions",IF(OR($I100="",$J100=""),"",MIN(IF($I100>=87.5,1,IF($I100>=75,0.875,IF($I100>=62.5,0.75,IF($I100>=50,0.625,IF($I100>=37.5,0.5,IF($I100>=25,0.375,IF($I100>=12.5,0.25,IF($I100>=0.01,0.125,0)))))))),IF($J100>=2,1,IF($J100>=1.5,0.875,IF($J100>=1,0.75,IF($J100>=0.75,0.625,IF($J100>=0.5,0.5,IF($J100>=0.25,0.375,IF($J100>=0.125,0.25,IF($J100>=0.01,0.125,0)))))))))),""))) | L100: =IF($A100="","",IF(AND($C100>=2021,$C100<=2026,$E100<>"",$K100>0,LOWER($N100)="sim",LOWER($O100)="sim",OR(AND($F100="Exterior",OR($G100="WoS",$G100="Scopus")),AND($F100="Brasil",OR(AND(OR($G100="WoS",$G100="Scopus"),$H100>=50),$G100="Dimensions")))),$K100,"")) | N100: sim
A101: LESSANDRO DE CONTI | B101: =IF($A101="","",IFERROR(VLOOKUP($A101,'Resumo por docente'!$A$8:$B$57,2,FALSE),"")) | C101: 2022 | D101: Nitrogen Critical Level in Leaves in -Chardonnay? and -Pinot Noir? Grapevines to Adequate Yield and Quality Must | E101: https://doi.org/10.3390/agronomy12051132 | K101: =IF($A101="","",IF(OR($G101="WoS",$G101="Scopus"),IF($H101="","",IF($H101>=87.5,1,IF($H101>=75,0.875,IF($H101>=62.5,0.75,IF($H101>=50,0.625,IF($H101>=37.5,0.5,IF($H101>=25,0.375,IF($H101>=12.5,0.25,IF($H101>=0.01,0.125,0))))))))),IF($G101="Dimensions",IF(OR($I101="",$J101=""),"",MIN(IF($I101>=87.5,1,IF($I101>=75,0.875,IF($I101>=62.5,0.75,IF($I101>=50,0.625,IF($I101>=37.5,0.5,IF($I101>=25,0.375,IF($I101>=12.5,0.25,IF($I101>=0.01,0.125,0)))))))),IF($J101>=2,1,IF($J101>=1.5,0.875,IF($J101>=1,0.75,IF($J101>=0.75,0.625,IF($J101>=0.5,0.5,IF($J101>=0.25,0.375,IF($J101>=0.125,0.25,IF($J101>=0.01,0.125,0)))))))))),""))) | L101: =IF($A101="","",IF(AND($C101>=2021,$C101<=2026,$E101<>"",$K101>0,LOWER($N101)="sim",LOWER($O101)="sim",OR(AND($F101="Exterior",OR($G101="WoS",$G101="Scopus")),AND($F101="Brasil",OR(AND(OR($G101="WoS",$G101="Scopus"),$H101>=50),$G101="Dimensions")))),$K101,"")) | N101: sim
A102: LESSANDRO DE CONTI | B102: =IF($A102="","",IFERROR(VLOOKUP($A102,'Resumo por docente'!$A$8:$B$57,2,FALSE),"")) | C102: 2022 | D102: The tolerance of grapevine rootstocks to copper excess and to the use of calcium and phosphorus to mitigate its phytotoxicity | E102: https://doi.org/10.1007/s11356-022-21515-0 | K102: =IF($A102="","",IF(OR($G102="WoS",$G102="Scopus"),IF($H102="","",IF($H102>=87.5,1,IF($H102>=75,0.875,IF($H102>=62.5,0.75,IF($H102>=50,0.625,IF($H102>=37.5,0.5,IF($H102>=25,0.375,IF($H102>=12.5,0.25,IF($H102>=0.01,0.125,0))))))))),IF($G102="Dimensions",IF(OR($I102="",$J102=""),"",MIN(IF($I102>=87.5,1,IF($I102>=75,0.875,IF($I102>=62.5,0.75,IF($I102>=50,0.625,IF($I102>=37.5,0.5,IF($I102>=25,0.375,IF($I102>=12.5,0.25,IF($I102>=0.01,0.125,0)))))))),IF($J102>=2,1,IF($J102>=1.5,0.875,IF($J102>=1,0.75,IF($J102>=0.75,0.625,IF($J102>=0.5,0.5,IF($J102>=0.25,0.375,IF($J102>=0.125,0.25,IF($J102>=0.01,0.125,0)))))))))),""))) | L102: =IF($A102="","",IF(AND($C102>=2021,$C102<=2026,$E102<>"",$K102>0,LOWER($N102)="sim",LOWER($O102)="sim",OR(AND($F102="Exterior",OR($G102="WoS",$G102="Scopus")),AND($F102="Brasil",OR(AND(OR($G102="WoS",$G102="Scopus"),$H102>=50),$G102="Dimensions")))),$K102,"")) | N102: sim
A103: LESSANDRO DE CONTI | B103: =IF($A103="","",IFERROR(VLOOKUP($A103,'Resumo por docente'!$A$8:$B$57,2,FALSE),"")) | C103: 2022 | D103: Physiological and biochemical characterization of copper-toxicity tolerance mechanism in grass species native to Pampa Biome and Atlantic Forest for use in phytoremediation | E103: https://doi.org/10.1007/s11356-022-22570-3 | K103: =IF($A103="","",IF(OR($G103="WoS",$G103="Scopus"),IF($H103="","",IF($H103>=87.5,1,IF($H103>=75,0.875,IF($H103>=62.5,0.75,IF($H103>=50,0.625,IF($H103>=37.5,0.5,IF($H103>=25,0.375,IF($H103>=12.5,0.25,IF($H103>=0.01,0.125,0))))))))),IF($G103="Dimensions",IF(OR($I103="",$J103=""),"",MIN(IF($I103>=87.5,1,IF($I103>=75,0.875,IF($I103>=62.5,0.75,IF($I103>=50,0.625,IF($I103>=37.5,0.5,IF($I103>=25,0.375,IF($I103>=12.5,0.25,IF($I103>=0.01,0.125,0)))))))),IF($J103>=2,1,IF($J103>=1.5,0.875,IF($J103>=1,0.75,IF($J103>=0.75,0.625,IF($J103>=0.5,0.5,IF($J103>=0.25,0.375,IF($J103>=0.125,0.25,IF($J103>=0.01,0.125,0)))))))))),""))) | L103: =IF($A103="","",IF(AND($C103>=2021,$C103<=2026,$E103<>"",$K103>0,LOWER($N103)="sim",LOWER($O103)="sim",OR(AND($F103="Exterior",OR($G103="WoS",$G103="Scopus")),AND($F103="Brasil",OR(AND(OR($G103="WoS",$G103="Scopus"),$H103>=50),$G103="Dimensions")))),$K103,"")) | N103: sim
A104: LESSANDRO DE CONTI | B104: =IF($A104="","",IFERROR(VLOOKUP($A104,'Resumo por docente'!$A$8:$B$57,2,FALSE),"")) | C104: 2022 | D104: PARÃ‚METROS PRODUTIVOS DE DIFERENTES HÃ_x008d_BRIDOS DE MILHO NA SAFRA 2019/2020 DA REGIÃƒO NOROESTE DO ESTADO DO RIO GRANDE DO SUL | K104: =IF($A104="","",IF(OR($G104="WoS",$G104="Scopus"),IF($H104="","",IF($H104>=87.5,1,IF($H104>=75,0.875,IF($H104>=62.5,0.75,IF($H104>=50,0.625,IF($H104>=37.5,0.5,IF($H104>=25,0.375,IF($H104>=12.5,0.25,IF($H104>=0.01,0.125,0))))))))),IF($G104="Dimensions",IF(OR($I104="",$J104=""),"",MIN(IF($I104>=87.5,1,IF($I104>=75,0.875,IF($I104>=62.5,0.75,IF($I104>=50,0.625,IF($I104>=37.5,0.5,IF($I104>=25,0.375,IF($I104>=12.5,0.25,IF($I104>=0.01,0.125,0)))))))),IF($J104>=2,1,IF($J104>=1.5,0.875,IF($J104>=1,0.75,IF($J104>=0.75,0.625,IF($J104>=0.5,0.5,IF($J104>=0.25,0.375,IF($J104>=0.125,0.25,IF($J104>=0.01,0.125,0)))))))))),""))) | L104: =IF($A104="","",IF(AND($C104>=2021,$C104<=2026,$E104<>"",$K104>0,LOWER($N104)="sim",LOWER($O104)="sim",OR(AND($F104="Exterior",OR($G104="WoS",$G104="Scopus")),AND($F104="Brasil",OR(AND(OR($G104="WoS",$G104="Scopus"),$H104>=50),$G104="Dimensions")))),$K104,"")) | N104: sim
A105: LESSANDRO DE CONTI | B105: =IF($A105="","",IFERROR(VLOOKUP($A105,'Resumo por docente'!$A$8:$B$57,2,FALSE),"")) | C105: 2022 | D105: Efeito de diferentes doses de zinco na qualidade de sementes de diferentes cultivares de trigo | E105: https://doi.org/10.35819/scientiatec.v9i2.5192 | K105: =IF($A105="","",IF(OR($G105="WoS",$G105="Scopus"),IF($H105="","",IF($H105>=87.5,1,IF($H105>=75,0.875,IF($H105>=62.5,0.75,IF($H105>=50,0.625,IF($H105>=37.5,0.5,IF($H105>=25,0.375,IF($H105>=12.5,0.25,IF($H105>=0.01,0.125,0))))))))),IF($G105="Dimensions",IF(OR($I105="",$J105=""),"",MIN(IF($I105>=87.5,1,IF($I105>=75,0.875,IF($I105>=62.5,0.75,IF($I105>=50,0.625,IF($I105>=37.5,0.5,IF($I105>=25,0.375,IF($I105>=12.5,0.25,IF($I105>=0.01,0.125,0)))))))),IF($J105>=2,1,IF($J105>=1.5,0.875,IF($J105>=1,0.75,IF($J105>=0.75,0.625,IF($J105>=0.5,0.5,IF($J105>=0.25,0.375,IF($J105>=0.125,0.25,IF($J105>=0.01,0.125,0)))))))))),""))) | L105: =IF($A105="","",IF(AND($C105>=2021,$C105<=2026,$E105<>"",$K105>0,LOWER($N105)="sim",LOWER($O105)="sim",OR(AND($F105="Exterior",OR($G105="WoS",$G105="Scopus")),AND($F105="Brasil",OR(AND(OR($G105="WoS",$G105="Scopus"),$H105>=50),$G105="Dimensions")))),$K105,"")) | N105: sim
A106: Luana Mendes dos Santos | B106: =IF($A106="","",IFERROR(VLOOKUP($A106,'Resumo por docente'!$A$8:$B$57,2,FALSE),"")) | C106: 2026 | D106: Remote Sensing of Nematode Stress in Coffee: UAV-Based Multispectral and Thermal Imaging Approaches | E106: https://doi.org/10.3390/agriengineering8010022 | K106: =IF($A106="","",IF(OR($G106="WoS",$G106="Scopus"),IF($H106="","",IF($H106>=87.5,1,IF($H106>=75,0.875,IF($H106>=62.5,0.75,IF($H106>=50,0.625,IF($H106>=37.5,0.5,IF($H106>=25,0.375,IF($H106>=12.5,0.25,IF($H106>=0.01,0.125,0))))))))),IF($G106="Dimensions",IF(OR($I106="",$J106=""),"",MIN(IF($I106>=87.5,1,IF($I106>=75,0.875,IF($I106>=62.5,0.75,IF($I106>=50,0.625,IF($I106>=37.5,0.5,IF($I106>=25,0.375,IF($I106>=12.5,0.25,IF($I106>=0.01,0.125,0)))))))),IF($J106>=2,1,IF($J106>=1.5,0.875,IF($J106>=1,0.75,IF($J106>=0.75,0.625,IF($J106>=0.5,0.5,IF($J106>=0.25,0.375,IF($J106>=0.125,0.25,IF($J106>=0.01,0.125,0)))))))))),""))) | L106: =IF($A106="","",IF(AND($C106>=2021,$C106<=2026,$E106<>"",$K106>0,LOWER($N106)="sim",LOWER($O106)="sim",OR(AND($F106="Exterior",OR($G106="WoS",$G106="Scopus")),AND($F106="Brasil",OR(AND(OR($G106="WoS",$G106="Scopus"),$H106>=50),$G106="Dimensions")))),$K106,""))
...

Sheet Destaques e PTTs
A1: Docente | B1: Linha de pesquisa/atuação | C1: Tipo de indicação | D1: Ano | E1: Tipologia oficial do PTT / natureza do destaque | F1: Título da experiência/produto | G1: Impacto na | H1: Dimensão(ões) predominante(s) | I1: Palavras-chave | J1: Objetivo/foco | K1: Descrição dos impactos e evidências | L1: ODS e metas | M1: Local de aplicação | N1: Beneficiários | O1: Parcerias | P1: Financiamento | Q1: Potencial de replicabilidade | R1: Justificativa de aderência | S1: Link de documentos comprobatórios | T1: Link do produto | U1: No Lattes? | V1: Ficha Impacto Real completa? | W1: Validação | X1: Outros DP envolvidos
A2: RANGEL FERNANDES PACHECO | B2: =IF($A2="","",IFERROR(VLOOKUP($A2,'Resumo por docente'!$A$8:$B$57,2,FALSE),"")) -> Inovação, Biotecnologia e Sustentabilidade Produtiva | C2: Destaque 1 | D2: 2025 | E2: Livro ou capítulo (somente destaque) | F2: Sistemas integrados no contexto das mudanças climáticas | G2: Ciência e Sociedade | H2: Ambiental | I2: Aquecimento global, Mudança Climática, Sistemas integrados de producao | J2: Capítulo de livro voltado a apresentar alguns impactos dos sistemas integrados agropecuários no contexto das mudanças climáticas. | K2: Livro publicado | L2: 1 e 2 | M2: Brasília/DF | N2: Setor agropecuário | O2: Embrapa RO | P2: Não | Q2: Não se aplica | R2: Aderente a linha Inovação, Biotecnologia e Sustentabilidade Produtiva | S2: https://www.embrapa.br/busca-de-publicacoes/-/publicacao/1178442/sistemas-integrados-no-contexto-das-mudancas-climaticas | T2: https://www.embrapa.br/busca-de-publicacoes/-/publicacao/1178442/sistemas-integrados-no-contexto-das-mudancas-climaticas | U2: sim | V2: sim | W2: =IF($A2="","",IF(OR($C2="",$D2="",$E2="",$F2=""),"INCOMPLETO",IF(OR($D2<2021,$D2>2026),"ANO FORA DA JANELA",IF(OR(LOWER($U2)<>"sim",LOWER($V2)<>"sim",$G2="",$H2="",$J2="",$K2="",$M2="",$N2="",$Q2="",$R2="",$S2=""),"INCOMPLETO",IF(LEFT($C2,3)="PTT",IF(COUNTIF('Estratos e PTTs'!$B$15:$B$30,$E2)=0,"TIPO PTT INVÁLIDO","OK"),"OK"))))) -> OK
A3: RANGEL FERNANDES PACHECO | B3: =IF($A3="","",IFERROR(VLOOKUP($A3,'Resumo por docente'!$A$8:$B$57,2,FALSE),"")) -> Inovação, Biotecnologia e Sustentabilidade Produtiva | C3: Destaque 2 | D3: 2025 | E3: Livro ou capítulo (somente destaque) | F3: Relação Ambiente-Planta-Animal em Sistemas Integrados. | G3: Ciência e Sociedade | H3: Ambiental | I3: Consumo alimentar dos ruminantes | J3: Capítulo de livro destinado a mostrar o que a ciência tem emcontrado sobre a relação ambiente-planta-animal em Sistemas Integrados. | K3: Livro publicado | L3: 1 e 2 | M3: Brasília/DF | N3: Setor agropecuário | O3: Embrapa RO | P3: Não | Q3: Não se aplica | R3: Aderente a linha Inovação, Biotecnologia e Sustentabilidade Produtiva | S3: https://www.embrapa.br/busca-de-publicacoes/-/publicacao/1178447/relacao-ambiente-planta-animal-em-sistemas-integrados | T3: https://www.embrapa.br/busca-de-publicacoes/-/publicacao/1178447/relacao-ambiente-planta-animal-em-sistemas-integrados | U3: sim | V3: sim | W3: =IF($A3="","",IF(OR($C3="",$D3="",$E3="",$F3=""),"INCOMPLETO",IF(OR($D3<2021,$D3>2026),"ANO FORA DA JANELA",IF(OR(LOWER($U3)<>"sim",LOWER($V3)<>"sim",$G3="",$H3="",$J3="",$K3="",$M3="",$N3="",$Q3="",$R3="",$S3=""),"INCOMPLETO",IF(LEFT($C3,3)="PTT",IF(COUNTIF('Estratos e PTTs'!$B$15:$B$30,$E3)=0,"TIPO PTT INVÁLIDO","OK"),"OK"))))) -> OK
A4: RANGEL FERNANDES PACHECO | B4: =IF($A4="","",IFERROR(VLOOKUP($A4,'Resumo por docente'!$A$8:$B$57,2,FALSE),"")) -> Inovação, Biotecnologia e Sustentabilidade Produtiva | C4: PTT adicional 1 | D4: 2025 | E4: Produto bibliográfico | F4: Forragicultura: Base da Pecuária Sustentável | G4: Ciência e Sociedade | H4: Múltiplas - especificar em K | I4: Agropecuária, Sustentabilidade Ambiental, Pastagens, Pecuária | J4: Livro destinado para estudantes e técnicos da área de pastagens. | K4: Livro publicado | L4: 1, 2 e 4 | M4: Frederico Westphalen/RS | N4: Estudantes e técnicos do segmento agropecuário | O4: não | P4: não | Q4: não se aplica | R4: Aderente a linha Inovação, Biotecnologia e Sustentabilidade Produtiva | S4: https://drive.google.com/file/d/1yDzjHUmogNWsiqyuyKvurF4rlJcnnLlu/view | T4: https://drive.google.com/file/d/1yDzjHUmogNWsiqyuyKvurF4rlJcnnLlu/view | U4: sim | V4: sim | W4: =IF($A4="","",IF(OR($C4="",$D4="",$E4="",$F4=""),"INCOMPLETO",IF(OR($D4<2021,$D4>2026),"ANO FORA DA JANELA",IF(OR(LOWER($U4)<>"sim",LOWER($V4)<>"sim",$G4="",$H4="",$J4="",$K4="",$M4="",$N4="",$Q4="",$R4="",$S4=""),"INCOMPLETO",IF(LEFT($C4,3)="PTT",IF(COUNTIF('Estratos e PTTs'!$B$15:$B$30,$E4)=0,"TIPO PTT INVÁLIDO","OK"),"OK"))))) -> OK
A5: RANGEL FERNANDES PACHECO | B5: =IF($A5="","",IFERROR(VLOOKUP($A5,'Resumo por docente'!$A$8:$B$57,2,FALSE),"")) -> Inovação, Biotecnologia e Sustentabilidade Produtiva | C5: PTT adicional 2 | D5: 2026 | E5: Produto bibliográfico | F5: SISTEMAS INTELIGENTES APLICADOS NA PREDIÇÃO DE PRENHEZ DE NOVILHAS DE DIFERENTES GRUPOS GENÉTICOS ACASALADAS AOS 14-16 MESES DE IDADE | G5: Ciência e Sociedade | H5: Múltiplas - especificar em K | I5: análise de componentes principais, aprendizado de máquina, árvore de decisão, escore de condição corporal, peso corporal | J5: Artigo de divulgação técnica voltado a predição de prenhez em novilhas de corte, identificando as variáveis de maior impacto. | K5: Artigo publicado. | L5: 1 e 2 | M5: Cascavel/PR | N5: Pesquisadores do setor pecuário | O5: não | P5: não | Q5: não se aplica | R5: Aderente a linha Inovação, Biotecnologia e Sustentabilidade Produtiva | S5: https://themaetscientia.fag.edu.br/index.php/RTES/article/view/2414/2011 | T5: https://themaetscientia.fag.edu.br/index.php/RTES/article/view/2414/2011 | U5: sim | V5: sim | W5: =IF($A5="","",IF(OR($C5="",$D5="",$E5="",$F5=""),"INCOMPLETO",IF(OR($D5<2021,$D5>2026),"ANO FORA DA JANELA",IF(OR(LOWER($U5)<>"sim",LOWER($V5)<>"sim",$G5="",$H5="",$J5="",$K5="",$M5="",$N5="",$Q5="",$R5="",$S5=""),"INCOMPLETO",IF(LEFT($C5,3)="PTT",IF(COUNTIF('Estratos e PTTs'!$B$15:$B$30,$E5)=0,"TIPO PTT INVÁLIDO","OK"),"OK"))))) -> OK
A6: RANGEL FERNANDES PACHECO | B6: =IF($A6="","",IFERROR(VLOOKUP($A6,'Resumo por docente'!$A$8:$B$57,2,FALSE),"")) -> Inovação, Biotecnologia e Sustentabilidade Produtiva | C6: PTT adicional 3 | D6: 2025 | E6: Produto bibliográfico | F6: Pastagens e sua Importância Ecológica e Econômica | G6: Ciência e Sociedade | H6: Ambiental | I6: alimentos, serviços ecossistêmicos | J6: Capítulo de livro voltado a compreensão da importância das pastagens no segmento agropecuário brasileiro. | K6: Capítulo de livro | L6: 1, 2 e 4 | M6: Frederico Westphalen/RS | N6: Estudantes e técnicos do segmento agropecuário | O6: não | P6: não | Q6: não se aplica | R6: Aderente a linha Inovação, Biotecnologia e Sustentabilidade Produtiva | S6: https://drive.google.com/file/d/1vwIDQ6lMsAjN4vNzT2_5B9lQWWCojmjt/view?usp=sharing | T6: https://drive.google.com/file/d/1vwIDQ6lMsAjN4vNzT2_5B9lQWWCojmjt/view?usp=sharing | U6: sim | V6: sim | W6: =IF($A6="","",IF(OR($C6="",$D6="",$E6="",$F6=""),"INCOMPLETO",IF(OR($D6<2021,$D6>2026),"ANO FORA DA JANELA",IF(OR(LOWER($U6)<>"sim",LOWER($V6)<>"sim",$G6="",$H6="",$J6="",$K6="",$M6="",$N6="",$Q6="",$R6="",$S6=""),"INCOMPLETO",IF(LEFT($C6,3)="PTT",IF(COUNTIF('Estratos e PTTs'!$B$15:$B$30,$E6)=0,"TIPO PTT INVÁLIDO","OK"),"OK"))))) -> OK
A7: ANDERSON SALDANHA BUENO | B7: =IF($A7="","",IFERROR(VLOOKUP($A7,'Resumo por docente'!$A$8:$B$57,2,FALSE),"")) -> Biodiversidade, Saúde Ambiental e Conservação | C7: Destaque 1 | D7: 2026 | E7: Produto bibliográfico | F7: Pequenos fragmentos florestais podem conservar mais aves quando o entorno é favorável | G7: Ciência e Sociedade | H7: Ambiental | I7: conservação da biodiversidade, fragmentação do habitat, florestas tropicais | J7: Divulgar estratégias de manejo em propriedades rurais que contribuam para a conservação de aves em fragmentos florestais. | K7: Textos em jornais de notícias/revistas | L7: 15 | M7: Global | N7: Gestores públicos, órgãos de conservação da natureza, proprierários rurais e cientistas | O7: University of East Anglia (Reino Unido) e Slippery Rock University (Estados Unidos) | P7: não | Q7: não se aplica | S7: https://doi.org/10.64628/ADE.whu7r59mf | T7: https://doi.org/10.64628/ADE.whu7r59mf | U7: sim | W7: =IF($A7="","",IF(OR($C7="",$D7="",$E7="",$F7=""),"INCOMPLETO",IF(OR($D7<2021,$D7>2026),"ANO FORA DA JANELA",IF(OR(LOWER($U7)<>"sim",LOWER($V7)<>"sim",$G7="",$H7="",$J7="",$K7="",$M7="",$N7="",$Q7="",$R7="",$S7=""),"INCOMPLETO",IF(LEFT($C7,3)="PTT",IF(COUNTIF('Estratos e PTTs'!$B$15:$B$30,$E7)=0,"TIPO PTT INVÁLIDO","OK"),"OK"))))) -> INCOMPLETO
A8: Volnei Luiz Meneghetti | B8: =IF($A8="","",IFERROR(VLOOKUP($A8,'Resumo por docente'!$A$8:$B$57,2,FALSE),"")) -> Inovação, Biotecnologia e Sustentabilidade Produtiva | C8: Destaque 1 | D8: 2021 | E8: Produto bibliográfico | F8: PROTOCOLO TECNOLÓGICO-OPERACIONAL PARA ARMAZENAMENTO E QUALIDADE DE TRIGO PARA INDÚSTRIA | G8: Ciência | H8: Múltiplas - especificar em K | I8: Armazenamento; Abastecimento; Grãos | J8: Capítulo apresenta um protocolo tecnológico-operacional para o armazenamento de trigo destinado à indústria, com orientações para reduzir perdas pós-colheita e preservar a qualidade dos grãos e seus derivados. | K8: Livro publicado | L8: 2 e 12 | M8: Brasília/DF | N8: Setor produtivo de grãos | O8: Conab/DF | P8: não | Q8: não se aplica | R8: Aderente a linha Inovação, Biotecnologia e Sustentabilidade Produtiva | S8: https://www.gov.br/conab/pt-br/acesso-a-informacao/institucional/publicacoes/outras-publicacoes/Perdas%20em%20transporte%20e%20armanenagem%20de%20graos/%40%40download/file | T8: https://www.gov.br/conab/pt-br/acesso-a-informacao/institucional/publicacoes/outras-publicacoes/Perdas%20em%20transporte%20e%20armanenagem%20de%20graos/%40%40download/file | U8: sim | V8: sim | W8: =IF($A8="","",IF(OR($C8="",$D8="",$E8="",$F8=""),"INCOMPLETO",IF(OR($D8<2021,$D8>2026),"ANO FORA DA JANELA",IF(OR(LOWER($U8)<>"sim",LOWER($V8)<>"sim",$G8="",$H8="",$J8="",$K8="",$M8="",$N8="",$Q8="",$R8="",$S8=""),"INCOMPLETO",IF(LEFT($C8,3)="PTT",IF(COUNTIF('Estratos e PTTs'!$B$15:$B$30,$E8)=0,"TIPO PTT INVÁLIDO","OK"),"OK"))))) -> OK
A9: Volnei Luiz Meneghetti | B9: =IF($A9="","",IFERROR(VLOOKUP($A9,'Resumo por docente'!$A$8:$B$57,2,FALSE),"")) -> Inovação, Biotecnologia e Sustentabilidade Produtiva | C9: Destaque 2 | D9: 2020 | E9: Relatório técnico conclusivo | F9: Diagnóstico de perdas qualitativas e quantitativas no armazenamento de trigo. | G9: Ciência | H9: Múltiplas - especificar em K | I9: Trigo; Armazenamento de grãos; Perdas pós-colheita. | J9: Diagnosticar as perdas qualitativas e quantitativas no armazenamento de trigo, identificando fatores que comprometem a conservação dos grãos e oportunidades para reduzir perdas pós-colheita. | K9: Relatório técnico conclusivo | L9: 12 | M9: Passo Fundo/RS | N9: Setor produtivo de grãos | O9: Embrapa Trigo | P9: não | Q9: não se aplica | R9: Aderente a linha Inovação, Biotecnologia e Sustentabilidade Produtiva | S9: https://www.infoteca.cnptia.embrapa.br/infoteca/bitstream/doc/1124354/1/DocOnline-186-Casiane-completo.pdf | T9: https://www.infoteca.cnptia.embrapa.br/infoteca/bitstream/doc/1124354/1/DocOnline-186-Casiane-completo.pdf | U9: sim | V9: sim | W9: =IF($A9="","",IF(OR($C9="",$D9="",$E9="",$F9=""),"INCOMPLETO",IF(OR($D9<2021,$D9>2026),"ANO FORA DA JANELA",IF(OR(LOWER($U9)<>"sim",LOWER($V9)<>"sim",$G9="",$H9="",$J9="",$K9="",$M9="",$N9="",$Q9="",$R9="",$S9=""),"INCOMPLETO",IF(LEFT($C9,3)="PTT",IF(COUNTIF('Estratos e PTTs'!$B$15:$B$30,$E9)=0,"TIPO PTT INVÁLIDO","OK"),"OK"))))) -> ANO FORA DA JANELA
A10: Kátia Maria Cardinal | B10: =IF($A10="","",IFERROR(VLOOKUP($A10,'Resumo por docente'!$A$8:$B$57,2,FALSE),"")) -> Inovação, Biotecnologia e Sustentabilidade Produtiva | C10: Destaque 1 | D10: 2025 | E10: Produto bibliográfico | F10: Global Impact of Antimicrobial Growth Promoters on Livestock Productivity: A Meta-Analysis for Economic Modeling | G10: Ciência e Sociedade | H10: Múltiplas - especificar em K | I10: Antimicrobianos; Meta-análise; Frangos, Suínos, Bovinos. | J10: Este estudo abordou, por meio de uma revisão sistemática e meta-análise, o impacto do uso de antimicrobianos promotores de crescimento em frangos de corte, suínos e bovinos em diferentes sistemas de produção. | K10: Artigo publicado que foi utilizado como base para o relatório da FAO sobre o uso de antimicrobioanos na produção animal. | L10: 12 e 15 | M10: Global | N10: Setor de produção animal. | O10: Food and Agriculture Organization of the United Nations (FAO) | P10: não | Q10: não se aplica | R10: Ãderente a linha Inovação, Biotecnologia e Sustentabilidade Produtiva | S10: https://doi.org/10.1016/j.prevetmed.2025.106754 | T10: https://doi.org/10.1016/j.prevetmed.2025.106754 | U10: sim | V10: sim | W10: =IF($A10="","",IF(OR($C10="",$D10="",$E10="",$F10=""),"INCOMPLETO",IF(OR($D10<2021,$D10>2026),"ANO FORA DA JANELA",IF(OR(LOWER($U10)<>"sim",LOWER($V10)<>"sim",$G10="",$H10="",$J10="",$K10="",$M10="",$N10="",$Q10="",$R10="",$S10=""),"INCOMPLETO",IF(LEFT($C10,3)="PTT",IF(COUNTIF('Estratos e PTTs'!$B$15:$B$30,$E10)=0,"TIPO PTT INVÁLIDO","OK"),"OK"))))) -> OK
A11: Kátia Maria Cardinal | B11: =IF($A11="","",IFERROR(VLOOKUP($A11,'Resumo por docente'!$A$8:$B$57,2,FALSE),"")) -> Inovação, Biotecnologia e Sustentabilidade Produtiva | C11: Destaque 2 | D11: 2026 | E11: Livro ou capítulo (somente destaque) | F11: The future of antimicrobial use in livestock | G11: Ciência e Sociedade | H11: Múltiplas - especificar em K | I11: Antimicrobianos; saúde única; produção animal. | J11: Fornecer projeções econômicas e de uso de antimicrobianos a longo prazo, servindo como uma ferramenta de tomada de decisão para governos, produtores e indústrias. Ele visa demonstrar que o custo da inação contra a resistência aos antimicrobianos na agropecuária é drasticamente maior do que o investimento necessário para adotar práticas sustentáveis. | K11: O relatório da FAO evidencia que a inação contra a resistência bacteriana gerará uma perda econômica de US$ 318 bilhões na pecuária global até 2040. Esse cenário força governos e produtores a investirem urgentemente em biossegurança e vacinação para conter o aumento no uso de antimicrobianos. Na prática, a eficácia de medicamentos vitais diminui, elevando a mortalidade de rebanhos e encarecendo a produção de alimentos. Como consequência direta, a saúde pública global é ameaçada pela disseminação de superbactérias pela cadeia alimentar, afetando a segurança alimentar mundial. | L11: 12 e 15 | M11: Global | N11: Governos, indústrias e setor agropecuário | O11: Food and Agriculture Organization of the United Nations (FAO) | P11: não | Q11: não se aplica | R11: Aderente a linha Inovação, Biotecnologia e Sustentabilidade Produtiva | S11: https://openknowledge.fao.org/handle/20.500.14283/cd9571en | T11: https://openknowledge.fao.org/handle/20.500.14283/cd9571en | U11: sim | V11: sim | W11: =IF($A11="","",IF(OR($C11="",$D11="",$E11="",$F11=""),"INCOMPLETO",IF(OR($D11<2021,$D11>2026),"ANO FORA DA JANELA",IF(OR(LOWER($U11)<>"sim",LOWER($V11)<>"sim",$G11="",$H11="",$J11="",$K11="",$M11="",$N11="",$Q11="",$R11="",$S11=""),"INCOMPLETO",IF(LEFT($C11,3)="PTT",IF(COUNTIF('Estratos e PTTs'!$B$15:$B$30,$E11)=0,"TIPO PTT INVÁLIDO","OK"),"OK"))))) -> OK
B12: =IF($A12="","",IFERROR(VLOOKUP($A12,'Resumo por docente'!$A$8:$B$57,2,FALSE),"")) | W12: =IF($A12="","",IF(OR($C12="",$D12="",$E12="",$F12=""),"INCOMPLETO",IF(OR($D12<2021,$D12>2026),"ANO FORA DA JANELA",IF(OR(LOWER($U12)<>"sim",LOWER($V12)<>"sim",$G12="",$H12="",$J12="",$K12="",$M12="",$N12="",$Q12="",$R12="",$S12=""),"INCOMPLETO",IF(LEFT($C12,3)="PTT",IF(COUNTIF('Estratos e PTTs'!$B$15:$B$30,$E12)=0,"TIPO PTT INVÁLIDO","OK"),"OK")))))
B13: =IF($A13="","",IFERROR(VLOOKUP($A13,'Resumo por docente'!$A$8:$B$57,2,FALSE),"")) | U13: sim | W13: =IF($A13="","",IF(OR($C13="",$D13="",$E13="",$F13=""),"INCOMPLETO",IF(OR($D13<2021,$D13>2026),"ANO FORA DA JANELA",IF(OR(LOWER($U13)<>"sim",LOWER($V13)<>"sim",$G13="",$H13="",$J13="",$K13="",$M13="",$N13="",$Q13="",$R13="",$S13=""),"INCOMPLETO",IF(LEFT($C13,3)="PTT",IF(COUNTIF('Estratos e PTTs'!$B$15:$B$30,$E13)=0,"TIPO PTT INVÁLIDO","OK"),"OK")))))
B14: =IF($A14="","",IFERROR(VLOOKUP($A14,'Resumo por docente'!$A$8:$B$57,2,FALSE),"")) | W14: =IF($A14="","",IF(OR($C14="",$D14="",$E14="",$F14=""),"INCOMPLETO",IF(OR($D14<2021,$D14>2026),"ANO FORA DA JANELA",IF(OR(LOWER($U14)<>"sim",LOWER($V14)<>"sim",$G14="",$H14="",$J14="",$K14="",$M14="",$N14="",$Q14="",$R14="",$S14=""),"INCOMPLETO",IF(LEFT($C14,3)="PTT",IF(COUNTIF('Estratos e PTTs'!$B$15:$B$30,$E14)=0,"TIPO PTT INVÁLIDO","OK"),"OK")))))
B15: =IF($A15="","",IFERROR(VLOOKUP($A15,'Resumo por docente'!$A$8:$B$57,2,FALSE),"")) | W15: =IF($A15="","",IF(OR($C15="",$D15="",$E15="",$F15=""),"INCOMPLETO",IF(OR($D15<2021,$D15>2026),"ANO FORA DA JANELA",IF(OR(LOWER($U15)<>"sim",LOWER($V15)<>"sim",$G15="",$H15="",$J15="",$K15="",$M15="",$N15="",$Q15="",$R15="",$S15=""),"INCOMPLETO",IF(LEFT($C15,3)="PTT",IF(COUNTIF('Estratos e PTTs'!$B$15:$B$30,$E15)=0,"TIPO PTT INVÁLIDO","OK"),"OK")))))
B16: =IF($A16="","",IFERROR(VLOOKUP($A16,'Resumo por docente'!$A$8:$B$57,2,FALSE),"")) | W16: =IF($A16="","",IF(OR($C16="",$D16="",$E16="",$F16=""),"INCOMPLETO",IF(OR($D16<2021,$D16>2026),"ANO FORA DA JANELA",IF(OR(LOWER($U16)<>"sim",LOWER($V16)<>"sim",$G16="",$H16="",$J16="",$K16="",$M16="",$N16="",$Q16="",$R16="",$S16=""),"INCOMPLETO",IF(LEFT($C16,3)="PTT",IF(COUNTIF('Estratos e PTTs'!$B$15:$B$30,$E16)=0,"TIPO PTT INVÁLIDO","OK"),"OK")))))
B17: =IF($A17="","",IFERROR(VLOOKUP($A17,'Resumo por docente'!$A$8:$B$57,2,FALSE),"")) | W17: =IF($A17="","",IF(OR($C17="",$D17="",$E17="",$F17=""),"INCOMPLETO",IF(OR($D17<2021,$D17>2026),"ANO FORA DA JANELA",IF(OR(LOWER($U17)<>"sim",LOWER($V17)<>"sim",$G17="",$H17="",$J17="",$K17="",$M17="",$N17="",$Q17="",$R17="",$S17=""),"INCOMPLETO",IF(LEFT($C17,3)="PTT",IF(COUNTIF('Estratos e PTTs'!$B$15:$B$30,$E17)=0,"TIPO PTT INVÁLIDO","OK"),"OK")))))
B18: =IF($A18="","",IFERROR(VLOOKUP($A18,'Resumo por docente'!$A$8:$B$57,2,FALSE),"")) | W18: =IF($A18="","",IF(OR($C18="",$D18="",$E18="",$F18=""),"INCOMPLETO",IF(OR($D18<2021,$D18>2026),"ANO FORA DA JANELA",IF(OR(LOWER($U18)<>"sim",LOWER($V18)<>"sim",$G18="",$H18="",$J18="",$K18="",$M18="",$N18="",$Q18="",$R18="",$S18=""),"INCOMPLETO",IF(LEFT($C18,3)="PTT",IF(COUNTIF('Estratos e PTTs'!$B$15:$B$30,$E18)=0,"TIPO PTT INVÁLIDO","OK"),"OK")))))
B19: =IF($A19="","",IFERROR(VLOOKUP($A19,'Resumo por docente'!$A$8:$B$57,2,FALSE),"")) | W19: =IF($A19="","",IF(OR($C19="",$D19="",$E19="",$F19=""),"INCOMPLETO",IF(OR($D19<2021,$D19>2026),"ANO FORA DA JANELA",IF(OR(LOWER($U19)<>"sim",LOWER($V19)<>"sim",$G19="",$H19="",$J19="",$K19="",$M19="",$N19="",$Q19="",$R19="",$S19=""),"INCOMPLETO",IF(LEFT($C19,3)="PTT",IF(COUNTIF('Estratos e PTTs'!$B$15:$B$30,$E19)=0,"TIPO PTT INVÁLIDO","OK"),"OK")))))
B20: =IF($A20="","",IFERROR(VLOOKUP($A20,'Resumo por docente'!$A$8:$B$57,2,FALSE),"")) | W20: =IF($A20="","",IF(OR($C20="",$D20="",$E20="",$F20=""),"INCOMPLETO",IF(OR($D20<2021,$D20>2026),"ANO FORA DA JANELA",IF(OR(LOWER($U20)<>"sim",LOWER($V20)<>"sim",$G20="",$H20="",$J20="",$K20="",$M20="",$N20="",$Q20="",$R20="",$S20=""),"INCOMPLETO",IF(LEFT($C20,3)="PTT",IF(COUNTIF('Estratos e PTTs'!$B$15:$B$30,$E20)=0,"TIPO PTT INVÁLIDO","OK"),"OK")))))
B21: =IF($A21="","",IFERROR(VLOOKUP($A21,'Resumo por docente'!$A$8:$B$57,2,FALSE),"")) | W21: =IF($A21="","",IF(OR($C21="",$D21="",$E21="",$F21=""),"INCOMPLETO",IF(OR($D21<2021,$D21>2026),"ANO FORA DA JANELA",IF(OR(LOWER($U21)<>"sim",LOWER($V21)<>"sim",$G21="",$H21="",$J21="",$K21="",$M21="",$N21="",$Q21="",$R21="",$S21=""),"INCOMPLETO",IF(LEFT($C21,3)="PTT",IF(COUNTIF('Estratos e PTTs'!$B$15:$B$30,$E21)=0,"TIPO PTT INVÁLIDO","OK"),"OK")))))
B22: =IF($A22="","",IFERROR(VLOOKUP($A22,'Resumo por docente'!$A$8:$B$57,2,FALSE),"")) | W22: =IF($A22="","",IF(OR($C22="",$D22="",$E22="",$F22=""),"INCOMPLETO",IF(OR($D22<2021,$D22>2026),"ANO FORA DA JANELA",IF(OR(LOWER($U22)<>"sim",LOWER($V22)<>"sim",$G22="",$H22="",$J22="",$K22="",$M22="",$N22="",$Q22="",$R22="",$S22=""),"INCOMPLETO",IF(LEFT($C22,3)="PTT",IF(COUNTIF('Estratos e PTTs'!$B$15:$B$30,$E22)=0,"TIPO PTT INVÁLIDO","OK"),"OK")))))
B23: =IF($A23="","",IFERROR(VLOOKUP($A23,'Resumo por docente'!$A$8:$B$57,2,FALSE),"")) | W23: =IF($A23="","",IF(OR($C23="",$D23="",$E23="",$F23=""),"INCOMPLETO",IF(OR($D23<2021,$D23>2026),"ANO FORA DA JANELA",IF(OR(LOWER($U23)<>"sim",LOWER($V23)<>"sim",$G23="",$H23="",$J23="",$K23="",$M23="",$N23="",$Q23="",$R23="",$S23=""),"INCOMPLETO",IF(LEFT($C23,3)="PTT",IF(COUNTIF('Estratos e PTTs'!$B$15:$B$30,$E23)=0,"TIPO PTT INVÁLIDO","OK"),"OK")))))
B24: =IF($A24="","",IFERROR(VLOOKUP($A24,'Resumo por docente'!$A$8:$B$57,2,FALSE),"")) | W24: =IF($A24="","",IF(OR($C24="",$D24="",$E24="",$F24=""),"INCOMPLETO",IF(OR($D24<2021,$D24>2026),"ANO FORA DA JANELA",IF(OR(LOWER($U24)<>"sim",LOWER($V24)<>"sim",$G24="",$H24="",$J24="",$K24="",$M24="",$N24="",$Q24="",$R24="",$S24=""),"INCOMPLETO",IF(LEFT($C24,3)="PTT",IF(COUNTIF('Estratos e PTTs'!$B$15:$B$30,$E24)=0,"TIPO PTT INVÁLIDO","OK"),"OK")))))
B25: =IF($A25="","",IFERROR(VLOOKUP($A25,'Resumo por docente'!$A$8:$B$57,2,FALSE),"")) | W25: =IF($A25="","",IF(OR($C25="",$D25="",$E25="",$F25=""),"INCOMPLETO",IF(OR($D25<2021,$D25>2026),"ANO FORA DA JANELA",IF(OR(LOWER($U25)<>"sim",LOWER($V25)<>"sim",$G25="",$H25="",$J25="",$K25="",$M25="",$N25="",$Q25="",$R25="",$S25=""),"INCOMPLETO",IF(LEFT($C25,3)="PTT",IF(COUNTIF('Estratos e PTTs'!$B$15:$B$30,$E25)=0,"TIPO PTT INVÁLIDO","OK"),"OK")))))
... B501: =IF($A501="","",IFERROR(VLOOKUP($A501,'Resumo por docente'!$A$8:$B$57,2,FALSE),"")) | W501: =IF($A501="","",IF(OR($C501="",$D501="",$E501="",$F501=""),"INCOMPLETO",IF(OR($D501<2021,$D501>2026),"ANO FORA DA JANELA",IF(OR(LOWER($U501)<>"sim",LOWER($V501)<>"sim",$G501="",$H501="",$J501="",$K501="",$M501="",$N501="",$Q501="",$R501="",$S501=""),"INCOMPLETO",IF(LEFT($C501,3)="PTT",IF(COUNTIF('Estratos e PTTs'!$B$15:$B$30,$E501)=0,"TIPO PTT INVÁLIDO","OK"),"OK")))))
